Workbook

Sheet Sheet1
A1: CATEGORIA_NETSUITE | B1: Concepto | C1: IS | D1: ÁREA | E1: ZONA PPTO | F1: EMPLEADO | G1: MONTO | H1: PERIODO | I1: AREA | J1: ZONA | K1: PCT_POND | L1: Fecha | M1: Tipo | N1: Número | O1: Clasf Efs | P1: ID SGN | Q1: PUESTO | R1: PAGADORA
A2: Sueldos y salarios | B2: ACEVEDO LOPEZ GERMAIN | C2: COGS | D2: OPERACIONES | E2: CENTRO | F2: GERMAIN ACEVEDO LOPEZ | G2: 12269.305 | H2: ENERO
A3: Sueldos y salarios | B3: ACEVEDO LOPEZ GERMAIN | C3: COGS | D3: OPERACIONES | E3: CENTRO | F3: GERMAIN ACEVEDO LOPEZ | G3: 12620.03 | H3: MARZO
A4: Sueldos y salarios | B4: ACEVEDO LOPEZ GERMAIN | C4: COGS | D4: OPERACIONES | E4: CENTRO | F4: GERMAIN ACEVEDO LOPEZ | G4: 10861.391 | H4: FEBRERO
A5: Sueldos y salarios | B5: ACEVEDO LOPEZ GERMAIN | C5: COGS | D5: OPERACIONES | E5: CENTRO | F5: GERMAIN ACEVEDO LOPEZ | G5: 10842.303 | H5: ABRIL
A6: Sueldos y salarios | B6: AGUILAR MORALES EMANUEL | C6: COGS | D6: OPERACIONES | E6: CENTRO | F6: EMANUEL AGUILAR MORALES | G6: 24075.35 | H6: MARZO
A7: Sueldos y salarios | B7: AGUILAR MORALES EMANUEL | C7: COGS | D7: OPERACIONES | E7: CENTRO | F7: EMANUEL AGUILAR MORALES | G7: 14312.507 | H7: FEBRERO
A8: Sueldos y salarios | B8: ALCANTARA SEGURA MIRIAM JOSEFINA | C8: GASTOS DE ADMINISTRACIÓN | D8: TÉCNICO | F8: MIRIAM JOSEFINA ALCANTARA SEGURA | G8: 14378.848 | H8: ENERO
A9: Sueldos y salarios | B9: ALCANTARA SEGURA MIRIAM JOSEFINA | C9: GASTOS DE ADMINISTRACIÓN | D9: TÉCNICO | F9: MIRIAM JOSEFINA ALCANTARA SEGURA | G9: 15993.283 | H9: MARZO
A10: Sueldos y salarios | B10: ALCANTARA SEGURA MIRIAM JOSEFINA | C10: GASTOS DE ADMINISTRACIÓN | D10: TÉCNICO | F10: MIRIAM JOSEFINA ALCANTARA SEGURA | G10: 15770.154 | H10: FEBRERO
A11: Sueldos y salarios | B11: ALMADA NOZATO DANNA PAOLA | C11: COGS | D11: OPERACIONES | E11: SURESTE | F11: DANNA PAOLA ALMADA NOZATO | G11: 13779.069 | H11: MARZO
A12: Sueldos y salarios | B12: ALMADA NOZATO DANNA PAOLA | C12: COGS | D12: OPERACIONES | E12: SURESTE | F12: DANNA PAOLA ALMADA NOZATO | G12: 13493.097 | H12: FEBRERO
A13: Sueldos y salarios | B13: ALMADA NOZATO DANNA PAOLA | C13: COGS | D13: OPERACIONES | E13: SURESTE | F13: DANNA PAOLA ALMADA NOZATO | G13: 13751.394 | H13: ENERO
A14: Sueldos y salarios | B14: ALMANZA GUZMAN FREDDY JESUS | C14: GASTOS DE ADMINISTRACIÓN | D14: BRAND BUILDING | F14: FREDDY JESUS ALMANZA GUZMAN | G14: 19234.553 | H14: ENERO
A15: Sueldos y salarios | B15: ALMANZA GUZMAN FREDDY JESUS | C15: GASTOS DE ADMINISTRACIÓN | D15: BRAND BUILDING | F15: FREDDY JESUS ALMANZA GUZMAN | G15: 23356.679 | H15: MARZO
A16: Sueldos y salarios | B16: ALMANZA GUZMAN FREDDY JESUS | C16: GASTOS DE ADMINISTRACIÓN | D16: BRAND BUILDING | F16: FREDDY JESUS ALMANZA GUZMAN | G16: 18896.204 | H16: FEBRERO
A17: Sueldos y salarios | B17: ALTAMIRANO DIAZ CIELO ANEL | C17: COGS | D17: OPERACIONES | E17: NOROESTE | F17: CIELO ANEL ALTAMIRANO DIAZ | G17: 11487.986 | H17: MARZO
A18: Sueldos y salarios | B18: ALTAMIRANO DIAZ CIELO ANEL | C18: COGS | D18: OPERACIONES | E18: NOROESTE | F18: CIELO ANEL ALTAMIRANO DIAZ | G18: 17785.736 | H18: FEBRERO
A19: Sueldos y salarios | B19: ALTAMIRANO DIAZ CIELO ANEL | C19: COGS | D19: OPERACIONES | E19: NOROESTE | F19: CIELO ANEL ALTAMIRANO DIAZ | G19: 18125.363 | H19: ENERO
A20: Sueldos y salarios | B20: ALVAREZ CABRERA RODRIGO | C20: COGS | D20: OPERACIONES | E20: OCCIDENTE | F20: RODRIGO ALVAREZ CABRERA | G20: 19431.204 | H20: FEBRERO
A21: Sueldos y salarios | B21: ALVAREZ CABRERA RODRIGO | C21: COGS | D21: OPERACIONES | E21: OCCIDENTE | F21: RODRIGO ALVAREZ CABRERA | G21: 19779.553 | H21: ENERO
A22: Sueldos y salarios | B22: ALVAREZ CABRERA RODRIGO | C22: COGS | D22: OPERACIONES | E22: OCCIDENTE | F22: RODRIGO ALVAREZ CABRERA | G22: 15802.44 | H22: MARZO
A23: Sueldos y salarios | B23: ALVAREZ CABRERA RODRIGO | C23: COGS | D23: OPERACIONES | E23: OCCIDENTE | F23: RODRIGO ALVAREZ CABRERA | G23: 10060.44 | H23: ABRIL
A24: Sueldos y salarios | B24: ALVAREZ CHAVEZ VICTOR MANUEL | C24: GASTOS DE ADMINISTRACIÓN | D24: COMERCIAL | F24: VICTOR MANUEL ALVAREZ CHAVEZ | G24: 18848.226 | H24: FEBRERO
A25: Sueldos y salarios | B25: ALVAREZ CHAVEZ VICTOR MANUEL | C25: GASTOS DE ADMINISTRACIÓN | D25: COMERCIAL | F25: VICTOR MANUEL ALVAREZ CHAVEZ | G25: 19080.558 | H25: MARZO
A26: Sueldos y salarios | B26: ALVAREZ CHAVEZ VICTOR MANUEL | C26: GASTOS DE ADMINISTRACIÓN | D26: COMERCIAL | F26: VICTOR MANUEL ALVAREZ CHAVEZ | G26: 19207.063 | H26: ENERO
A27: Sueldos y salarios | B27: AREVALO CERVANTES MIGUEL ANGEL | C27: GASTOS DE ADMINISTRACIÓN | D27: BRAND BUILDING | F27: MIGUEL ANGEL AREVALO CERVANTES | G27: 20193.283 | H27: MARZO
A28: Sueldos y salarios | B28: AREVALO CERVANTES MIGUEL ANGEL | C28: GASTOS DE ADMINISTRACIÓN | D28: BRAND BUILDING | F28: MIGUEL ANGEL AREVALO CERVANTES | G28: 20050.154 | H28: FEBRERO
A29: Sueldos y salarios | B29: AREVALO CERVANTES MIGUEL ANGEL | C29: GASTOS DE ADMINISTRACIÓN | D29: BRAND BUILDING | F29: MIGUEL ANGEL AREVALO CERVANTES | G29: 20427.175 | H29: ENERO
A30: Sueldos y salarios | B30: ARRAZOLA SANTAELLA ALBERTO NICOLAS | C30: COGS | D30: OPERACIONES | E30: SURESTE | F30: ALBERTO NICOLAS ARRAZOLA SANTAELLA | G30: 8107.3609 | H30: FEBRERO
A31: Sueldos y salarios | B31: ARRAZOLA SANTAELLA ALBERTO NICOLAS | C31: COGS | D31: OPERACIONES | E31: SURESTE | F31: ALBERTO NICOLAS ARRAZOLA SANTAELLA | G31: 20303.011 | H31: MARZO
A32: Sueldos y salarios | B32: ARRAZOLA SANTAELLA ALBERTO NICOLAS | C32: COGS | D32: OPERACIONES | E32: SURESTE | F32: ALBERTO NICOLAS ARRAZOLA SANTAELLA | G32: 18427.44 | H32: ABRIL
A33: Sueldos y salarios | B33: ARREOLA ALATRISTE ALEXANDRA ESTEPHANIA | C33: COGS | D33: TÉCNICO | F33: ALEXANDRA ESTEPHANIA ARREOLA ALATRISTE | G33: 13202.829 | H33: MARZO
A34: Sueldos y salarios | B34: ARREOLA ALATRISTE ALEXANDRA ESTEPHANIA | C34: COGS | D34: TÉCNICO | F34: ALEXANDRA ESTEPHANIA ARREOLA ALATRISTE | G34: 10059.743 | H34: FEBRERO
A35: Sueldos y salarios | B35: ARREOLA ALATRISTE ALEXANDRA ESTEPHANIA | C35: COGS | D35: TÉCNICO | F35: ALEXANDRA ESTEPHANIA ARREOLA ALATRISTE | G35: 7350 | H35: ENERO
A36: Sueldos y salarios | B36: ARVIZU ESTRADA ALBA MARIANA | C36: COGS | D36: OPERACIONES | E36: CENTRO | F36: ALBA MARIANA ARVIZU ESTRADA | G36: 15770.03 | H36: MARZO
A37: Sueldos y salarios | B37: ARVIZU ESTRADA ALBA MARIANA | C37: COGS | D37: OPERACIONES | E37: CENTRO | F37: ALBA MARIANA ARVIZU ESTRADA | G37: 14071.391 | H37: FEBRERO
A38: Sueldos y salarios | B38: ARVIZU ESTRADA ALBA MARIANA | C38: COGS | D38: OPERACIONES | E38: CENTRO | F38: ALBA MARIANA ARVIZU ESTRADA | G38: 3209.1708 | H38: ENERO
A39: Sueldos y salarios | B39: ARVIZU ESTRADA ALBA MARIANA | C39: COGS | D39: OPERACIONES | E39: CENTRO | F39: ALBA MARIANA ARVIZU ESTRADA | G39: 15277.44 | H39: ABRIL
A40: Sueldos y salarios | B40: BACA AGUIRRE ANTONIO | C40: COGS | D40: OPERACIONES | E40: NOROESTE | F40: ANTONIO BACA AGUIRRE | G40: 17823.58 | H40: FEBRERO
A41: Sueldos y salarios | B41: BACA AGUIRRE ANTONIO | C41: COGS | D41: OPERACIONES | E41: NOROESTE | F41: ANTONIO BACA AGUIRRE | G41: 18141.678 | H41: ENERO
A42: Sueldos y salarios | B42: BACA AGUIRRE ANTONIO | C42: COGS | D42: OPERACIONES | E42: NOROESTE | F42: ANTONIO BACA AGUIRRE | G42: 10866.02 | H42: MARZO
A43: Sueldos y salarios | B43: BACA AGUIRRE ANTONIO | C43: COGS | D43: OPERACIONES | E43: NOROESTE | F43: ANTONIO BACA AGUIRRE | G43: 7247.5095 | H43: ABRIL
A44: Sueldos y salarios | B44: BALTAZAR RODRIGUEZ SERGIO ALBERTO | C44: COGS | D44: OPERACIONES | E44: NORTE | F44: SERGIO ALBERTO BALTAZAR RODRIGUEZ | G44: 16006.679 | H44: MARZO
A45: Sueldos y salarios | B45: BALTAZAR RODRIGUEZ SERGIO ALBERTO | C45: COGS | D45: OPERACIONES | E45: NORTE | F45: SERGIO ALBERTO BALTAZAR RODRIGUEZ | G45: 15686.204 | H45: FEBRERO
A46: Sueldos y salarios | B46: BALTAZAR RODRIGUEZ SERGIO ALBERTO | C46: COGS | D46: OPERACIONES | E46: NORTE | F46: SERGIO ALBERTO BALTAZAR RODRIGUEZ | G46: 15964.553 | H46: ENERO
A47: Sueldos y salarios | B47: BERNAL MONROY MARIA DEL PILAR JAZMINE | C47: COGS | D47: OPERACIONES | E47: CENTRO | F47: MARIA DEL PILAR JAZMINE BERNAL MONROY | G47: 14885.847 | H47: ENERO
... A49: Sueldos y salarios | B49: BERNAL MONROY MARIA DEL PILAR JAZMINE | C49: COGS | D49: OPERACIONES | E49: CENTRO | F49: MARIA DEL PILAR JAZMINE BERNAL MONROY | G49: 16766.512 | H49: FEBRERO
A50: Sueldos y salarios | B50: FRANCISCO JAVIER BERRUETA GUTIERREZ | C50: OTROS Facturación / GASTOS | D50: SOCIOS | F50: FRANCISCO JAVIER BERRUETA GUTIERREZ | G50: =11977.36+(131250*2) -> 274477.36 | H50: ENERO
A51: Sueldos y salarios | B51: FRANCISCO JAVIER BERRUETA GUTIERREZ | C51: OTROS Facturación / GASTOS | D51: SOCIOS | F51: FRANCISCO JAVIER BERRUETA GUTIERREZ | G51: =11977.36+(131250*2) -> 274477.36 | H51: FEBRERO
A52: Sueldos y salarios | B52: FRANCISCO JAVIER BERRUETA GUTIERREZ | C52: OTROS Facturación / GASTOS | D52: SOCIOS | F52: FRANCISCO JAVIER BERRUETA GUTIERREZ | G52: =11977.36+(131250*2) -> 274477.36 | H52: MARZO
A53: Sueldos y salarios | B53: FRANCISCO JAVIER BERRUETA GUTIERREZ | C53: OTROS Facturación / GASTOS | D53: SOCIOS | F53: FRANCISCO JAVIER BERRUETA GUTIERREZ | G53: =11977.36+(131250*2) -> 274477.36 | H53: ABRIL
A54: Sueldos y salarios | B54: JOSE DE JESUS RAMIREZ GONZALEZ | C54: COGS | D54: OPERACIONES | E54: CENTRO | F54: JOSE DE JESUS RAMIREZ GONZALEZ | G54: 20127.76 | H54: ENERO
A55: Sueldos y salarios | B55: SUSANA RUTH GARCIA MARTINEZ | C55: OTROS Facturación / GASTOS | D55: LAE | F55: SUSANA RUTH GARCIA MARTINEZ | G55: 12999.9 | H55: ENERO
A56: Sueldos y salarios | B56: SUSANA RUTH GARCIA MARTINEZ | C56: OTROS Facturación / GASTOS | D56: LAE | F56: SUSANA RUTH GARCIA MARTINEZ | G56: 12999.9 | H56: FEBRERO
A57: Sueldos y salarios | B57: SUSANA RUTH GARCIA MARTINEZ | C57: OTROS Facturación / GASTOS | D57: LAE | F57: SUSANA RUTH GARCIA MARTINEZ | G57: 12999.9 | H57: MARZO
A58: Sueldos y salarios | B58: SUSANA RUTH GARCIA MARTINEZ | C58: OTROS Facturación / GASTOS | D58: LAE | F58: SUSANA RUTH GARCIA MARTINEZ | G58: 12999.9 | H58: ABRIL
A59: Sueldos y salarios | B59: DIEGO GUERRA GUTIERREZ | C59: OTROS Facturación / GASTOS | D59: LAE | F59: DIEGO GUERRA GUTIERREZ | G59: 12999.9 | H59: ENERO
A60: Sueldos y salarios | B60: DIEGO GUERRA GUTIERREZ | C60: OTROS Facturación / GASTOS | D60: LAE | F60: DIEGO GUERRA GUTIERREZ | G60: 12999.9 | H60: FEBRERO
A61: Sueldos y salarios | B61: DIEGO GUERRA GUTIERREZ | C61: OTROS Facturación / GASTOS | D61: LAE | F61: DIEGO GUERRA GUTIERREZ | G61: 12999.9 | H61: MARZO
A62: Sueldos y salarios | B62: DIEGO GUERRA GUTIERREZ | C62: OTROS Facturación / GASTOS | D62: LAE | F62: DIEGO GUERRA GUTIERREZ | G62: 12999.9 | H62: ABRIL
A63: Sueldos y salarios | B63: JOSE CARLOS SAENZ FERNANDEZ | C63: GASTOS DE ADMINISTRACIÓN | D63: COMERCIAL | F63: JOSE CARLOS SAENZ FERNANDEZ | G63: 16219.1 | H63: ENERO
A64: Sueldos y salarios | B64: JOSE CARLOS SAENZ FERNANDEZ | C64: GASTOS DE ADMINISTRACIÓN | D64: COMERCIAL | F64: JOSE CARLOS SAENZ FERNANDEZ | G64: 22000.14 | H64: FEBRERO
A65: Sueldos y salarios | B65: JOSE CARLOS SAENZ FERNANDEZ | C65: GASTOS DE ADMINISTRACIÓN | D65: COMERCIAL | F65: JOSE CARLOS SAENZ FERNANDEZ | G65: 22000.14 | H65: MARZO
A66: Sueldos y salarios | B66: JOSE CARLOS SAENZ FERNANDEZ | C66: GASTOS DE ADMINISTRACIÓN | D66: COMERCIAL | F66: JOSE CARLOS SAENZ FERNANDEZ | G66: 22000.14 | H66: ABRIL
A67: Sueldos y salarios | B67: NADIA YURIT ARAUJO ISLAS | C67: COGS | D67: OPERACIONES | E67: CENTRO | F67: NADIA YURIT ARAUJO ISLAS | G67: 5192.95 | H67: ENERO
A68: Sueldos y salarios | B68: NADIA YURIT ARAUJO ISLAS | C68: COGS | D68: OPERACIONES | E68: CENTRO | F68: NADIA YURIT ARAUJO ISLAS | G68: 12182.49 | H68: FEBRERO
A69: Sueldos y salarios | B69: NADIA YURIT ARAUJO ISLAS | C69: COGS | D69: OPERACIONES | E69: CENTRO | F69: NADIA YURIT ARAUJO ISLAS | G69: 13977.58 | H69: MARZO
A70: Sueldos y salarios | B70: NADIA YURIT ARAUJO ISLAS | C70: COGS | D70: OPERACIONES | E70: CENTRO | F70: NADIA YURIT ARAUJO ISLAS | G70: 13977.58 | H70: ABRIL
A71: Sueldos y salarios | B71: BERRUETA GONZALEZ FRANCISCO JAVIER | C71: GASTOS DE ADMINISTRACIÓN | D71: PENDIENTE | F71: FRANCISCO JAVIER BERRUETA GONZALEZ | G71: 30450 | H71: ENERO
A72: Sueldos y salarios | B72: BERRUETA GONZALEZ FRANCISCO JAVIER | C72: GASTOS DE ADMINISTRACIÓN | D72: PENDIENTE | F72: FRANCISCO JAVIER BERRUETA GONZALEZ | G72: 30450 | H72: MARZO
A73: Sueldos y salarios | B73: BERRUETA GONZALEZ FRANCISCO JAVIER | C73: GASTOS DE ADMINISTRACIÓN | D73: PENDIENTE | F73: FRANCISCO JAVIER BERRUETA GONZALEZ | G73: 30450 | H73: FEBRERO
A74: Sueldos y salarios | B74: BERRUETA GUTIERREZ SOFIA | C74: GASTOS DE ADMINISTRACIÓN | D74: TÉCNICO | F74: SOFIA BERRUETA GUTIERREZ | G74: 23583.237 | H74: MARZO
A75: Sueldos y salarios | B75: BERRUETA GUTIERREZ SOFIA | C75: GASTOS DE ADMINISTRACIÓN | D75: TÉCNICO | F75: SOFIA BERRUETA GUTIERREZ | G75: 13045.633 | H75: FEBRERO
A76: Sueldos y salarios | B76: BERRUETA GUTIERREZ SOFIA | C76: GASTOS DE ADMINISTRACIÓN | D76: TÉCNICO | F76: SOFIA BERRUETA GUTIERREZ | G76: 13291.944 | H76: ENERO
A77: Sueldos y salarios | B77: BOCANEGRA MARTINEZ ELEAZAR | C77: COGS | D77: TÉCNICO | F77: ELEAZAR BOCANEGRA MARTINEZ | G77: 16300.949 | H77: FEBRERO
A78: Sueldos y salarios | B78: BOCANEGRA MARTINEZ ELEAZAR | C78: COGS | D78: TÉCNICO | F78: ELEAZAR BOCANEGRA MARTINEZ | G78: 16669.546 | H78: ENERO
A79: Sueldos y salarios | B79: BOCANEGRA MARTINEZ ELEAZAR | C79: COGS | D79: TÉCNICO | F79: ELEAZAR BOCANEGRA MARTINEZ | G79: 16518.123 | H79: MARZO
A80: Sueldos y salarios | B80: BRAVO ZAPIAIN NATALIA | C80: GASTOS DE ADMINISTRACIÓN | D80: COMERCIAL | F80: NATALIA BRAVO ZAPIAIN | G80: 18843.097 | H80: FEBRERO
A81: Sueldos y salarios | B81: BRAVO ZAPIAIN NATALIA | C81: GASTOS DE ADMINISTRACIÓN | D81: COMERCIAL | F81: NATALIA BRAVO ZAPIAIN | G81: 15931.394 | H81: ENERO
A82: Sueldos y salarios | B82: BRAVO ZAPIAIN NATALIA | C82: GASTOS DE ADMINISTRACIÓN | D82: COMERCIAL | F82: NATALIA BRAVO ZAPIAIN | G82: 19074.755 | H82: MARZO
... A85: Sueldos y salarios | B85: CABRERA TERAN ARTURO | C85: GASTOS DE ADMINISTRACIÓN | D85: BRAND BUILDING | F85: ARTURO CABRERA TERAN | G85: 14418.283 | H85: MARZO
A86: Sueldos y salarios | B86: CAMACHO MONCADA MARIA JOSE | C86: COGS | D86: OPERACIONES | E86: OCCIDENTE | F86: MARIA JOSE CAMACHO MONCADA | G86: 15633.097 | H86: FEBRERO
A87: Sueldos y salarios | B87: CAMACHO MONCADA MARIA JOSE | C87: COGS | D87: OPERACIONES | E87: OCCIDENTE | F87: MARIA JOSE CAMACHO MONCADA | G87: 3181.7528 | H87: ENERO
A88: Sueldos y salarios | B88: CAMACHO MONCADA MARIA JOSE | C88: COGS | D88: OPERACIONES | E88: OCCIDENTE | F88: MARIA JOSE CAMACHO MONCADA | G88: 15924.755 | H88: MARZO
A89: Sueldos y salarios | B89: CAMACHO NUÑO IVAN ANGEL | C89: COGS | D89: OPERACIONES | E89: OCCIDENTE | F89: IVAN ANGEL CAMACHO NUÑO | G89: 17051.678 | H89: ENERO
A90: Sueldos y salarios | B90: CAMACHO NUÑO IVAN ANGEL | C90: COGS | D90: OPERACIONES | E90: OCCIDENTE | F90: IVAN ANGEL CAMACHO NUÑO | G90: 8493.071 | H90: FEBRERO
A91: Sueldos y salarios | B91: CATARINO TENORIO GRISELDA | C91: COGS | D91: OPERACIONES | E91: OCCIDENTE | F91: GRISELDA CATARINO TENORIO | G91: 14652.097 | H91: FEBRERO
A92: Sueldos y salarios | B92: CATARINO TENORIO GRISELDA | C92: COGS | D92: OPERACIONES | E92: OCCIDENTE | F92: GRISELDA CATARINO TENORIO | G92: 13969.394 | H92: ENERO
A93: Sueldos y salarios | B93: CATARINO TENORIO GRISELDA | C93: COGS | D93: OPERACIONES | E93: OCCIDENTE | F93: GRISELDA CATARINO TENORIO | G93: 15924.755 | H93: MARZO
A94: Sueldos y salarios | B94: CERVANTES AGUILAR JENNIFER MICHELLE | C94: OTROS Facturación / GASTOS | D94: TÉCNICO | F94: JENNIFER MICHELLE CERVANTES AGUILAR | G94: 17571.832 | H94: MARZO
A95: Sueldos y salarios | B95: CERVANTES AGUILAR JENNIFER MICHELLE | C95: OTROS Facturación / GASTOS | D95: TÉCNICO | F95: JENNIFER MICHELLE CERVANTES AGUILAR | G95: 17355.964 | H95: FEBRERO
A96: Sueldos y salarios | B96: CERVANTES AGUILAR JENNIFER MICHELLE | C96: OTROS Facturación / GASTOS | D96: TÉCNICO | F96: JENNIFER MICHELLE CERVANTES AGUILAR | G96: 17763.365 | H96: ENERO
A97: Sueldos y salarios | B97: CORNEJO JIMENEZ MARLEN (MULTIZONA) | C97: COGS | D97: OPERACIONES | E97: NOROESTE | F97: MARLEN CORNEJO JIMENEZ | G97: =26433.84557/3 -> 8811.2819 | H97: MARZO
A98: Sueldos y salarios | B98: CORNEJO JIMENEZ MARLEN (MULTIZONA) | C98: COGS | D98: OPERACIONES | E98: SURESTE | F98: MARLEN CORNEJO JIMENEZ | G98: =26433.84557/3 -> 8811.2819 | H98: MARZO
A99: Sueldos y salarios | B99: CORNEJO JIMENEZ MARLEN (MULTIZONA) | C99: COGS | D99: OPERACIONES | E99: OCCIDENTE | F99: MARLEN CORNEJO JIMENEZ | G99: =26433.84557/3 -> 8811.2819 | H99: MARZO
A100: Sueldos y salarios | B100: CORNEJO JIMENEZ MARLEN (MULTIZONA) | C100: COGS | D100: OPERACIONES | E100: NOROESTE | F100: MARLEN CORNEJO JIMENEZ | G100: =18888.877198/3 -> 6296.2924 | H100: FEBRERO
A101: Sueldos y salarios | B101: CORNEJO JIMENEZ MARLEN (MULTIZONA) | C101: COGS | D101: OPERACIONES | E101: SURESTE | F101: MARLEN CORNEJO JIMENEZ | G101: =18888.877198/3 -> 6296.2924 | H101: FEBRERO
A102: Sueldos y salarios | B102: CORNEJO JIMENEZ MARLEN (MULTIZONA) | C102: COGS | D102: OPERACIONES | E102: OCCIDENTE | F102: MARLEN CORNEJO JIMENEZ | G102: =18888.877198/3 -> 6296.2924 | H102: FEBRERO
A103: Sueldos y salarios | B103: CORNEJO JIMENEZ MARLEN (MULTIZONA) | C103: COGS | D103: OPERACIONES | E103: NOROESTE | F103: MARLEN CORNEJO JIMENEZ | G103: =20299.69469/3 -> 6766.5649 | H103: ENERO
...

Sheet 2025
A1: CATEGORIA_NETSUITE | B1: Concepto | C1: IS | D1: ÁREA | E1: ZONA PPTO | F1: EMPLEADO | G1: MONTO | H1: PERIODO | I1: NOTAS
A2: Viaticos y gastos de viaje | B2: COMPRA ORDEN DE PAGO SPEI 020125 =REFERENCIA CTA/CLABE: 002180650607646915, BXI SPEI BCO:002 BENEF:UBR PAGOS MEXICO SA DE CV (DATO NO VERIFICADO POR ESTA INSTITUCIÓN), Pago factura FFY 4293285 CVE RASTREO: 7875APR2202501023678059828 RFC: No capturado IVA: 000000000000.00 BANAMEX HORA LIQ: 10:51:50 | G2: $102,507.13 | H2: 45658 | I2: UBER
A3: Comisiones bancarias | B3: COMISION ORDEN DE PAGO SPEI REFERENCIA: 020125 | G3: $5.00 | H3: 45658 | I3: COMISIONES BANCARIAS
A4: Comisiones bancarias | B4: I.V.A. ORDEN DE PAGO SPEI REFERENCIA: 020125 | G4: $0.80 | H4: 45658 | I4: COMISIONES BANCARIAS
A5: Papeleria y articulos de oficina | B5: COMPRA ORDEN DE PAGO SPEI 020125 =REFERENCIA CTA/CLABE: 021320040177324969, BXI SPEI BCO:021 BENEF:ZAPOPAN ESCOLAR SA DE CV (DATO NO VERIFICADO POR ESTA INSTITUCIÓN), Pago factura ZES000225777 CVE RASTREO: 7875APR2202501023679087530 RFC: No capturado IVA: 000000000000.00 HSBC HORA LIQ: 15:42:26 | G5: $1,693.38 | H5: 45658 | I5: PAPELERIA
A6: Comisiones bancarias | B6: COMISION ORDEN DE PAGO SPEI REFERENCIA: 020125 | G6: $5.00 | H6: 45658 | I6: COMISIONES BANCARIAS
A7: Comisiones bancarias | B7: I.V.A. ORDEN DE PAGO SPEI REFERENCIA: 020125 | G7: $0.80 | H7: 45658 | I7: COMISIONES BANCARIAS
A8: Arrendamiento Automotriz | B8: 0229984CARGO DOMICILIACION CGO DOMICILIACION:VW Leasing LEYENDA: VOLKSWAGEN LEASING REF SERV EMISOR:0060229984 CVE DE RASTREO:02107200021000820250102219127 REF:0229984 RFC VLE060918B86 IVA: 0.00 | G8: $20,721.48 | H8: 45658 | I8: LEASING VEHICULOS
A9: Telefono, internet | B9: TRASPASO A CUENTA DE TERCEROS 0003012025 IVA:00000000.00 , A LA CUENTA: 0259644345 Pago factura QCOME5361 AL R.F.C. LAN120809LR8 | G9: $17,400.00 | H9: 45658 | I9: TELEFONO E INTERNET
A10: Arrendamiento a personas fisicas resid nal | B10: COMPRA ORDEN DE PAGO SPEI 030125 =REFERENCIA CTA/CLABE: 021680040571712668, BXI SPEI BCO:021 BENEF:ANGEL OROSCO ANGELES (DATO NO VERIFICADO POR ESTA INSTITUCIÓN), Pago facturas 6324 y 6325 CVE RASTREO: 7875APR2202501033682619257 RFC: No capturado IVA: 000000000000.00 HSBC HORA LIQ: 17:22:27 | G10: $43,376.18 | H10: 45658 | I10: IMPRESIONES QUERETARO
A11: Comisiones bancarias | B11: COMISION ORDEN DE PAGO SPEI REFERENCIA: 030125 | G11: $5.00 | H11: 45658 | I11: COMISIONES BANCARIAS
A12: Comisiones bancarias | B12: I.V.A. ORDEN DE PAGO SPEI REFERENCIA: 0030125 | G12: $0.80 | H12: 45658 | I12: COMISIONES BANCARIAS
A13: Viaticos y gastos de viaje | B13: COMPRA ORDEN DE PAGO SPEI 030125 =REFERENCIA CTA/CLABE: 002580904396504698, BXI SPEI BCO:002 BENEF:BEATRIZ IRENE MEDELLIN ROSALE (DATO NO VERIFICADO POR ESTA INSTITUCIÓN), Pago de facturas FB6 B9F y 77D CVE RASTREO: 7875APR1202501033682637247 RFC: No capturado IVA: 000000000000.00 BANAMEX HORA LIQ: 17:26:47 | G13: $13,055.80 | H13: 45658 | I13: EQUIPAMIENTO Y RECARGAS
... A21: Comisiones bancarias | B21: I.V.A. ORDEN DE PAGO SPEI REFERENCIA: 030125 | G21: $0.80 | H21: 45658 | I21: COMISIONES BANCARIAS
B22: TRASPASO A CUENTA DE TERCEROS 0003012025 IVA:00000000.00 , A LA CUENTA: 1095347243 Pago factura Z07814 AL R.F.C. GSH191022B67 | G22: $2,924.39 | H22: 45658
A23: Viaticos y gastos de viaje | B23: COMPRA ORDEN DE PAGO SPEI 030125 =REFERENCIA CTA/CLABE: 646180401000017358, BXI SPEI BCO:646 BENEF:EFECTIVALE FINTECH (DATO NO VERIFICADO POR ESTA INSTITUCIÓN), 0168731 CVE RASTREO: 7875APR2202501033682707978 RFC: No capturado IVA: 000000000000.00 STP HORA LIQ: 17:45:13 | G23: $176,706.64 | H23: 45658 | I23: VIATICOS
A24: Comisiones bancarias | B24: COMISION ORDEN DE PAGO SPEI REFERENCIA: 030125 | G24: $5.00 | H24: 45658 | I24: COMISIONES BANCARIAS
A25: Comisiones bancarias | B25: I.V.A. ORDEN DE PAGO SPEI REFERENCIA: 030125 | G25: $0.80 | H25: 45658 | I25: COMISIONES BANCARIAS
A26: Viaticos y gastos de viaje | B26: COMPRA ORDEN DE PAGO SPEI 030125 =REFERENCIA CTA/CLABE: 021180042182424610, BXI SPEI BCO:021 BENEF:EFECTIVALE S DE RL DE CV (DATO NO VERIFICADO POR ESTA INSTITUCIÓN), C0180251001COMBTAR00 CVE RASTREO: 7875APR2202501033682724845 RFC: No capturado IVA: 000000000000.00 HSBC HORA LIQ: 17:49:51 | G26: $10,215.34 | H26: 45658 | I26: VIATICOS
A27: Comisiones bancarias | B27: COMISION ORDEN DE PAGO SPEI REFERENCIA: 030125 | G27: $5.00 | H27: 45658 | I27: COMISIONES BANCARIAS
A28: Comisiones bancarias | B28: I.V.A. ORDEN DE PAGO SPEI REFERENCIA: 030125 | G28: $0.80 | H28: 45658 | I28: COMISIONES BANCARIAS
A29: Sueldos y salarios | B29: COMPRA ORDEN DE PAGO SPEI 030125 =REFERENCIA CTA/CLABE: 012180001191796583, BXI SPEI BCO:012 BENEF:CONSORCIO EMPRENDEDOR LA FINCA (DATO NO VERIFICADO POR ESTA INSTITUCIÓN), Pago factura CVE RASTREO: 7875APR1202501033682754690 RFC: CEF180301697 IVA: 000000000000.00 BBVA MEXICO HORA LIQ: 18:04:53 | G29: $49,926.65 | H29: 45658 | I29: NOMINA
A30: Comisiones bancarias | B30: COMISION ORDEN DE PAGO SPEI REFERENCIA: 030125 | G30: $5.00 | H30: 45658 | I30: COMISIONES BANCARIAS
A31: Comisiones bancarias | B31: I.V.A. ORDEN DE PAGO SPEI REFERENCIA: 030125 | G31: $0.80 | H31: 45658 | I31: COMISIONES BANCARIAS
A32: Sueldos y salarios | B32: COMPRA ORDEN DE PAGO SPEI 030125 =REFERENCIA CTA/CLABE: 012180001197280747, BXI SPEI BCO:012 BENEF:SERV INDUSTRIALES ENDENSA (DATO NO VERIFICADO POR ESTA INSTITUCIÓN), Pago factura CVE RASTREO: 7875APR2202501033682795035 RFC: SIE210526EWA IVA: 000000000000.00 BBVA MEXICO HORA LIQ: 18:15:41 | G32: $13,890.77 | H32: 45658 | I32: NOMINA
A33: Comisiones bancarias | B33: COMISION ORDEN DE PAGO SPEI REFERENCIA: 030125 | G33: $5.00 | H33: 45658 | I33: COMISIONES BANCARIAS
A34: Comisiones bancarias | B34: I.V.A. ORDEN DE PAGO SPEI REFERENCIA: 030125 | G34: $0.80 | H34: 45658 | I34: COMISIONES BANCARIAS
... A87: Comisiones bancarias | B87: I.V.A. ORDEN DE PAGO SPEI REFERENCIA: 090125 | G87: $0.80 | H87: 45658 | I87: COMISIONES BANCARIAS
B88: TRASPASO A CUENTA DE TERCEROS 0009012025 IVA:00000000.00 , A LA CUENTA: 1227275781 PD UPS APODACA NL SEM02 AL R.F.C. CUMS810521CG2 | G88: $2,714.25 | H88: 45658 | I88: PASES DE CAJA (FONDOS CLIENTES)
A89: Sueldos y salarios | B89: COMPRA ORDEN DE PAGO SPEI 090125 =REFERENCIA CTA/CLABE: 012180001191796583, BXI SPEI BCO:012 BENEF:CONSORCIO EMPRENDEDOR LA FINCA (DATO NO VERIFICADO POR ESTA INSTITUCIÓN), Pago factura CVE RASTREO: 7875APR1202501093695401128 RFC: CEF180301697 IVA: 000000000000.00 BBVA MEXICO HORA LIQ: 12:51:56 | G89: $126,527.93 | H89: 45658 | I89: NOMINA
A90: Comisiones bancarias | B90: COMISION ORDEN DE PAGO SPEI REFERENCIA: 090125 | G90: $5.00 | H90: 45658 | I90: COMISIONES BANCARIAS
A91: Comisiones bancarias | B91: I.V.A. ORDEN DE PAGO SPEI REFERENCIA: 090125 | G91: $0.80 | H91: 45658 | I91: COMISIONES BANCARIAS
A92: Sueldos y salarios | B92: COMPRA ORDEN DE PAGO SPEI 090125 =REFERENCIA CTA/CLABE: 012180001197280747, BXI SPEI BCO:012 BENEF:SERV INDUSTRIALES ENDENSA (DATO NO VERIFICADO POR ESTA INSTITUCIÓN), Pago factura CVE RASTREO: 7875APR2202501093695409350 RFC: SIE210526EWA IVA: 000000000000.00 BBVA MEXICO HORA LIQ: 12:54:41 | G92: $69,034.58 | H92: 45658 | I92: NOMINA
A93: Comisiones bancarias | B93: COMISION ORDEN DE PAGO SPEI REFERENCIA: 090125 | G93: $5.00 | H93: 45658 | I93: COMISIONES BANCARIAS
A94: Comisiones bancarias | B94: I.V.A. ORDEN DE PAGO SPEI REFERENCIA: 090125 | G94: $0.80 | H94: 45658 | I94: COMISIONES BANCARIAS
A95: Dictamenes | B95: COMPRA ORDEN DE PAGO SPEI 090125 =REFERENCIA CTA/CLABE: 030470900013178030, BXI SPEI BCO:030 BENEF:JUVENAL LEAL HERNANDEZ (DATO NO VERIFICADO POR ESTA INSTITUCIÓN), Dict electrico pepsico cedis 712 769 y n CVE RASTREO: 7875APR2202501093695579909 RFC: No capturado IVA: 000000000000.00 BAJIO HORA LIQ: 13:48:39 | G95: $12,488.62 | H95: 45658 | I95: DICTAMENES
A96: Comisiones bancarias | B96: COMISION ORDEN DE PAGO SPEI REFERENCIA: 090125 | G96: $5.00 | H96: 45658 | I96: COMISIONES BANCARIAS
A97: Comisiones bancarias | B97: I.V.A. ORDEN DE PAGO SPEI REFERENCIA: 090125 | G97: $0.80 | H97: 45658 | I97: COMISIONES BANCARIAS
A98: Dictamenes | B98: COMPRA ORDEN DE PAGO SPEI 090125 =REFERENCIA CTA/CLABE: 030470900013178030, BXI SPEI BCO:030 BENEF:JUVENAL LEAL HERNANDEZ (DATO NO VERIFICADO POR ESTA INSTITUCIÓN), VERIFICACION ELECTRICA PEPSICO PATZCUARO CVE RASTREO: 7875APR2202501093695588426 RFC: No capturado IVA: 000000000000.00 BAJIO HORA LIQ: 13:51:45 | G98: $13,346.62 | H98: 45658 | I98: DICTAMENES
A99: Comisiones bancarias | B99: COMISION ORDEN DE PAGO SPEI REFERENCIA: 090125 | G99: $5.00 | H99: 45658 | I99: COMISIONES BANCARIAS
A100: Comisiones bancarias | B100: I.V.A. ORDEN DE PAGO SPEI REFERENCIA: 090125 | G100: $0.80 | H100: 45658 | I100: COMISIONES BANCARIAS
... A105: Comisiones bancarias | B105: I.V.A. ORDEN DE PAGO SPEI REFERENCIA: 090125 | G105: $0.80 | H105: 45658 | I105: COMISIONES BANCARIAS
B106: COMPRA ORDEN DE PAGO SPEI 090125 =REFERENCIA CTA/CLABE: 012680027965369565, BXI SPEI BCO:012 BENEF:FRANCISCO BERRUETA GONZALEZ (DATO NO VERIFICADO POR ESTA INSTITUCIÓN), Registro Cd Lerdo Dgo sem02 CVE RASTREO: 7875APR2202501093695637591 RFC: No capturado IVA: 000000000000.00 BBVA MEXICO HORA LIQ: 14:07:43 | C106: COGS | D106: OPERACIONES | G106: $4,342.80 | H106: 45658 | I106: REGISTROS PC (protección civil)
A107: Comisiones bancarias | B107: COMISION ORDEN DE PAGO SPEI REFERENCIA: 090125 | G107: $5.00 | H107: 45658 | I107: COMISIONES BANCARIAS
A108: Comisiones bancarias | B108: I.V.A. ORDEN DE PAGO SPEI REFERENCIA: 090125 | G108: $0.80 | H108: 45658 | I108: COMISIONES BANCARIAS
A109: Papeleria y articulos de oficina | B109: COMPRA ORDEN DE PAGO SPEI 090125 =REFERENCIA CTA/CLABE: 058597000025830419, BXI SPEI BCO:058 BENEF:SILVIA GUADALUPE RAMIREZ GUER (DATO NO VERIFICADO POR ESTA INSTITUCIÓN), Pago factura 877D5774 CVE RASTREO: 7875APR2202501093696009556 RFC: RAGS820903IP0 IVA: 000000000000.00 BANREGIO HORA LIQ: 16:08:56 | G109: $1,239.81 | H109: 45658 | I109: GASTOS OFICINA
A110: Comisiones bancarias | B110: COMISION ORDEN DE PAGO SPEI REFERENCIA: 090125 | G110: $5.00 | H110: 45658 | I110: COMISIONES BANCARIAS
A111: Comisiones bancarias | B111: I.V.A. ORDEN DE PAGO SPEI REFERENCIA: 0090125 | G111: $0.80 | H111: 45658 | I111: COMISIONES BANCARIAS
B112: COMPRA ORDEN DE PAGO SPEI 090125 =REFERENCIA CTA/CLABE: 012680015139118428, BXI SPEI BCO:012 BENEF:JORGE ALBERTO AVALOS WALDO (DATO NO VERIFICADO POR ESTA INSTITUCIÓN), Pago factura 3519 CVE RASTREO: 7875APR2202501093696107101 RFC: No capturado IVA: 000000000000.00 BBVA MEXICO HORA LIQ: 16:41:17 | G112: $2,459.20 | H112: 45658
A113: Comisiones bancarias | B113: COMISION ORDEN DE PAGO SPEI REFERENCIA: 090125 | G113: $5.00 | H113: 45658 | I113: COMISIONES BANCARIAS
A114: Comisiones bancarias | B114: I.V.A. ORDEN DE PAGO SPEI REFERENCIA: 090125 | G114: $0.80 | H114: 45658 | I114: COMISIONES BANCARIAS
A115: Viaticos y gastos de viaje | B115: COMPRA ORDEN DE PAGO SPEI 090125 =REFERENCIA CTA/CLABE: 012680015139118428, BXI SPEI BCO:012 BENEF:JORGE ALBERTO AVALOS WALDO (DATO NO VERIFICADO POR ESTA INSTITUCIÓN), SERV DE RECARGA A EXTINTOR DE 6 0 KG PQS CVE RASTREO: 7875APR2202501093696126793 RFC: No capturado IVA: 000000000000.00 BBVA MEXICO HORA LIQ: 16:46:57 | G115: $6,113.20 | H115: 45658 | I115: EQUIPAMIENTO Y RECARGAS
A116: Comisiones bancarias | B116: COMISION ORDEN DE PAGO SPEI REFERENCIA: 090125 | G116: $5.00 | H116: 45658 | I116: COMISIONES BANCARIAS
A117: Comisiones bancarias | B117: I.V.A. ORDEN DE PAGO SPEI REFERENCIA: 090125 | G117: $0.80 | H117: 45658 | I117: COMISIONES BANCARIAS
A118: Mensajería | B118: COMPRA ORDEN DE PAGO SPEI 090125 =REFERENCIA CTA/CLABE: 012180004432867893, BXI SPEI BCO:012 BENEF:DHL express mexico sa de cv (DATO NO VERIFICADO POR ESTA INSTITUCIÓN), 9804519685 CVE RASTREO: 7875APR1202501093696139697 RFC: No capturado IVA: 000000000000.00 BBVA MEXICO HORA LIQ: 16:51:13 | G118: $3,128.10 | H118: 45658 | I118: MENSAJERIA
A119: Comisiones bancarias | B119: COMISION ORDEN DE PAGO SPEI REFERENCIA: 090125 | G119: $5.00 | H119: 45658 | I119: COMISIONES BANCARIAS
A120: Comisiones bancarias | B120: I.V.A. ORDEN DE PAGO SPEI REFERENCIA: 090125 | G120: $0.80 | H120: 45658 | I120: COMISIONES BANCARIAS
A121: Papeleria y articulos de oficina | B121: COMPRA ORDEN DE PAGO SPEI 090125 =REFERENCIA CTA/CLABE: 058597000025830419, BXI SPEI BCO:058 BENEF:SILVIA GUADALUPE RAMIREZ GUER (DATO NO VERIFICADO POR ESTA INSTITUCIÓN), Pago factura 4FBAAD60 CVE RASTREO: 7875APR1202501093696150270 RFC: RAGS820903IP0 IVA: 000000000000.00 BANREGIO HORA LIQ: 16:54:52 | G121: $1,438.79 | H121: 45658 | I121: GASTOS OFICINA
A122: Comisiones bancarias | B122: COMISION ORDEN DE PAGO SPEI REFERENCIA: 090125 | G122: $5.00 | H122: 45658 | I122: COMISIONES BANCARIAS
A123: Comisiones bancarias | B123: I.V.A. ORDEN DE PAGO SPEI REFERENCIA: 090125 | G123: $0.80 | H123: 45658 | I123: COMISIONES BANCARIAS
A124: Sueldos y salarios | B124: COMPRA ORDEN DE PAGO SPEI 100125 =REFERENCIA CTA/CLABE: 012180001223109022, BXI SPEI BCO:012 BENEF:BRYTALAR CONSULTORES EN ING (DATO NO VERIFICADO POR ESTA INSTITUCIÓN), Pago factura CVE RASTREO: 7875APR1202501103697423749 RFC: BCI231002GC2 IVA: 000000000000.00 BBVA MEXICO HORA LIQ: 09:05:42 | G124: $5,322.38 | H124: 45658 | I124: NOMINA
... A149: Comisiones bancarias | B149: I.V.A. ORDEN DE PAGO SPEI REFERENCIA: 130125 | G149: $0.80 | H149: 45658 | I149: COMISIONES BANCARIAS
B150: COMPRA ORDEN DE PAGO SPEI 130125 =REFERENCIA CTA/CLABE: 002680902661053899, BXI SPEI BCO:002 BENEF:Edgar Alonso Aguilar Negrete (DATO NO VERIFICADO POR ESTA INSTITUCIÓN), Pago FV IS 1210 CVE RASTREO: 7875APR2202501133704831621 RFC: No capturado IVA: 000000000000.00 BANAMEX HORA LIQ: 10:34:54 | G150: $851.65 | H150: 45658 | I150: SISTEMAS RENTA CONMUTADOR
A151: Comisiones bancarias | B151: COMISION ORDEN DE PAGO SPEI REFERENCIA: 130125 | G151: $5.00 | H151: 45658 | I151: COMISIONES BANCARIAS
A152: Comisiones bancarias | B152: I.V.A. ORDEN DE PAGO SPEI REFERENCIA: 130125 | G152: $0.80 | H152: 45658 | I152: COMISIONES BANCARIAS
B153: COMPRA ORDEN DE PAGO SPEI 130125 =REFERENCIA CTA/CLABE: 002680902661053899, BXI SPEI BCO:002 BENEF:Edgar Alonso Aguilar Negrete (DATO NO VERIFICADO POR ESTA INSTITUCIÓN), Pago FV IS 1228 CVE RASTREO: 7875APR1202501133704851219 RFC: No capturado IVA: 000000000000.00 BANAMEX HORA LIQ: 10:41:54 | G153: $1,386.37 | H153: 45658 | I153: SISTEMAS RENTA CONMUTADOR
A154: Comisiones bancarias | B154: COMISION ORDEN DE PAGO SPEI REFERENCIA: 130125 | G154: $5.00 | H154: 45658 | I154: COMISIONES BANCARIAS
A155: Comisiones bancarias | B155: I.V.A. ORDEN DE PAGO SPEI REFERENCIA: 130125 | G155: $0.80 | H155: 45658 | I155: COMISIONES BANCARIAS
B156: COMPRA ORDEN DE PAGO SPEI 130125 =REFERENCIA CTA/CLABE: 002680902661053899, BXI SPEI BCO:002 BENEF:Edgar Alonso Aguilar Negrete (DATO NO VERIFICADO POR ESTA INSTITUCIÓN), Accesorios electronicosquemadores extern CVE RASTREO: 7875APR1202501133704864094 RFC: No capturado IVA: 000000000000.00 BANAMEX HORA LIQ: 10:46:10 | G156: $596.70 | H156: 45658 | I156: SISTEMAS MEMORIAS USB
A157: Comisiones bancarias | B157: COMISION ORDEN DE PAGO SPEI REFERENCIA: 130125 | G157: $5.00 | H157: 45658 | I157: COMISIONES BANCARIAS
A158: Comisiones bancarias | B158: I.V.A. ORDEN DE PAGO SPEI REFERENCIA: 130125 | G158: $0.80 | H158: 45658 | I158: COMISIONES BANCARIAS
A159: Comisiones Efectivale | B159: COMPRA ORDEN DE PAGO SPEI 130125 =REFERENCIA CTA/CLABE: 646501401000017351, BXI SPEI BCO:646 BENEF:EFECTIVALE FINTECH (DATO NO VERIFICADO POR ESTA INSTITUCIÓN), 0169479 CVE RASTREO: 7875APR2202501133704995586 RFC: No capturado IVA: 000000000000.00 STP HORA LIQ: 11:29:53 | G159: $807.36 | H159: 45658 | I159: COMISIONES EFECTIVALE
A160: Comisiones bancarias | B160: COMISION ORDEN DE PAGO SPEI REFERENCIA: 130125 | G160: $5.00 | H160: 45658 | I160: COMISIONES BANCARIAS
A161: Comisiones bancarias | B161: I.V.A. ORDEN DE PAGO SPEI REFERENCIA: 130125 | G161: $0.80 | H161: 45658 | I161: COMISIONES BANCARIAS
A162: Sueldos y salarios | B162: COMPRA ORDEN DE PAGO SPEI 130125 =REFERENCIA CTA/CLABE: 014180655087659052, BXI SPEI BCO:014 BENEF:GROWTHSTUDIO (DATO NO VERIFICADO POR ESTA INSTITUCIÓN), Pago factura CVE RASTREO: 7875APR1202501133705679233 RFC: No capturado IVA: 000000000000.00 SANTANDER HORA LIQ: 15:07:42 | G162: $9,486.70 | H162: 45658 | I162: NOMINA
A163: Comisiones bancarias | B163: COMISION ORDEN DE PAGO SPEI REFERENCIA: 0130125 | G163: $5.00 | H163: 45658 | I163: COMISIONES BANCARIAS
A164: Comisiones bancarias | B164: I.V.A. ORDEN DE PAGO SPEI REFERENCIA: 0130125 | G164: $0.80 | H164: 45658 | I164: COMISIONES BANCARIAS
A165: Mantenimiento y conservacion | B165: TRASPASO A CUENTA DE TERCEROS 0013012025 IVA:00000000.00 , A LA CUENTA: 0538018409 Pago cot 123868 AL R.F.C. AVA730426HT0 | G165: $4,985.90 | H165: 45658 | I165: MANTENIMIENTO VEHICULOS
A166: Mantenimiento y conservacion | B166: TRASPASO A CUENTA DE TERCEROS 0013012025 IVA:00000000.00 , A LA CUENTA: 0691382407 ORDEN DE SERV 404 AL R.F.C. WOC110727E32 | G166: $5,240.00 | H166: 45658 | I166: MANTENIMIENTO VEHICULOS
B167: 3362983CARGO DOMICILIACION CGO DOMICILIACION:FONDO DE LAS NACIONES UNIDAS LEYENDA: DONATIVOS UNICEF REF SERV EMISOR:00087446050000175815 CVE DE RASTREO:202501130700018702504429362984 REF:3362983 RFC FNU540520JX8 IVA: 0.00 | G167: $383.00 | H167: 45658 | I167: DONATIVOS
A168: Papeleria y articulos de oficina | B168: COMPRA ORDEN DE PAGO SPEI 140125 =REFERENCIA CTA/CLABE: 014580655069894228, BXI SPEI BCO:014 BENEF:ABASTECEDORA DE OFICINAS (DATO NO VERIFICADO POR ESTA INSTITUCIÓN), Pago COT 2922289 CVE RASTREO: 7875APR2202501143708179189 RFC: No capturado IVA: 000000000000.00 SANTANDER HORA LIQ: 13:16:46 | G168: $7,380.99 | H168: 45658 | I168: PAPELERIA
A169: Comisiones bancarias | B169: COMISION ORDEN DE PAGO SPEI REFERENCIA: 140125 | G169: $5.00 | H169: 45658 | I169: COMISIONES BANCARIAS
A170: Comisiones bancarias | B170: I.V.A. ORDEN DE PAGO SPEI REFERENCIA: 140125 | G170: $0.80 | H170: 45658 | I170: COMISIONES BANCARIAS
A171: Papeleria y articulos de oficina | B171: COMPRA ORDEN DE PAGO SPEI 4659825 =REFERENCIA CTA/CLABE: 014580655069894228, BXI SPEI BCO:014 BENEF:ABASTECEDORA DE OFICINAS (DATO NO VERIFICADO POR ESTA INSTITUCIÓN), 4659825 CVE RASTREO: 7875APR1202501143708206977 RFC: No capturado IVA: 000000000000.00 SANTANDER HORA LIQ: 13:24:46 | G171: $7,380.99 | H171: 45658 | I171: PAPELERIA
A172: Comisiones bancarias | B172: COMISION ORDEN DE PAGO SPEI REFERENCIA: 4659825 | G172: $5.00 | H172: 45658 | I172: COMISIONES BANCARIAS
A173: Comisiones bancarias | B173: I.V.A. ORDEN DE PAGO SPEI REFERENCIA: 4659825 | G173: $0.80 | H173: 45658 | I173: COMISIONES BANCARIAS
B174: PAGO DE LDC-IMSS ALTA: Z1KMF3QY4C6K179SZ5971000Y5Q6001F6C8000U9DB0000000X689 ID PAGO: Z3423762106202412339299 TOTAL: 0000000005393221 RASTREO: 000041926 | G174: $53,932.21 | H174: 45658
A175: Agua | B175: COMPRA ORDEN DE PAGO SPEI 150125 =REFERENCIA CTA/CLABE: 030680900003677328, BXI SPEI BCO:030 BENEF:CAMSA SOLUCIONES FISCALES SC (DATO NO VERIFICADO POR ESTA INSTITUCIÓN), Pago ISN diciembre CVE RASTREO: 7875APR1202501153710867881 RFC: No capturado IVA: 000000000000.00 BAJIO HORA LIQ: 10:42:57 | G175: $5,413.00 | H175: 45658 | I175: SERVICIOS CONTABLES
A176: Comisiones bancarias | B176: COMISION ORDEN DE PAGO SPEI REFERENCIA: 150125 | G176: $5.00 | H176: 45658 | I176: COMISIONES BANCARIAS
A177: Comisiones bancarias | B177: I.V.A. ORDEN DE PAGO SPEI REFERENCIA: 150125 | G177: $0.80 | H177: 45658 | I177: COMISIONES BANCARIAS
A178: Mensajería | B178: COMPRA ORDEN DE PAGO SPEI 150125 =REFERENCIA CTA/CLABE: 012180004432867893, BXI SPEI BCO:012 BENEF:DHL express mexico sa de cv (DATO NO VERIFICADO POR ESTA INSTITUCIÓN), 9804519685 CVE RASTREO: 7875APR1202501153710887754 RFC: No capturado IVA: 000000000000.00 BBVA MEXICO HORA LIQ: 10:47:41 | G178: $3,724.49 | H178: 45658 | I178: MENSAJERIA
A179: Comisiones bancarias | B179: COMISION ORDEN DE PAGO SPEI REFERENCIA: 150125 | G179: $5.00 | H179: 45658 | I179: COMISIONES BANCARIAS
A180: Comisiones bancarias | B180: I.V.A. ORDEN DE PAGO SPEI REFERENCIA: 150125 | G180: $0.80 | H180: 45658 | I180: COMISIONES BANCARIAS
A181: Sueldos y salarios | B181: COMPRA ORDEN DE PAGO SPEI 150125 =REFERENCIA CTA/CLABE: 012180001228039414, BXI SPEI BCO:012 BENEF:MEDICA DE OAXACA SA DE CV (DATO NO VERIFICADO POR ESTA INSTITUCIÓN), Pago factura CVE RASTREO: 7875APR2202501153711057660 RFC: MOA030716677 IVA: 000000000000.00 BBVA MEXICO HORA LIQ: 11:26:04 | G181: $1,050.83 | H181: 45658 | I181: NOMINA
A182: Comisiones bancarias | B182: COMISION ORDEN DE PAGO SPEI REFERENCIA: 150125 | G182: $5.00 | H182: 45658 | I182: COMISIONES BANCARIAS
A183: Comisiones bancarias | B183: I.V.A. ORDEN DE PAGO SPEI REFERENCIA: 150125 | G183: $0.80 | H183: 45658 | I183: COMISIONES BANCARIAS
A184: Comisiones bancarias | B184: COMISION ORDEN DE PAGO SPEI REFERENCIA: 150125 | G184: $5.00 | H184: 45658 | I184: COMISIONES BANCARIAS
A185: Comisiones bancarias | B185: I.V.A. ORDEN DE PAGO SPEI REFERENCIA: 150125 | G185: $0.80 | H185: 45658 | I185: COMISIONES BANCARIAS
A186: Sueldos y salarios | B186: COMPRA ORDEN DE PAGO SPEI 160125 =REFERENCIA CTA/CLABE: 012180001197280747, BXI SPEI BCO:012 BENEF:SERV INDUSTRIALES ENDENSA (DATO NO VERIFICADO POR ESTA INSTITUCIÓN), Pago factura CVE RASTREO: 7875APR1202501163714458595 RFC: SIE210526EWA IVA: 000000000000.00 BBVA MEXICO HORA LIQ: 09:13:41 | G186: $94,878.57 | H186: 45658 | I186: NOMINA
... A191: Comisiones bancarias | B191: I.V.A. ORDEN DE PAGO SPEI REFERENCIA: 160125 | G191: $0.80 | H191: 45658 | I191: COMISIONES BANCARIAS
...

Sheet NOTAS
A2: CORNEJO JIMENEZ MARLEN | B2: Está asignada a 3 zonas, se realizó una división de su monto de nómina en cada mes
B3: No tiene nómina interna en abril
A4: CRUZ RODRIGUEZ MARINA CRISTHEL | B4: No tiene zona designada, se asignó de acuerdo a la zona de nómina de los archivos de nom externa
A5: GARCIA CORTES BELLMAR ALONSO | B5: No tiene zona designada, se asignó de acuerdo a la zona de nómina de los archivos de nom externa
A6: HIDALGO RODRIGUEZ JESUS EULALIO | B6: No tiene zona designada, se asignó de acuerdo a la zona de nómina de los archivos de nom externa
A7: LEDEZMA LONGORIA DANIKA (MULTIZONA) | B7: Está asignada a 3 zonas, se realizó una división de su monto de nómina en cada mes
A8: MACIAS BERNACHE ESMERALDA GALILEA | B8: No tiene zona designada, se asignó de acuerdo a la zona de nómina de los archivos de nom externa
A9: MIRELES ORNELAS JORGE | B9: No tiene zona designada, se asignó de acuerdo a la zona de nómina de los archivos de nom externa
A10: MORENO CAMPOS ARMANDO | B10: No tiene zona designada, se asignó de acuerdo a la zona de nómina de los archivos de nom externa
A11: MURO JIMENEZ GERARDO AUGUSTO | B11: No tiene zona designada, se asignó de acuerdo a la zona de nómina de los archivos de nom externa
A12: PEREZ LOPEZ LUIS GUSTAVO | B12: No tiene zona designada, se asignó de acuerdo a la zona de nómina de los archivos de nom externa
A14: MORENO CATARINO VICTOR URIEL | B14: EN EL ARCHIVO DE MARIO ESTÁ COMO NORTE Y EN EL BUDGET COMO NOROESTE
A15: Las depreciaciones de equipo de cómputo y mob de oficina se dividen por headcount, la de automoviles se manda a ops
A16: Se hizo reconteo de headcount para división de egresos a partir de depreciaciones | K16: LAE
A17: PREGUNTAR POR CONCEPTO devolucion en febrero | K17: 4 MESES EN CONCLUIRSE
A18: SE agregó LAE como dirección | K18: EMPIEZA egresos bajos y sbe
A19: preguntar de PAGO DE INTERESES 88059964-089590332 de 7mil sobre si es comision o intereses | K19: 12 millones de inver
A20: preguntar de loc box | B20: (se mandó 50% a técnico y 50% a LAE) | K20: 250 mil de renta mensual por construir
A21: PENDIENTE UNIFORMES, VER QUIEN LOS USA | K21: costo financiero: 1% para factoraje hasta 2% capital mint
A22: SE ELIMINÓ BBVA855 POR -0,17 | K22: minimizar gasto inecesario de pagar rentas por no hacer nada
A23: Arquitectura - Jorge Gonzalez Hernandez Magri MacBook Pro 14" MDE14E/A Chip M5 CPU10 GPU10 16GB 1TB Negro Espacial | C23: REVISAR EL EGRESSO DE SISTEMAS EMPRESARIALES DABO, ES DE 1981 Y EL GASTO FUE DE 45 K | K23: minimizar riesgo de subidas de precios y servicios
A24: KORNER SALES, VIATICOS TIENEN 719 Y EN CAMSA HAY 619,83 | K24: menor costo financiero
A25: preguntar de BANCO MONEX S.A. INSTITUCION DE BANCA MULTIPLE, MONEX GRUPO FINANCIERO fideicomiso | K25: una vez empezando no se para
A26: Revisar Belanea Mexico recarga de Arturo Ret, es posible que ya esté en dispersiones si el gasto se hizo con clara | K26: componente mas grande: mano de obra
K28: safety net: ya no autorizo mas pagos cuando llego a 1.5 mill

Sheet DF_LIMPIO1
A1: Fecha | B1: Tipo | C1: Número | D1: Concepto | E1: Referencia | F1: Cargos | G1: Clasf Efs | H1: Abonos | I1: Saldo
A2: 01/Ene/2026 | B2: Diario | C2: 297 | D2: NOMINA QUINCENAL ENERO 2026 | F2: 146471.83 | G2: Sueldos y salarios | H2: 0 | I2: 146471.83
A3: 01/Ene/2026 | B3: Diario | C3: 500 | D3: PROVISION IMSS ENERO 2026 | E3: IMSS | F3: 13833.01 | G3: Cuotas al IMSS | H3: 0 | I3: 13833.01
A4: 01/Ene/2026 | B4: Diario | C4: 501 | D4: IMPUESTO SOBRE NOMINA | E4: ISN | F4: 3569 | G4: Impuesto estatal sobre nóminas | H4: 0 | I4: 3569
A5: 01/Ene/2026 | B5: Diario | C5: 280 | D5: UNIDAD DE NEGOCIO NIBER | E5: F-5904 | F5: 179.18 | G5: Servicios administrativos | H5: 0 | I5: 179.18
A6: 01/Ene/2026 | B6: Diario | C6: 280 | D6: UNIDAD DE NEGOCIO NIBER | E6: F-5900 | F6: 1260 | G6: Servicios administrativos | H6: 0 | I6: 1439.18
A7: 01/Ene/2026 | B7: Diario | C7: 280 | D7: UNIDAD DE NEGOCIO NIBER | E7: F-5903 | F7: 2616 | G7: Servicios administrativos | H7: 0 | I7: 4055.18
A8: 01/Ene/2026 | B8: Diario | C8: 280 | D8: UNIDAD DE NEGOCIO NIBER | E8: F-5907 | F8: 51405.6 | G8: Servicios administrativos | H8: 0 | I8: 55460.78
A9: 01/Ene/2026 | B9: Diario | C9: 280 | D9: UNIDAD DE NEGOCIO NIBER | E9: F-5901 | F9: 215465.96 | G9: Servicios administrativos | H9: 0 | I9: 270926.74
A10: 01/Ene/2026 | B10: Diario | C10: 280 | D10: UNIDAD DE NEGOCIO NIBER | E10: F-5908 | F10: 228035.56 | G10: Servicios administrativos | H10: 0 | I10: 498962.3
A11: 01/Ene/2026 | B11: Diario | C11: 288 | D11: BRYTALAR CONSULTORES EN INGENIERIA Y OBRAS | E11: F-766 | F11: 4613.53 | G11: Servicios administrativos | H11: 0 | I11: 503575.83
A12: 01/Ene/2026 | B12: Diario | C12: 288 | D12: BRYTALAR CONSULTORES EN INGENIERIA Y OBRAS | E12: F-770 | F12: 4613.53 | G12: Servicios administrativos | H12: 0 | I12: 508189.36
A13: 01/Ene/2026 | B13: Diario | C13: 288 | D13: BRYTALAR CONSULTORES EN INGENIERIA Y OBRAS | E13: F-771 | F13: 4613.53 | G13: Servicios administrativos | H13: 0 | I13: 512802.89
A14: 01/Ene/2026 | B14: Diario | C14: 288 | D14: BRYTALAR CONSULTORES EN INGENIERIA Y OBRAS | E14: F-778 | F14: 4613.53 | G14: Servicios administrativos | H14: 0 | I14: 517416.42
... A103: 01/Ene/2026 | B103: Diario | C103: 287 | D103: GRUMINER | E103: F-430 | F103: 25000 | G103: Seguros y fianzas | H103: 0 | I103: 25000
A104: 02/Ene/2026 | B104: Egresos | C104: 2 | D104: SEGUROS BANORTE | E104: 48728 | F104: 3608.33 | G104: Seguros y fianzas | H104: 0 | I104: 28608.33
A105: 13/Ene/2026 | B105: Egresos | C105: 79 | D105: SEGUROS BANORTE | E105: 48938 | F105: 53535 | G105: Seguros y fianzas | H105: 0 | I105: 82143.33
A106: 27/Ene/2026 | B106: Egresos | C106: 148 | D106: SEGUROS Y FIANZAS | E106: 49147 | F106: 5700.83 | G106: Seguros y fianzas | H106: 0 | I106: 87844.16
A107: 01/Ene/2026 | B107: Diario | C107: 262 | D107: CUOTAS Y SUSCRIPCIONES | E107: F-VARIOS | F107: 585.56 | G107: Cuotas y suscripciones | H107: 0 | I107: 585.56
A108: 01/Ene/2026 | B108: Diario | C108: 276 | D108: EDGAR ALONSO AGUILAR NEGRETE | E108: F-1615 | F108: 1227.1 | G108: Cuotas y suscripciones | H108: 0 | I108: 1812.66
A109: 01/Ene/2026 | B109: Diario | C109: 276 | D109: EDGAR ALONSO AGUILAR NEGRETE | E109: F-1632 | F109: 4275 | G109: Cuotas y suscripciones | H109: 0 | I109: 6087.66
A110: 01/Ene/2026 | B110: Diario | C110: 276 | D110: EDGAR ALONSO AGUILAR NEGRETE | E110: F-1620 | F110: 18254.66 | G110: Cuotas y suscripciones | H110: 0 | I110: 24342.32
A111: 01/Ene/2026 | B111: Diario | C111: 276 | D111: IMR SOFTWARE | E111: F-4614 | F111: 4500 | G111: Cuotas y suscripciones | H111: 0 | I111: 28842.32
A112: 01/Ene/2026 | B112: Diario | C112: 276 | D112: IMR SOFTWARE | E112: F-2586 | F112: 3190 | G112: Cuotas y suscripciones | H112: 0 | I112: 32032.32
A113: 01/Ene/2026 | B113: Diario | C113: 276 | D113: ONLINE CARRER CENTER MEXICO | E113: F-3101 | F113: 3864 | G113: Cuotas y suscripciones | H113: 0 | I113: 35896.32
A114: 01/Ene/2026 | B114: Diario | C114: 281 | D114: GOOGLE MX | E114: F-2523 | F114: -5233.75 | G114: Cuotas y suscripciones | H114: 0 | I114: 30662.57
A115: 01/Ene/2026 | B115: Diario | C115: 281 | D115: GOOGLE MX | E115: F-2524 | F115: -3274.32 | G115: Cuotas y suscripciones | H115: 0 | I115: 27388.25
A116: 01/Ene/2026 | B116: Diario | C116: 281 | D116: GOOGLE MX | E116: F-5241 | F116: 8508.07 | G116: Cuotas y suscripciones | H116: 0 | I116: 35896.32
A117: 01/Ene/2026 | B117: Diario | C117: 281 | D117: GOOGLE MX | E117: F-7673 | F117: 8620.69 | G117: Cuotas y suscripciones | H117: 0 | I117: 44517.01
A118: 01/Ene/2026 | B118: Diario | C118: 282 | D118: JESUS ALEJANDRO GALLARZA ORTEGA | E118: F- | F118: 46093.1 | G118: Cuotas y suscripciones | H118: 0 | I118: 90610.11
A119: 16/Ene/2026 | B119: Egresos | C119: 106 | D119: PAGO INTERESES XEPELIN | E119: 49013 | F119: 7067.24 | G119: Cuotas y suscripciones | H119: 0 | I119: 97677.35
A120: 22/Ene/2026 | B120: Egresos | C120: 220 | D120: INVOICE | E120: BBVA793 | F120: 3052.96 | G120: Cuotas y suscripciones | H120: 0 | I120: 100730.31
A121: 22/Ene/2026 | B121: Egresos | C121: 235 | D121: INVOICE | E121: BBVAUSD | F121: 14460.38 | G121: Cuotas y suscripciones | H121: 0 | I121: 115190.69
A122: 22/Ene/2026 | B122: Egresos | C122: 236 | D122: INVOICE | E122: BBVAUSD | F122: 28237.34 | G122: Cuotas y suscripciones | H122: 0 | I122: 143428.03
A123: 23/Ene/2026 | B123: Egresos | C123: 237 | D123: INVOICE | E123: BBVAUSD | F123: 6454.65 | G123: Cuotas y suscripciones | H123: 0 | I123: 149882.68
A124: 23/Ene/2026 | B124: Egresos | C124: 238 | D124: INVOICE | E124: BBVAUSD | F124: 2422.94 | G124: Cuotas y suscripciones | H124: 0 | I124: 152305.62
A125: 29/Ene/2026 | B125: Egresos | C125: 241 | D125: BBVAUSD | E125: BBVAUSD | F125: 86195.46 | G125: Cuotas y suscripciones | H125: 0 | I125: 238501.08
A126: 29/Ene/2026 | B126: Egresos | C126: 252 | D126: BBVAUSD ARIBA | E126: BBVAUSD | F126: 2478.51 | G126: Cuotas y suscripciones | H126: 0 | I126: 240979.59
A127: 01/Ene/2026 | B127: Diario | C127: 292 | D127: MARIA SONIA RODRIGUEZ GONZALEZ | E127: F-3115 | F127: 32000 | G127: Fletes y acarreos | H127: 0 | I127: 32000
A128: 01/Ene/2026 | B128: Diario | C128: 269 | D128: UNIFORMES | E128: F-VARIOS | F128: 6378.42 | G128: Uniformes | H128: 0 | I128: 6378.42
A129: 01/Ene/2026 | B129: Diario | C129: 294 | D129: ALBERTO SANCHEZ BENAVIDES | E129: F-1909 | F129: 4212 | G129: Uniformes | H129: 0 | I129: 10590.42
A130: 01/Ene/2026 | B130: Diario | C130: 294 | D130: ALBERTO SANCHEZ BENAVIDES | E130: F-1940 | F130: 14762 | G130: Uniformes | H130: 0 | I130: 25352.42
A131: 01/Ene/2026 | B131: Diario | C131: 294 | D131: SEGURIDAD TECNICA MAT | E131: F-123377 | F131: 583.4 | G131: Uniformes | H131: 0 | I131: 25935.82
... A134: 05/Ene/2026 | B134: Egresos | C134: 200 | D134: INTERESES 9651320420 | E134: BBVA749 | F134: 272.02 | G134: GASTOS NO DEDUCIBLES | H134: 0 | I134: 672.02
A135: 07/Ene/2026 | B135: Egresos | C135: 27 | D135: BEPENSA LEASING | E135: 48793 | F135: 0.01 | G135: GASTOS NO DEDUCIBLES | H135: 0 | I135: 672.03
A136: 07/Ene/2026 | B136: Egresos | C136: 28 | D136: VOLKSWAGEN LEASING | E136: 48794 | F136: 14252.68 | G136: GASTOS NO DEDUCIBLES | H136: 0 | I136: 14924.71
A137: 13/Ene/2026 | B137: Egresos | C137: 78 | D137: ND | E137: 48935 | F137: 1849.04 | G137: GASTOS NO DEDUCIBLES | H137: 0 | I137: 16773.75
A138: 14/Ene/2026 | B138: Egresos | C138: 95 | D138: ND | E138: 48981 | F138: 428 | G138: GASTOS NO DEDUCIBLES | H138: 0 | I138: 17201.75
A139: 22/Ene/2026 | B139: Egresos | C139: 234 | D139: BBVAUSD | E139: BBVAUSD | F139: 1256.54 | G139: GASTOS NO DEDUCIBLES | H139: 0 | I139: 18458.29
A140: 23/Ene/2026 | B140: Egresos | C140: 222 | D140: ND | E140: BBVA797 | F140: 4958.17 | G140: GASTOS NO DEDUCIBLES | H140: 0 | I140: 23416.46
A141: 30/Ene/2026 | B141: Egresos | C141: 242 | D141: BBVAUSD ND | E141: BBVAUSD ND | F141: 1121.46 | G141: GASTOS NO DEDUCIBLES | H141: 0 | I141: 24537.92
A142: 01/Ene/2026 | B142: Diario | C142: 285 | D142: DHL EXPRESS MEXICO | E142: F-4083 | F142: 1614.2 | G142: Mensajería | H142: 0 | I142: 1614.2
A143: 01/Ene/2026 | B143: Diario | C143: 285 | D143: DHL EXPRESS MEXICO | E143: F-5245 | F143: 8686.68 | G143: Mensajería | H143: 0 | I143: 10300.88
A144: 01/Ene/2026 | B144: Diario | C144: 285 | D144: DHL EXPRESS MEXICO | E144: F-8506 | F144: 12420.34 | G144: Mensajería | H144: 0 | I144: 22721.22
A145: 01/Ene/2026 | B145: Diario | C145: 285 | D145: DHL EXPRESS MEXICO | E145: F-44791 | F145: 14372.07 | G145: Mensajería | H145: 0 | I145: 37093.29
A146: 01/Ene/2026 | B146: Diario | C146: 285 | D146: DHL EXPRESS MEXICO | E146: F-2880 | F146: 15416.65 | G146: Mensajería | H146: 0 | I146: 52509.94
A147: 01/Ene/2026 | B147: Diario | C147: 278 | D147: DISEÑO EDIFICACION Y ASESORIA CIVIL | E147: F-2600 | F147: 8000 | G147: Dictamenes | H147: 0 | I147: 8000
A148: 01/Ene/2026 | B148: Diario | C148: 278 | D148: DISTRIBUIDORA PENINSULUX | E148: F-1 | F148: 24124.7 | G148: Dictamenes | H148: 0 | I148: 32124.7
A149: 01/Ene/2026 | B149: Diario | C149: 278 | D149: GOBIERNO DEL ESTADO DE MEXICO | E149: F- | F149: 8208 | G149: Dictamenes | H149: 0 | I149: 40332.7
A150: 01/Ene/2026 | B150: Diario | C150: 278 | D150: GUILLERMO FRANCISCO ARREOLA OLIVEROS | E150: F- | F150: 689.66 | G150: Dictamenes | H150: 0 | I150: 41022.36
... A189: 01/Ene/2026 | B189: Diario | C189: 279 | D189: GROWTHSTUDIO | E189: F-2287 | F189: 262500 | G189: Diseño digital | H189: 0 | I189: 834150.74
A190: 31/Ene/2026 | B190: Diario | C190: 303 | D190: REVERSAS INGRESOS | F190: -619202.69 | G190: Diseño digital | H190: 0 | I190: 214948.05
A191: 31/Ene/2026 | B191: Diario | C191: 303 | D191: REVERSAS INGRESOS | F191: -33600 | G191: Diseño digital | H191: 0 | I191: 181348.05
A192: 01/Ene/2026 | B192: Diario | C192: 267 | D192: REGISTROS GUBERNAMENTALES | E192: F-VARIOS | F192: 67868.64 | G192: REGISTROS GUBERNAMENTALES | H192: 0 | I192: 67868.64
A193: 01/Ene/2026 | B193: Diario | C193: 291 | D193: REGISTROS | E193: F- | F193: 64130 | G193: REGISTROS GUBERNAMENTALES | H193: 0 | I193: 131998.64
A194: 01/Ene/2026 | B194: Diario | C194: 502 | D194: DEPRECIACIONES | F194: 6213.65 | G194: Depreciación de maquinaria y equipo | H194: 0 | I194: 6213.65
A195: 01/Ene/2026 | B195: Diario | C195: 502 | D195: DEPRECIACIONES | F195: 791.67 | G195: Depr de autom, autob, camiones, tractoc | H195: 0 | I195: 791.67
A196: 01/Ene/2026 | B196: Diario | C196: 502 | D196: DEPRECIACIONES | F196: 9349.03 | G196: Depreciación de mobiliario y eq de ofic | H196: 0 | I196: 9349.03
A197: 01/Ene/2026 | B197: Diario | C197: 502 | D197: DEPRECIACIONES | F197: 32688.17 | G197: Depreciación de equipo de cómputo | H197: 0 | I197: 32688.17
A198: 01/Ene/2026 | B198: Diario | C198: 502 | D198: DEPRECIACIONES | F198: 5539.44 | G198: Depreciación de otros activos fijos | H198: 0 | I198: 5539.44
A199: 01/Ene/2026 | B199: Diario | C199: 502 | D199: DEPRECIACIONES | F199: 5828.89 | G199: Depreciación de instalación | H199: 0 | I199: 5828.89
A200: 01/Ene/2026 | B200: Diario | C200: 502 | D200: AMORTIZACION | F200: 203058.79 | G200: Amortización acumulada de Software | H200: 0 | I200: 203058.79
A201: 01/Ene/2026 | B201: Egresos | C201: 300 | D201: VALUACION CAMBIARIA | F201: 5557.72 | G201: Pérdida cambiaria | H201: 0 | I201: 5557.72
A202: 05/Ene/2026 | B202: Egresos | C202: 7 | D202: PAGO DE INTERESES 88059964-089590332 | E202: 48740 | F202: 31802.26 | G202: Intereses a cargo bancario nacional | H202: 0 | I202: 31802.26
A203: 05/Ene/2026 | B203: Egresos | C203: 200 | D203: INTERESES 9651320420 | E203: BBVA749 | F203: 126798.61 | G203: Intereses a cargo bancario nacional | H203: 0 | I203: 158600.87
A204: 16/Ene/2026 | B204: Egresos | C204: 106 | D204: PAGO INTERESES XEPELIN | E204: 49013 | F204: 44066.6 | G204: Intereses a cargo bancario nacional | H204: 0 | I204: 202667.47
A205: 05/Ene/2026 | B205: Egresos | C205: 7 | D205: PAGO DE INTERESES 88059964-089590332 | E205: 48740 | F205: 78740 | G205: Comisiones Bancarias | H205: 0 | I205: 78740
A206: 07/Ene/2026 | B206: Egresos | C206: 202 | D206: BBVA MEXICO | E206: BBVA751 | F206: 3700.28 | G206: Comisiones Bancarias | H206: 0 | I206: 82440.28
A207: 23/Ene/2026 | B207: Egresos | C207: 240 | D207: COMISIONES BANCARIAS BBVA USD | E207: COMISIONES BANCARIAS | F207: 524.48 | G207: Comisiones Bancarias | H207: 0 | I207: 82964.76
A208: 23/Ene/2026 | B208: Diario | C208: 400 | D208: PAGO TC CLARA | E208: 49124 | F208: 9948.99 | G208: Comisiones Bancarias | H208: 0 | I208: 92913.75
A209: 30/Ene/2026 | B209: Egresos | C209: 243 | D209: AFIRME | E209: COMISIONES BANCARIAS | F209: 400 | G209: Comisiones Bancarias | H209: 0 | I209: 93313.75
A210: 31/Ene/2026 | B210: Egresos | C210: 246 | D210: COMISIONES BANCARIAS INBURSA | E210: COMISIONES BANCARIAS INBURSA | F210: 256.55 | G210: Comisiones Bancarias | H210: 0 | I210: 93570.3
A211: 31/Ene/2026 | B211: Egresos | C211: 247 | D211: COMISIONES BANCARIAS SCOTIABANK | E211: COMISIONES BANCARIAS SCORTIA | F211: 620 | G211: Comisiones Bancarias | H211: 0 | I211: 94190.3
A212: 01/Ene/2026 | B212: Diario | C212: 295 | D212: EFECTIVALE | E212: F-3188581 | F212: 858.75 | G212: Comisiones Efectivale | H212: 0 | I212: 858.75
A213: 01/Ene/2026 | B213: Diario | C213: 295 | D213: EFECTIVALE | E213: F-3196634 | F213: 858.75 | G213: Comisiones Efectivale | H213: 0 | I213: 1717.5
A214: 01/Ene/2026 | B214: Diario | C214: 295 | D214: EFECTIVALE | E214: F-3173500 | F214: 1202.25 | G214: Comisiones Efectivale | H214: 0 | I214: 2919.75
A215: 01/Ene/2026 | B215: Diario | C215: 295 | D215: EFECTIVALE | E215: F-3181065 | F215: 1374 | G215: Comisiones Efectivale | H215: 0 | I215: 4293.75
A216: 01/Ene/2026 | B216: Diario | C216: 296 | D216: EFECTIFINTECH | E216: F-54797 | F216: 600 | G216: Comisiones Efectivale | H216: 0 | I216: 4893.75
A217: 01/Ene/2026 | B217: Diario | C217: 296 | D217: EFECTIFINTECH | E217: F-56083 | F217: 600 | G217: Comisiones Efectivale | H217: 0 | I217: 5493.75
A218: 01/Ene/2026 | B218: Diario | C218: 296 | D218: EFECTIFINTECH | E218: F-55444 | F218: 600 | G218: Comisiones Efectivale | H218: 0 | I218: 6093.75
A219: 01/Ene/2026 | B219: Diario | C219: 296 | D219: EFECTIFINTECH | E219: F-54158 | F219: 660 | G219: Comisiones Efectivale | H219: 0 | I219: 6753.75

Sheet DF_LIMPIO2
A1: CATEGORIA_NETSUITE | B1: Concepto | C1: IS | D1: ÁREA | E1: ZONA PPTO | F1: EMPLEADO | G1: MONTO | H1: PERIODO | I1: AREA | J1: ZONA | K1: PCT_POND | L1: Fecha | M1: Tipo | N1: Número | O1: Clasf Efs | P1: ID SGN | Q1: PUESTO | R1: PAGADORA | S1: Columna 19 | T1: Columna 20 | U1: Columna 21 | V1: Columna 22 | W1: Columna 23 | X1: Columna 24 | Y1: Columna 25
A2: Otros gastos generales | B2: ACTIVE LEASING | C2: OTROS Facturación / GASTOS | D2: LAE | G2: 7343.97 | L2: 01/Feb/2026 | M2: Diario | N2: 18 | O2: Arrendamiento a pers morales residtes nal | S2: Equipo médico
A3: Asistencia Legal | B3: ADMINISTRACION N23 | C3: GASTOS DE ADMINISTRACIÓN | D3: COMERCIAL | G3: 344.82 | L3: 01/Feb/2026 | M3: Diario | N3: 34 | O3: Servicios administrativos
A4: Uniformes | B4: ALBERTO SANCHEZ BENAVIDES | C4: GASTOS DE ADMINISTRACIÓN | D4: OTROS | G4: 830 | L4: 01/Feb/2026 | M4: Diario | N4: 39 | O4: Uniformes
A5: Uniformes | B5: ALBERTO SANCHEZ BENAVIDES | C5: GASTOS DE ADMINISTRACIÓN | D5: OTROS | G5: 4718 | L5: 01/Feb/2026 | M5: Diario | N5: 39 | O5: Uniformes
A6: Uniformes | B6: ALBERTO SANCHEZ BENAVIDES | C6: GASTOS DE ADMINISTRACIÓN | D6: OTROS | G6: 10518 | L6: 01/Feb/2026 | M6: Diario | N6: 39 | O6: Uniformes
A7: Otros gastos generales | B7: ALL PHARMA | C7: GASTOS DE ADMINISTRACIÓN | D7: RH | G7: 270.98 | L7: 01/Feb/2026 | M7: Diario | N7: 25 | O7: Insumos para control de incendios
A8: Amortizacion acumulada de Software | B8: AMORTIZACION | C8: GASTOS DE ADMINISTRACIÓN | D8: FINANZAS | G8: 51069.485 | L8: 01/Feb/2026 | M8: Diario | N8: 502 | O8: Amortización acumulada de Software
A9: Amortizacion acumulada de Software | B9: AMORTIZACION | C9: COGS | D9: OPERACIONES | G9: 51069.485 | L9: 01/Feb/2026 | M9: Diario | N9: 502
A10: Arrendamiento a pers fisicas residtes nal | B10: ANGEL OROSCO ANGELES | C10: POR CLASIFICAR | D10: OTROS | G10: 17285.92 | L10: 01/Feb/2026 | M10: Diario | N10: 31 | O10: Papelería y artículos de oficina
A11: Arrendamiento a pers fisicas residtes nal | B11: ANGEL OROSCO ANGELES | C11: POR CLASIFICAR | D11: OTROS | G11: 22480.9 | L11: 01/Feb/2026 | M11: Diario | N11: 31 | O11: Papelería y artículos de oficina
A12: Mantenimiento y conservacion | B12: ARMANDO HERRERA VELAZQUEZ | C12: GASTOS DE ADMINISTRACIÓN | D12: BRAND BUILDING | G12: 102.80985 | L12: 01/Feb/2026 | M12: Diario | N12: 29 | O12: Mantenimiento y conservación
A13: Mantenimiento y conservacion | B13: ARMANDO HERRERA VELAZQUEZ | C13: GASTOS DE ADMINISTRACIÓN | D13: COMERCIAL | G13: 219.63923
A14: Mantenimiento y conservacion | B14: ARMANDO HERRERA VELAZQUEZ | C14: GASTOS DE ADMINISTRACIÓN | D14: DIRECTIVO | G14: 74.770803
A15: Mantenimiento y conservacion | B15: ARMANDO HERRERA VELAZQUEZ | C15: GASTOS DE ADMINISTRACIÓN | D15: FINANZAS | G15: 98.136679
A16: Mantenimiento y conservacion | B16: ARMANDO HERRERA VELAZQUEZ | C16: COGS | D16: OPERACIONES | G16: 1453.3575
A17: Mantenimiento y conservacion | B17: ARMANDO HERRERA VELAZQUEZ | C17: GASTOS DE ADMINISTRACIÓN | D17: RH | G17: 74.770803
A18: Mantenimiento y conservacion | B18: ARMANDO HERRERA VELAZQUEZ | C18: GASTOS DE ADMINISTRACIÓN | D18: TÉCNICO | G18: 537.41515
A19: Otros gastos generales | B19: ARRENDADORA HMS | C19: GASTOS DE ADMINISTRACIÓN | D19: OTROS | G19: 8900 | L19: 01/Feb/2026 | M19: Diario | N19: 21 | O19: Cuotas y suscripciones
A20: Gestoría | B20: ARTURO RAMSES CONTRERAS TORRES | C20: COGS | D20: OPERACIONES | G20: 56473.56 | L20: 01/Feb/2026 | M20: Diario | N20: 19 | O20: Capacitaciones
A21: Transportación terrestre | B21: AUTOMOVILES PRO SNOP | C21: COGS | D21: OPERACIONES | G21: 341293.1 | L21: 01/Feb/2026 | M21: Diario | N21: 187 | O21: Arrendamiento a pers morales residtes nal
A22: Transportación terrestre | B22: AUTOMOVILES PRO SNOP | C22: COGS | D22: OPERACIONES | G22: 168490 | L22: 27/Feb/2026 | M22: Egresos | N22: 258 | O22: GASTOS NO DEDUCIBLES
A23: OTROS EGRESOS FINAN | B23: BANCO MONEX S.A. INSTITUCION DE BANCA MULTIPLE, MONEX GRUPO FINANCIERO | C23: OTROS Facturación / GASTOS | D23: LAE | G23: 7500 | L23: 01/Feb/2026 | M23: Diario | N23: 34 | O23: Servicios administrativos
A24: Otros gastos generales | B24: BANCO MONEX S.A. INSTITUCION DE BANCA MULTIPLE, MONEX GRUPO FINANCIERO | C24: GASTOS DE ADMINISTRACIÓN | D24: FINANZAS | G24: 140000 | L24: 01/Feb/2026 | M24: Diario | N24: 34 | O24: Servicios administrativos
A25: Insumos para cursos | B25: BEATRIZ IRENE MEDELLIN ROSALES | C25: COGS | D25: OPERACIONES | G25: 2160 | L25: 01/Feb/2026 | M25: Diario | N25: 27 | O25: Insumos para cursos
A26: Viaticos y gastos de viaje | B26: BELANEA MEXICO | C26: GASTOS DE ADMINISTRACIÓN | D26: TÉCNICO | F26: Arturo Retana | G26: 129.31 | L26: 01/Feb/2026 | M26: Diario | N26: 37 | O26: Teléfono, internet
A27: Otros gastos generales | B27: BEPENSA LEASING | C27: GASTOS DE ADMINISTRACIÓN | D27: OTROS | G27: 114992.67 | L27: 01/Feb/2026 | M27: Diario | N27: 18 | O27: Arrendamiento a pers morales residtes nal
A28: Otros gastos generales | B28: BEPENSA LEASING | C28: GASTOS DE ADMINISTRACIÓN | D28: OTROS | G28: 0.01 | L28: 01/Feb/2026 | M28: Egresos | N28: 1 | O28: GASTOS NO DEDUCIBLES
A29: Viaticos y gastos de viaje | B29: BOLETOS DE AVION | C29: COGS | G29: 62245.98 | L29: 01/Feb/2026 | M29: Diario | N29: 1 | O29: Boletos de Avión
A30: Insumos para cursos | B30: BOXES & MORE MJ24 | C30: COGS | D30: OPERACIONES | G30: 2094.93 | L30: 01/Feb/2026 | M30: Diario | N30: 28 | O30: Limpieza
A31: Dictamenes | B31: BRENDA ELIZABETH REYES ROMERO | C31: COGS | D31: OPERACIONES | G31: 9500 | L31: 01/Feb/2026 | M31: Diario | N31: 23 | O31: Dictamenes
A32: Sueldos y salarios | B32: BRYTALAR CONSULTORES EN INGENIERIA Y OBRAS | G32: 4613.53 | L32: 01/Feb/2026 | M32: Diario | N32: 23 | O32: Dictamenes
A33: Sueldos y salarios | B33: BRYTALAR CONSULTORES EN INGENIERIA Y OBRAS | G33: 4619.48 | L33: 01/Feb/2026 | M33: Diario | N33: 23 | O33: Dictamenes
A34: Sueldos y salarios | B34: BRYTALAR CONSULTORES EN INGENIERIA Y OBRAS | G34: 4619.48 | L34: 01/Feb/2026 | M34: Diario | N34: 23 | O34: Dictamenes
A35: Sueldos y salarios | B35: BRYTALAR CONSULTORES EN INGENIERIA Y OBRAS | G35: 4619.48 | L35: 01/Feb/2026 | M35: Diario | N35: 23 | O35: Dictamenes
A36: Sueldos y salarios | B36: BRYTALAR CONSULTORES EN INGENIERIA Y OBRAS | G36: 79715.31 | L36: 01/Feb/2026 | M36: Diario | N36: 23 | O36: Dictamenes
A37: Sueldos y salarios | B37: BRYTALAR CONSULTORES EN INGENIERIA Y OBRAS | G37: 81582.86 | L37: 01/Feb/2026 | M37: Diario | N37: 23 | O37: Dictamenes
A38: Honorarios a personas fis residentes nal | B38: CAMSA SOLUCIONES FISCALES | C38: GASTOS DE ADMINISTRACIÓN | D38: FINANZAS | G38: 21340.52 | L38: 01/Feb/2026 | M38: Diario | N38: 33 | O38: Servicios administrativos
A39: Comisiones bancarias | B39: CAPITALMINT ADM | C39: GASTOS DE ADMINISTRACIÓN | D39: FINANZAS | G39: 187500 | L39: 01/Feb/2026 | M39: Diario | N39: 24 | O39: GESTION DE EVENTOS
A40: Viaticos y gastos de viaje | B40: CASETAS | C40: COGS | G40: 44230.46 | L40: 01/Feb/2026 | M40: Diario | N40: 2 | O40: Casetas y estacionamientos
A41: Combustibles y lubricantes | B41: COMBUSTIBLE | C41: COGS | D41: OPERACIONES | G41: =18280.59/2 -> 9140.295 | L41: 01/Feb/2026 | M41: Diario | N41: 3 | O41: Combustibles y lubricantes
A42: Combustibles y lubricantes | B42: COMBUSTIBLE | C42: COGS | D42: TÉCNICO | G42: =18280.59/2 -> 9140.295 | L42: 01/Feb/2026 | M42: Diario | N42: 3 | O42: Combustibles y lubricantes
A43: Combustibles y lubricantes | B43: COMBUSTIBLE | C43: COGS | D43: OPERACIONES | G43: =1710.79/2 -> 855.395 | L43: 01/Feb/2026 | M43: Diario | N43: 186 | O43: Combustibles y lubricantes
A44: Combustibles y lubricantes | B44: COMBUSTIBLE | C44: COGS | D44: TÉCNICO | G44: =1710.79/2 -> 855.395 | L44: 01/Feb/2026 | M44: Diario | N44: 186 | O44: Combustibles y lubricantes
A45: Comisiones bancarias | B45: COMISIONES BANCARIAS BBVA | C45: GASTOS DE ADMINISTRACIÓN | D45: FINANZAS | G45: 3724.01 | L45: 06/Feb/2026 | M45: Egresos | N45: 182 | O45: Comisiones Bancarias
A46: Comisiones bancarias | B46: COMISIONES BANCARIAS USD | C46: GASTOS DE ADMINISTRACIÓN | D46: FINANZAS | G46: 516.48 | L46: 24/Feb/2026 | M46: Egresos | N46: 223 | O46: Comisiones Bancarias
A47: Sueldos y salarios | B47: CONSORCIO EMPRENDEDOR LA FINCA | G47: 5480.62 | L47: 01/Feb/2026 | M47: Diario | N47: 33 | O47: Servicios administrativos
A48: Sueldos y salarios | B48: CONSORCIO EMPRENDEDOR LA FINCA | G48: 21000 | L48: 01/Feb/2026 | M48: Diario | N48: 33 | O48: Servicios administrativos
A49: Sueldos y salarios | B49: CONSORCIO EMPRENDEDOR LA FINCA | G49: 44284.8 | L49: 01/Feb/2026 | M49: Diario | N49: 33 | O49: Servicios administrativos
A50: Sueldos y salarios | B50: CONSORCIO EMPRENDEDOR LA FINCA | G50: 65767.87 | L50: 01/Feb/2026 | M50: Diario | N50: 33 | O50: Servicios administrativos
A51: Sueldos y salarios | B51: CONSORCIO EMPRENDEDOR LA FINCA | G51: 106653.61 | L51: 01/Feb/2026 | M51: Diario | N51: 33 | O51: Servicios administrativos
A52: Sueldos y salarios | B52: CONSORCIO EMPRENDEDOR LA FINCA | G52: 125202.91 | L52: 01/Feb/2026 | M52: Diario | N52: 33 | O52: Servicios administrativos
A53: Sueldos y salarios | B53: CONSORCIO EMPRENDEDOR LA FINCA | G53: 282920.87 | L53: 01/Feb/2026 | M53: Diario | N53: 33 | O53: Servicios administrativos
A54: Sueldos y salarios | B54: CONSORCIO EMPRENDEDOR LA FINCA | G54: 307996.97 | L54: 01/Feb/2026 | M54: Diario | N54: 33 | O54: Servicios administrativos
A55: Viaticos y gastos de viaje | B55: CONSUMO | C55: COGS | G55: 252069.36 | L55: 01/Feb/2026 | M55: Diario | N55: 4 | O55: Consumos
A56: Viaticos y gastos de viaje | B56: CONSUMOS | C56: COGS | G56: 7844.47 | L56: 01/Feb/2026 | M56: Diario | N56: 41 | O56: Consumos
A57: Viaticos y gastos de viaje | B57: CONSUMOS | C57: COGS | G57: 12561.43 | L57: 01/Feb/2026 | M57: Diario | N57: 185 | O57: Consumos
A58: Otros gastos generales | B58: CORPORATIVO AQUA QUERETARO | C58: GASTOS DE ADMINISTRACIÓN | D58: OTROS | G58: 215517.24 | L58: 01/Feb/2026 | M58: Diario | N58: 21 | O58: Cuotas y suscripciones
A59: Propaganda y publicidad | B59: CREATIVOS POR NATURALEZA | C59: GASTOS DE ADMINISTRACIÓN | D59: BRAND BUILDING | G59: 29000 | L59: 01/Feb/2026 | M59: Diario | N59: 33 | O59: Servicios administrativos
A60: SIN CLASIFICAR | B60: CUOTAS | G60: 107.76 | L60: 01/Feb/2026 | M60: Diario | N60: 5 | O60: Cuotas y suscripciones
A61: Estimulo al personal | B61: DEALSTAR | C61: GASTOS DE ADMINISTRACIÓN | D61: RH | G61: 20166.66 | L61: 01/Feb/2026 | M61: Diario | N61: 22 | O61: CUPONSTAR
A62: Estimulo al personal | B62: DEALSTAR | C62: GASTOS DE ADMINISTRACIÓN | D62: RH | G62: 3713 | L62: 01/Feb/2026 | M62: Diario | N62: 22 | O62: CUPONSTAR
A63: Arrendamiento a pers morales residtes nal | B63: DELL LEASING MEXICO | C63: TÉCNICO | D63: GASTOS DE ADMINISTRACIÓN | G63: 24583.378 | L63: 01/Feb/2026 | M63: Diario | N63: 18 | O63: Arrendamiento a pers morales residtes nal
A64: Arrendamiento a pers morales residtes nal | B64: DELL LEASING MEXICO | C64: RH | D64: GASTOS DE ADMINISTRACIÓN | G64: 1755.9556 | L64: 01/Feb/2026 | M64: Diario | N64: 18 | O64: Arrendamiento a pers morales residtes nal
A65: Arrendamiento a pers morales residtes nal | B65: DELL LEASING MEXICO | C65: OPERACIONES | D65: COGS | G65: 33363.156 | L65: 01/Feb/2026 | M65: Diario | N65: 18 | O65: Arrendamiento a pers morales residtes nal
A66: Arrendamiento a pers morales residtes nal | B66: DELL LEASING MEXICO | C66: FINANZAS | D66: GASTOS DE ADMINISTRACIÓN | G66: 4682.5481 | L66: 01/Feb/2026 | M66: Diario | N66: 18 | O66: Arrendamiento a pers morales residtes nal
A67: Arrendamiento a pers morales residtes nal | B67: DELL LEASING MEXICO | C67: BRAND BUILDING | D67: GASTOS DE ADMINISTRACIÓN | G67: 2633.9333 | L67: 01/Feb/2026 | M67: Diario | N67: 18 | O67: Arrendamiento a pers morales residtes nal
A68: Arrendamiento a pers morales residtes nal | B68: DELL LEASING MEXICO | C68: COMERCIAL | D68: GASTOS DE ADMINISTRACIÓN | G68: 9365.0963 | L68: 01/Feb/2026 | M68: Diario | N68: 18 | O68: Arrendamiento a pers morales residtes nal
A69: Arrendamiento a pers morales residtes nal | B69: DELL LEASING MEXICO | C69: DIRECTIVO | D69: GASTOS DE ADMINISTRACIÓN | G69: 2633.9333 | L69: 01/Feb/2026 | M69: Diario | N69: 18 | O69: Arrendamiento a pers morales residtes nal
A70: Depreciacion de maquinaria y equipo | B70: DEPRECIACIONES | C70: GASTOS DE ADMINISTRACIÓN | D70: OTROS | G70: 6213.65 | L70: 01/Feb/2026 | M70: Diario | N70: 502 | O70: Depreciación de maquinaria y equipo
A71: Depr de autom, autob, camiones, tractoc | B71: DEPRECIACIONES | C71: COGS | D71: OPERACIONES | G71: 791.67 | L71: 01/Feb/2026 | M71: Diario | N71: 502 | O71: Depr de autom, autob, camiones, tractoc
A72: Depreciacion de mobiliario y eq de ofic | B72: DEPRECIACIONES | C72: GASTOS DE ADMINISTRACIÓN | D72: BRAND BUILDING | G72: 375.32602
A73: Depreciacion de mobiliario y eq de ofic | B73: DEPRECIACIONES | C73: GASTOS DE ADMINISTRACIÓN | D73: COMERCIAL | G73: 801.83286
A74: Depreciacion de mobiliario y eq de ofic | B74: DEPRECIACIONES | C74: GASTOS DE ADMINISTRACIÓN | D74: DIRECTIVO | G74: 272.96438
A75: Depreciacion de mobiliario y eq de ofic | B75: DEPRECIACIONES | C75: GASTOS DE ADMINISTRACIÓN | D75: FINANZAS | G75: 358.26575
A76: Depreciacion de mobiliario y eq de ofic | B76: DEPRECIACIONES | C76: COGS | D76: OPERACIONES | G76: 5305.7451
A77: Depreciacion de mobiliario y eq de ofic | B77: DEPRECIACIONES | C77: GASTOS DE ADMINISTRACIÓN | D77: RH | G77: 272.96438
A78: Depreciacion de mobiliario y eq de ofic | B78: DEPRECIACIONES | C78: GASTOS DE ADMINISTRACIÓN | D78: TÉCNICO | G78: 1961.9315
A79: Depreciacion de equipo de computo | B79: DEPRECIACIONES | C79: GASTOS DE ADMINISTRACIÓN | D79: BRAND BUILDING | G79: 1312.2988
A80: Depreciacion de equipo de computo | B80: DEPRECIACIONES | C80: GASTOS DE ADMINISTRACIÓN | D80: COMERCIAL | G80: 2803.5474
A81: Depreciacion de equipo de computo | B81: DEPRECIACIONES | C81: GASTOS DE ADMINISTRACIÓN | D81: DIRECTIVO | G81: 954.39912
A82: Depreciacion de equipo de computo | B82: DEPRECIACIONES | C82: GASTOS DE ADMINISTRACIÓN | D82: FINANZAS | G82: 1252.6489
A83: Depreciacion de equipo de computo | B83: DEPRECIACIONES | C83: COGS | D83: OPERACIONES | G83: 18551.133
A84: Depreciacion de equipo de computo | B84: DEPRECIACIONES | C84: GASTOS DE ADMINISTRACIÓN | D84: RH | G84: 954.39912 | L84: 01/Feb/2026 | M84: Diario | N84: 502 | O84: Depreciación de mobiliario y eq de ofic
A85: Depreciacion de equipo de computo | B85: DEPRECIACIONES | C85: GASTOS DE ADMINISTRACIÓN | D85: TÉCNICO | G85: 6859.7437 | L85: 01/Feb/2026 | M85: Diario | N85: 502 | O85: Depreciación de equipo de cómputo
A86: Depreciacion de otros activos fijos | B86: DEPRECIACIONES | C86: GASTOS DE ADMINISTRACIÓN | D86: OTROS | G86: 5539.44 | L86: 01/Feb/2026 | M86: Diario | N86: 502 | O86: Depreciación de otros activos fijos
A87: Depreciacion de otros activos fijos | B87: DEPRECIACIONES | C87: GASTOS DE ADMINISTRACIÓN | D87: OTROS | G87: 5828.89 | L87: 01/Feb/2026 | M87: Diario | N87: 502 | O87: Depreciación de instalación
A88: Devolución | B88: DEVOLUCION | G88: 1067.93 | L88: 09/Feb/2026 | M88: Egresos | N88: 220 | O88: Pérdida cambiaria
A89: Mensajería | B89: DHL EXPRESS MEXICO | C89: COGS | D89: OPERACIONES | G89: 6043.26 | L89: 01/Feb/2026 | M89: Diario | N89: 30 | O89: Mensajería
A90: Mensajería | B90: DHL EXPRESS MEXICO | C90: COGS | D90: OPERACIONES | G90: 9498.12 | L90: 01/Feb/2026 | M90: Diario | N90: 30 | O90: Mensajería
A91: Mensajería | B91: DHL EXPRESS MEXICO | C91: COGS | D91: OPERACIONES | G91: 22068.81 | L91: 01/Feb/2026 | M91: Diario | N91: 30 | O91: Mensajería
A92: Mensajería | B92: DHL EXPRESS MEXICO | C92: COGS | D92: OPERACIONES | G92: 17272.86 | L92: 01/Feb/2026 | M92: Diario | N92: 188 | O92: Mensajería
A93: Dictamenes | B93: DIONNE SHAMIRA SOTO CORRALES | C93: COGS | D93: OPERACIONES | G93: 7000 | L93: 01/Feb/2026 | M93: Diario | N93: 23 | O93: Dictamenes
A94: Dictamenes | B94: DISEÑO EDIFICACION Y ASESORIA CIVIL | C94: COGS | D94: OPERACIONES | G94: 12000 | L94: 01/Feb/2026 | M94: Diario | N94: 23 | O94: Dictamenes
A95: Papeleria y articulos de oficina | B95: DISTRIBUIDORA NEGRETE QRO | C95: COGS | D95: OPERACIONES | G95: 2500 | L95: 01/Feb/2026 | M95: Diario | N95: 18 | O95: Arrendamiento a pers morales residtes nal
A96: Papeleria y articulos de oficina | B96: DISTRIBUIDORA NEGRETE QRO | C96: COGS | D96: OPERACIONES | G96: 6859.6 | L96: 01/Feb/2026 | M96: Diario | N96: 18 | O96: Arrendamiento a pers morales residtes nal
A97: Papeleria y articulos de oficina | B97: DISTRIBUIDORA NEGRETE QRO | C97: COGS | D97: OPERACIONES | G97: 13195.7 | L97: 01/Feb/2026 | M97: Diario | N97: 187 | O97: Arrendamiento a pers morales residtes nal
A98: Telefono, internet | B98: E-NGENIUM INFRAESTRUCTURA | C98: GASTOS DE ADMINISTRACIÓN | D98: OTROS | G98: 12232.83 | L98: 01/Feb/2026 | M98: Diario | N98: 21 | O98: Cuotas y suscripciones
A99: Telefono, internet | B99: E-NGENIUM INFRAESTRUCTURA | C99: GASTOS DE ADMINISTRACIÓN | D99: OTROS | G99: 69860 | L99: 01/Feb/2026 | M99: Diario | N99: 21 | O99: Cuotas y suscripciones
A100: Honorarios a personas fis residentes nal | B100: EDGAR ALONSO AGUILAR NEGRETE | C100: GASTOS DE ADMINISTRACIÓN | D100: TÉCNICO | G100: 1630.82 | L100: 01/Feb/2026 | M100: Diario | N100: 21 | O100: Cuotas y suscripciones
...

Sheet DF_LIMPIO3
A1: CATEGORIA_NETSUITE | B1: Concepto | C1: IS | D1: ÁREA | E1: ZONA PPTO | F1: EMPLEADO | G1: MONTO | H1: PERIODO | I1: AREA | J1: ZONA | K1: PCT_POND | L1: Fecha | M1: Tipo | N1: Número | O1: Clasf Efs | P1: ID SGN | Q1: PUESTO | R1: PAGADORA | S1: Columna 19 | T1: Columna 20 | U1: Columna 21 | V1: Columna 22 | W1: Columna 23 | X1: Columna 24 | Y1: Columna 25
A2: Papeleria y articulos de oficina | B2: ABASTECEDORA DE OFICINAS | C2: COGS | D2: OPERACIONES | G2: 2771.61 | L2: 01/Mar/2026 | M2: Diario | N2: 241 | O2: Papelería y artículos de oficina
A3: Otros gastos generales | B3: ACTIVE LEASING | C3: GASTOS DE ADMINISTRACIÓN | D3: COMERCIAL | G3: 7343.97 | L3: 01/Mar/2026 | M3: Diario | N3: 228 | O3: Arrendamiento a pers morales residtes nal
A4: Asistencia Legal | B4: ADMINISTRACION N23 | C4: GASTOS DE ADMINISTRACIÓN | D4: COMERCIAL | G4: 1000 | L4: 06/Mar/2026 | M4: Egresos | N4: 61 | O4: GASTOS NO DEDUCIBLES
A5: Asistencia Legal | B5: ADMINISTRACION N23 | C5: GASTOS DE ADMINISTRACIÓN | D5: COMERCIAL | G5: 352 | L5: 06/Mar/2026 | M5: Egresos | N5: 62 | O5: GASTOS NO DEDUCIBLES
A6: Asistencia Legal | B6: ADMINISTRACION N23 | C6: GASTOS DE ADMINISTRACIÓN | D6: COMERCIAL | G6: 344.82 | L6: 01/Mar/2026 | M6: Diario | N6: 229 | O6: Asistencia Legal
A7: Asistencia Legal | B7: ADMINISTRACION N23 | C7: GASTOS DE ADMINISTRACIÓN | D7: COMERCIAL | G7: 10000 | L7: 01/Mar/2026 | M7: Diario | N7: 229 | O7: Asistencia Legal
A8: Asistencia Legal | B8: ADMINISTRACION N23 | C8: GASTOS DE ADMINISTRACIÓN | D8: COMERCIAL | G8: 21893.46 | L8: 01/Mar/2026 | M8: Diario | N8: 229 | O8: Asistencia Legal
A9: Uniformes | B9: ALBERTO SANCHEZ BENAVIDES | C9: GASTOS DE ADMINISTRACIÓN | D9: OTROS | G9: 4150 | L9: 01/Mar/2026 | M9: Diario | N9: 241 | O9: Papelería y artículos de oficina
A10: Amortizacion acumulada de Software | B10: AMORTIZACION | C10: GASTOS DE ADMINISTRACIÓN | D10: FINANZAS | G10: 51889.725 | L10: 01/Mar/2026 | M10: Diario | N10: 401 | O10: Amortización acumulada de Software
A11: Amortizacion acumulada de Software | B11: AMORTIZACION | C11: COGS | D11: OPERACIONES | G11: 51889.725 | L11: 01/Mar/2026 | M11: Diario | N11: 401
A12: SIN CLASIFICAR | B12: ANA LUCIA PEREZ MENDOZA | G12: 1468 | L12: 01/Mar/2026 | M12: Diario | N12: 241 | O12: Papelería y artículos de oficina
A13: Arrendamiento a pers fisicas residtes nal | B13: ANGEL OROSCO ANGELES | C13: POR CLASIFICAR | D13: OTROS | G13: 3092.07 | L13: 01/Mar/2026 | M13: Diario | N13: 228 | O13: Arrendamiento a pers físicas residtes nal
A14: Arrendamiento a pers fisicas residtes nal | B14: ANGEL OROSCO ANGELES | C14: POR CLASIFICAR | D14: OTROS | G14: 49042.22 | L14: 01/Mar/2026 | M14: Diario | N14: 228 | O14: Arrendamiento a pers físicas residtes nal
A15: Arrendamiento a pers fisicas residtes nal | B15: ANGEL OROSCO ANGELES | C15: POR CLASIFICAR | D15: OTROS | G15: 3756.68 | L15: 01/Mar/2026 | M15: Diario | N15: 228 | O15: Arrendamiento a pers morales residtes nal
A16: Arrendamiento a pers fisicas residtes nal | B16: ANGEL OROSCO ANGELES | C16: POR CLASIFICAR | D16: OTROS | G16: 57369.14 | L16: 01/Mar/2026 | M16: Diario | N16: 228 | O16: Arrendamiento a pers morales residtes nal
A17: SIN CLASIFICAR | B17: ARMANDO RIVERA LOPEZ | G17: 1500 | L17: 01/Mar/2026 | M17: Diario | N17: 243 | O17: Servicios administrativos
A18: Otros gastos generales | B18: ARRENDADORA HMS | C18: GASTOS DE ADMINISTRACIÓN | D18: OTROS | G18: 8900 | L18: 01/Mar/2026 | M18: Diario | N18: 228 | O18: Arrendamiento a pers morales residtes nal
A19: SIN CLASIFICAR | B19: ARTICULOS DE ELECTRINICOS | G19: 1807.76 | L19: 01/Mar/2026 | M19: Diario | N19: 213 | O19: Mantenimiento y conservación
A20: SIN CLASIFICAR | B20: ARTURO RAMSES CONTRERAS TORRES | G20: 56473.56 | L20: 01/Mar/2026 | M20: Diario | N20: 230 | O20: Capacitaciones
A21: SIN CLASIFICAR | B21: AUTOMOVILES ESCANDINAVOS DEL CENTRO | G21: 28630.8 | L21: 01/Mar/2026 | M21: Diario | N21: 239 | O21: Mantenimiento y conservación
A22: Otros gastos generales | B22: BEPENSA LEASING | C22: GASTOS DE ADMINISTRACIÓN | D22: OTROS | G22: 114992.67 | L22: 01/Mar/2026 | M22: Diario | N22: 228 | O22: Arrendamiento a pers morales residtes nal
A23: Viaticos y gastos de viaje | B23: BOLETOS DE AVION | C23: COGS | G23: 246928.64 | L23: 01/Mar/2026 | M23: Diario | N23: 214 | O23: Boletos de Avión
A24: Gastos no deducibles | B24: BRENDA ELIZABETH REYES ROMERO | C24: OTROS INGRESOS / GASTOS | G24: 8500 | L24: 01/Mar/2026 | M24: Diario | N24: 234 | O24: Dictamenes
A25: Sueldos y salarios | B25: BRYTALAR CONSULTORES EN INGENIERIA Y OBRAS | G25: 4596.31 | L25: 01/Mar/2026 | M25: Diario | N25: 243 | O25: Servicios administrativos
A26: Sueldos y salarios | B26: BRYTALAR CONSULTORES EN INGENIERIA Y OBRAS | G26: 4598.08 | L26: 01/Mar/2026 | M26: Diario | N26: 243 | O26: Servicios administrativos
A27: Sueldos y salarios | B27: BRYTALAR CONSULTORES EN INGENIERIA Y OBRAS | G27: 4852.41 | L27: 01/Mar/2026 | M27: Diario | N27: 243 | O27: Servicios administrativos
A28: Sueldos y salarios | B28: BRYTALAR CONSULTORES EN INGENIERIA Y OBRAS | G28: 4852.41 | L28: 01/Mar/2026 | M28: Diario | N28: 243 | O28: Servicios administrativos
A29: Sueldos y salarios | B29: BRYTALAR CONSULTORES EN INGENIERIA Y OBRAS | G29: 6378.41 | L29: 01/Mar/2026 | M29: Diario | N29: 243 | O29: Servicios administrativos
A30: Sueldos y salarios | B30: BRYTALAR CONSULTORES EN INGENIERIA Y OBRAS | G30: 80776.28 | L30: 01/Mar/2026 | M30: Diario | N30: 243 | O30: Servicios administrativos
A31: Sueldos y salarios | B31: BRYTALAR CONSULTORES EN INGENIERIA Y OBRAS | G31: 81281.09 | L31: 01/Mar/2026 | M31: Diario | N31: 243 | O31: Servicios administrativos
A32: Honorarios a personas fis residentes nal | B32: CAMSA SOLUCIONES FISCALES | C32: GASTOS DE ADMINISTRACIÓN | D32: FINANZAS | G32: 11200 | L32: 01/Mar/2026 | M32: Diario | N32: 243 | O32: Servicios administrativos
A33: Honorarios a personas fis residentes nal | B33: CAMSA SOLUCIONES FISCALES | C33: GASTOS DE ADMINISTRACIÓN | D33: FINANZAS | G33: 21340.52 | L33: 01/Mar/2026 | M33: Diario | N33: 243 | O33: Servicios administrativos
A34: SIN CLASIFICAR | B34: CAPACITACIONES | G34: 9852 | L34: 01/Mar/2026 | M34: Diario | N34: 215 | O34: Capacitaciones
A35: SIN CLASIFICAR | B35: CARLOS GONZALEZ FLORES | G35: 6000 | L35: 01/Mar/2026 | M35: Diario | N35: 234 | O35: Dictamenes
A36: SIN CLASIFICAR | B36: CARLOS OBRYAN RAMIREZ GARZA | G36: 7700 | L36: 01/Mar/2026 | M36: Diario | N36: 234 | O36: Dictamenes
A37: Viaticos y gastos de viaje | B37: CASETAS | C37: COGS | G37: 66273.68 | L37: 01/Mar/2026 | M37: Diario | N37: 216 | O37: Casetas y estacionamientos
A38: SIN CLASIFICAR | B38: CESAR JAVIER RODRIGUEZ MONTIEL | G38: 13600 | L38: 01/Mar/2026 | M38: Diario | N38: 234 | O38: Dictamenes
A39: Combustibles y lubricantes | B39: COMBUSTIBLE | C39: COGS | D39: TÉCNICO | G39: =54349.86/2 -> 27174.93 | L39: 01/Mar/2026 | M39: Diario | N39: 217 | O39: Combustibles y lubricantes
A40: Combustibles y lubricantes | B40: COMBUSTIBLE | C40: COGS | D40: OPERACIONES | G40: =54349.86/2 -> 27174.93 | L40: 01/Mar/2026 | M40: Diario | N40: 217 | O40: Combustibles y lubricantes
A41: SIN CLASIFICAR | B41: COMISIONES BANCARIAS BANORTE | G41: 64053.37 | L41: 05/Mar/2026 | M41: Egresos | N41: 57 | O41: Intereses a cargo bancario nacional
A42: SIN CLASIFICAR | B42: COMISIONES BANCARIAS BANORTE | G42: 805 | L42: 05/Mar/2026 | M42: Egresos | N42: 57 | O42: Comisiones Bancarias
A43: Comisiones bancarias | B43: COMISIONES BANCARIAS BBVA | C43: GASTOS DE ADMINISTRACIÓN | D43: FINANZAS | G43: 2899.6 | L43: 05/Mar/2026 | M43: Egresos | N43: 226 | O43: Comisiones Bancarias
A44: Sueldos y salarios | B44: CONSORCIO EMPRENDEDOR LA FINCA | G44: 3412.5 | L44: 01/Mar/2026 | M44: Diario | N44: 243 | O44: Servicios administrativos
A45: Sueldos y salarios | B45: CONSORCIO EMPRENDEDOR LA FINCA | G45: 7312.39 | L45: 01/Mar/2026 | M45: Diario | N45: 243 | O45: Servicios administrativos
A46: Sueldos y salarios | B46: CONSORCIO EMPRENDEDOR LA FINCA | G46: 33932.83 | L46: 01/Mar/2026 | M46: Diario | N46: 243 | O46: Servicios administrativos
A47: Sueldos y salarios | B47: CONSORCIO EMPRENDEDOR LA FINCA | G47: 34075.3 | L47: 01/Mar/2026 | M47: Diario | N47: 243 | O47: Servicios administrativos
A48: Sueldos y salarios | B48: CONSORCIO EMPRENDEDOR LA FINCA | G48: 35837.16 | L48: 01/Mar/2026 | M48: Diario | N48: 243 | O48: Servicios administrativos
A49: Sueldos y salarios | B49: CONSORCIO EMPRENDEDOR LA FINCA | G49: 37800 | L49: 01/Mar/2026 | M49: Diario | N49: 243 | O49: Servicios administrativos
A50: Sueldos y salarios | B50: CONSORCIO EMPRENDEDOR LA FINCA | G50: 40110 | L50: 01/Mar/2026 | M50: Diario | N50: 243 | O50: Servicios administrativos
A51: Sueldos y salarios | B51: CONSORCIO EMPRENDEDOR LA FINCA | G51: 91891.59 | L51: 01/Mar/2026 | M51: Diario | N51: 243 | O51: Servicios administrativos
A52: Sueldos y salarios | B52: CONSORCIO EMPRENDEDOR LA FINCA | G52: 109076.84 | L52: 01/Mar/2026 | M52: Diario | N52: 243 | O52: Servicios administrativos
A53: Sueldos y salarios | B53: CONSORCIO EMPRENDEDOR LA FINCA | G53: 279292.67 | L53: 01/Mar/2026 | M53: Diario | N53: 243 | O53: Servicios administrativos
A54: Sueldos y salarios | B54: CONSORCIO EMPRENDEDOR LA FINCA | G54: 294407.25 | L54: 01/Mar/2026 | M54: Diario | N54: 243 | O54: Servicios administrativos
A55: Sueldos y salarios | B55: CONSORCIO EMPRENDEDOR LA FINCA | G55: 380493.75 | L55: 01/Mar/2026 | M55: Diario | N55: 243 | O55: Servicios administrativos
A56: SIN CLASIFICAR | B56: CONSULTORES EN EVALUACION DE NORMAS MEXICANAS | G56: 13000 | L56: 01/Mar/2026 | M56: Diario | N56: 234 | O56: Dictamenes
A57: Viaticos y gastos de viaje | B57: CONSUMOS | C57: COGS | G57: 398608.39 | L57: 01/Mar/2026 | M57: Diario | N57: 218 | O57: Consumos
A58: Viaticos y gastos de viaje | B58: CONSUMOS | C58: COGS | G58: 65520.29 | L58: 01/Mar/2026 | M58: Diario | N58: 248 | O58: Consumos
A59: SIN CLASIFICAR | B59: CORPORATIVO RIVERNEZ | G59: 2173.6 | L59: 01/Mar/2026 | M59: Diario | N59: 241 | O59: Papelería y artículos de oficina
A60: Propaganda y publicidad | B60: CREATIVOS POR NATURALEZA | C60: GASTOS DE ADMINISTRACIÓN | D60: BRAND BUILDING | G60: 29000 | L60: 01/Mar/2026 | M60: Diario | N60: 243 | O60: Servicios administrativos
A61: Cuotas y suscripciones | B61: CUOTAS Y SUSCRIPCIONES | C61: GASTOS DE ADMINISTRACIÓN | D61: OTROS | G61: 9633.08 | L61: 01/Mar/2026 | M61: Diario | N61: 219 | O61: Cuotas y suscripciones
A62: SIN CLASIFICAR | B62: CURSO DE PRIMEROS AUXILIOS | G62: 29174 | L62: 13/Mar/2026 | M62: Egresos | N62: 112 | O62: GASTOS NO DEDUCIBLES
A63: SIN CLASIFICAR | B63: CURSO DE PRIMEROS AUXILIOS | G63: 72550 | L63: 01/Mar/2026 | M63: Diario | N63: 230 | O63: Dictamenes
A64: SIN CLASIFICAR | B64: CURSO DE PRIMEROS AUXILIOS | G64: 72550 | L64: 01/Mar/2026 | M64: Diario | N64: 230 | O64: Capacitaciones
A65: SIN CLASIFICAR | B65: CURSO DE PRIMEROS AUXILIOS | G65: 72550 | L65: 01/Mar/2026 | M65: Diario | N65: 230 | O65: Capacitaciones
A66: SIN CLASIFICAR | B66: CURSO DE PRIMEROS AUXILIOS | G66: 72550 | L66: 01/Mar/2026 | M66: Diario | N66: 230 | O66: Capacitaciones
A67: SIN CLASIFICAR | B67: CURSO DE PRIMEROS AUXILIOS | G67: 265050 | L67: 01/Mar/2026 | M67: Diario | N67: 230 | O67: Capacitaciones
A68: SIN CLASIFICAR | B68: DANIEL GONZALO ACOSTA AGUIRRE | G68: 517.24 | L68: 01/Mar/2026 | M68: Diario | N68: 245 | O68: Uniformes
A69: Limpieza | B69: DAVID ULISES MIGUEL SANCHEZ OLIVARES | C69: GASTOS DE ADMINISTRACIÓN | D69: OTROS | G69: 11643.08 | L69: 01/Mar/2026 | M69: Diario | N69: 238 | O69: Limpieza
A70: SIN CLASIFICAR | B70: DEALSTAR | G70: 3713 | L70: 01/Mar/2026 | M70: Diario | N70: 233 | O70: CUPONSTAR
A71: Arrendamiento a pers morales residtes nal | B71: DELL LEASING MEXICO | C71: TÉCNICO | D71: GASTOS DE ADMINISTRACIÓN | G71: 16469.917 | L71: 01/Mar/2026 | M71: Diario | N71: 228 | O71: Arrendamiento a pers morales residtes nal
A72: Arrendamiento a pers morales residtes nal | B72: DELL LEASING MEXICO | C72: RH | D72: GASTOS DE ADMINISTRACIÓN | G72: 1176.4227 | L72: 01/Mar/2026 | M72: Diario | N72: 228 | O72: Arrendamiento a pers morales residtes nal
A73: Arrendamiento a pers morales residtes nal | B73: DELL LEASING MEXICO | C73: OPERACIONES | D73: COGS | G73: 22352.031 | L73: 01/Mar/2026 | M73: Diario | N73: 228 | O73: Arrendamiento a pers morales residtes nal
A74: Arrendamiento a pers morales residtes nal | B74: DELL LEASING MEXICO | C74: FINANZAS | D74: GASTOS DE ADMINISTRACIÓN | G74: 3137.1271 | L74: 01/Mar/2026 | M74: Diario | N74: 228 | O74: Arrendamiento a pers morales residtes nal
A75: Arrendamiento a pers morales residtes nal | B75: DELL LEASING MEXICO | C75: BRAND BUILDING | D75: GASTOS DE ADMINISTRACIÓN | G75: 1764.634 | L75: 01/Mar/2026 | M75: Diario | N75: 228 | O75: Arrendamiento a pers morales residtes nal
A76: Arrendamiento a pers morales residtes nal | B76: DELL LEASING MEXICO | C76: COMERCIAL | D76: GASTOS DE ADMINISTRACIÓN | G76: 6274.2542 | L76: 01/Mar/2026 | M76: Diario | N76: 228 | O76: Arrendamiento a pers morales residtes nal
A77: Arrendamiento a pers morales residtes nal | B77: DELL LEASING MEXICO | C77: DIRECTIVO | D77: GASTOS DE ADMINISTRACIÓN | G77: 1764.634 | L77: 01/Mar/2026 | M77: Diario | N77: 228 | O77: Arrendamiento a pers morales residtes nal
A78: Depreciacion de maquinaria y equipo | B78: DEPRECIACIONES | C78: GASTOS DE ADMINISTRACIÓN | D78: OTROS | G78: 6213.65 | L78: 01/Mar/2026 | M78: Diario | N78: 401 | O78: Depreciación de maquinaria y equipo
A79: Depr de autom, autob, camiones, tractoc | B79: DEPRECIACIONES | C79: COGS | D79: OPERACIONES | G79: 791.67 | L79: 01/Mar/2026 | M79: Diario | N79: 401 | O79: Depr de autom, autob, camiones, tractoc
A80: Depreciacion de mobiliario y eq de ofic | B80: DEPRECIACIONES | C80: GASTOS DE ADMINISTRACIÓN | D80: BRAND BUILDING | G80: 381.34431
A81: Depreciacion de mobiliario y eq de ofic | B81: DEPRECIACIONES | C81: GASTOS DE ADMINISTRACIÓN | D81: COMERCIAL | G81: 814.69011
A82: Depreciacion de mobiliario y eq de ofic | B82: DEPRECIACIONES | C82: GASTOS DE ADMINISTRACIÓN | D82: DIRECTIVO | G82: 277.34131
A83: Depreciacion de mobiliario y eq de ofic | B83: DEPRECIACIONES | C83: GASTOS DE ADMINISTRACIÓN | D83: FINANZAS | G83: 364.01047
A84: Depreciacion de mobiliario y eq de ofic | B84: DEPRECIACIONES | C84: COGS | D84: OPERACIONES | G84: 5390.8218
A85: Depreciacion de mobiliario y eq de ofic | B85: DEPRECIACIONES | C85: GASTOS DE ADMINISTRACIÓN | D85: RH | G85: 277.34131
A86: Depreciacion de mobiliario y eq de ofic | B86: DEPRECIACIONES | C86: GASTOS DE ADMINISTRACIÓN | D86: TÉCNICO | G86: 1993.3907
A87: Depreciacion de equipo de computo | B87: DEPRECIACIONES | C87: GASTOS DE ADMINISTRACIÓN | D87: BRAND BUILDING | G87: 1312.2988
A88: Depreciacion de equipo de computo | B88: DEPRECIACIONES | C88: GASTOS DE ADMINISTRACIÓN | D88: COMERCIAL | G88: 2803.5474
A89: Depreciacion de equipo de computo | B89: DEPRECIACIONES | C89: GASTOS DE ADMINISTRACIÓN | D89: DIRECTIVO | G89: 954.39912
A90: Depreciacion de equipo de computo | B90: DEPRECIACIONES | C90: GASTOS DE ADMINISTRACIÓN | D90: FINANZAS | G90: 1252.6489
A91: Depreciacion de equipo de computo | B91: DEPRECIACIONES | C91: COGS | D91: OPERACIONES | G91: 18551.133
A92: Depreciacion de equipo de computo | B92: DEPRECIACIONES | C92: GASTOS DE ADMINISTRACIÓN | D92: RH | G92: 954.39912 | L92: 01/Mar/2026 | M92: Diario | N92: 401 | O92: Depreciación de mobiliario y eq de ofic
A93: Depreciacion de equipo de computo | B93: DEPRECIACIONES | C93: GASTOS DE ADMINISTRACIÓN | D93: TÉCNICO | G93: 6859.7437 | L93: 01/Mar/2026 | M93: Diario | N93: 401 | O93: Depreciación de equipo de cómputo
A94: Depreciacion de otros activos fijos | B94: DEPRECIACIONES | C94: GASTOS DE ADMINISTRACIÓN | D94: OTROS | G94: 5539.44 | L94: 01/Mar/2026 | M94: Diario | N94: 401 | O94: Depreciación de otros activos fijos
A95: Depreciacion de otros activos fijos | B95: DEPRECIACIONES | C95: GASTOS DE ADMINISTRACIÓN | D95: OTROS | G95: 5828.89 | L95: 01/Mar/2026 | M95: Diario | N95: 401 | O95: Depreciación de instalación
A96: Mensajería | B96: DHL EXPRESSS | C96: COGS | D96: OPERACIONES | G96: 13588.66 | L96: 01/Mar/2026 | M96: Diario | N96: 240 | O96: Mensajería
A97: Mensajería | B97: DHL EXPRESSS | C97: COGS | D97: OPERACIONES | G97: 15742.65 | L97: 01/Mar/2026 | M97: Diario | N97: 240 | O97: Mensajería
A98: Mensajería | B98: DHL EXPRESSS | C98: COGS | D98: OPERACIONES | G98: 17105.11 | L98: 01/Mar/2026 | M98: Diario | N98: 240 | O98: Mensajería
A99: Mensajería | B99: DHL EXPRESSS | C99: COGS | D99: OPERACIONES | G99: 17874.99 | L99: 01/Mar/2026 | M99: Diario | N99: 240 | O99: Mensajería
A100: Mensajería | B100: DHL EXPRESSS | C100: COGS | D100: OPERACIONES | G100: 32343.11 | L100: 01/Mar/2026 | M100: Diario | N100: 240 | O100: Mensajería
...

Sheet nom_interna
B1: 1 de Enero del 2026 al 15 de Enero del 2026 Fecha de Pago : 15 de Enero del 2026 | H1: 16 de Enero del 2026 al 31 de Enero del 2026 Fecha de Pago : 31 de Enero del 2026
B3: Empleado | C3: Sueldo neto | D3: Area | H3: Empleado | I3: Sueldo neto | J3: Area
A4: 1 | B4: FRANCISCO JAVIER BERRUETA GUTIERREZ | C4: 5988.68 | D4: Otros | G4: 1 | H4: FRANCISCO JAVIER BERRUETA GUTIERREZ | I4: 5988.68 | J4: Otros
A5: 2 | B5: JOSE DE JESUS RAMIREZ GONZALEZ | C5: 12874.48 | D5: Aperaciones | G5: 2 | H5: JOSE DE JESUS RAMIREZ GONZALEZ | I5: 7253.28 | J5: Aperaciones
A6: 3 | B6: SUSANA RUTH GARCIA MARTINEZ | C6: 6499.95 | D6: Otros - LAE | G6: 3 | H6: SUSANA RUTH GARCIA MARTINEZ | I6: 6499.95 | J6: Otros - LAE
A7: 4 | B7: DIEGO JOSUE MALAGON MORALES | C7: 6499.95 | D7: Direccion | G7: 4 | H7: DIEGO JOSUE MALAGON MORALES | I7: 6499.95 | J7: Direccion
A8: 5 | B8: DIEGO GUERRA GUTIERREZ | C8: 6499.95 | D8: Otros - LAE | G8: 5 | H8: DIEGO GUERRA GUTIERREZ | I8: 6499.95 | J8: Otros - LAE
A9: 6 | B9: ALEJANDRO MORALES ROMERO | C9: 13123.05 | D9: Tecnico | G9: 6 | H9: ALEJANDRO MORALES ROMERO | I9: 13123.05 | J9: Tecnico
A10: 7 | B10: GINA ARLETTE DUARTE RODRIGUEZ | C10: 6499.95 | D10: Admon | G10: 7 | H10: GINA ARLETTE DUARTE RODRIGUEZ | I10: 6499.95 | J10: Admon
A11: 8 | B11: JOSE CARLOS SAENZ FERNANDEZ | C11: 8109.55 | D11: Admon | G11: 8 | H11: JOSE CARLOS SAENZ FERNANDEZ | I11: 8109.55 | J11: Admon
A12: 9 | B12: NADIA YURIT ARAUJO ISLAS | C12: 5192.95 | D12: Operaciones | G12: 9 | H12: NADIA YURIT ARAUJO ISLAS | I12: 0 | J12: Operaciones
A13: 10 | C13: =SUM(C4:C12) -> 71288.51 | I13: =SUM(I4:I12) -> 60474.36
A14: 11
B16: 1 de Febrero del 2026 al 15 de Febrero del 2026 Fecha de Pago : 13 de febrero del 2026 | H16: 16 de Febrero del 2026 al 28 de Febrero del 2026 Fecha de Pago : 27 de Febrero del 2026
B18: Empleado | C18: Sueldo neto | D18: Area
B19: FRANCISCO JAVIER BERRUETA GUTIERREZ | C19: 5989.43 | D19: Otros | H19: Empleado | I19: Sueldo neto | J19: Area
B20: JOSE DE JESUS RAMIREZ GONZALEZ | C20: 0 | D20: Aperaciones | G20: 1 | H20: FRANCISCO JAVIER BERRUETA GUTIERREZ | I20: 5989.43 | J20: Otros
B21: SUSANA RUTH GARCIA MARTINEZ | C21: 6499.95 | D21: Otros - LAE | G21: 2 | H21: JOSE DE JESUS RAMIREZ GONZALEZ | I21: 0 | J21: Aperaciones
B22: DIEGO JOSUE MALAGON MORALES | C22: 6499.95 | D22: Direccion | G22: 3 | H22: SUSANA RUTH GARCIA MARTINEZ | I22: 6499.95 | J22: Otros - LAE
B23: DIEGO GUERRA GUTIERREZ | C23: 6499.95 | D23: Otros - LAE | G23: 4 | H23: DIEGO JOSUE MALAGON MORALES | I23: 6499.95 | J23: Direccion
B24: ALEJANDRO MORALES ROMERO | C24: 13123.8 | D24: Tecnico | G24: 5 | H24: DIEGO GUERRA GUTIERREZ | I24: 6499.95 | J24: Otros - LAE
B25: GINA ARLETTE DUARTE RODRIGUEZ | C25: 6499.95 | D25: Admon | G25: 6 | H25: ALEJANDRO MORALES ROMERO | I25: 13123.8 | J25: Tecnico
B26: JOSE CARLOS SAENZ FERNANDEZ | C26: 11000.07 | D26: Admon | G26: 7 | H26: GINA ARLETTE DUARTE RODRIGUEZ | I26: 6499.95 | J26: Admon
B27: NADIA YURIT ARAUJO ISLAS | C27: 5193.7 | D27: Operaciones | G27: 8 | H27: JOSE CARLOS SAENZ FERNANDEZ | I27: 11000.07 | J27: Admon
C28: =SUM(C19:C27) -> 61306.8 | G28: 9 | H28: NADIA YURIT ARAUJO ISLAS | I28: 6988.79 | J28: Operaciones
G29: 10 | H29: -EDGARDO RAMIRO VIDAL CAMBERO | I29: 1575.2 | J29: Operaciones
G30: 11 | H30: -GERMAIN ACEVEDO LOPEZ | I30: 1575.2 | J30: Operaciones
G31: 12 | H31: -ALBA AMARIANA ARVIZU | I31: 1575.2 | J31: Operaciones
G32: 13 | H32: -NESTOR AXEL ESPINOSA MENDOZA | I32: 1575.2 | J32: Operaciones
G33: 14 | H33: -MARIANA GUADALUPE VILLEGAS BOLAÑO | I33: 1575.2 | J33: Operaciones
G34: 15 | H34: -IRIS SELENE HIDALGO JIMENEZ | I34: 1575.2 | J34: Operaciones
G35: 16 | H35: -EBER GALLARDO PADILLA | I35: 1575.2 | J35: Operaciones
G36: 17 | H36: -OMAR ANGEL RANGEL SANCHEZ | I36: 1575.2 | J36: Operaciones
I37: =SUM(I20:I36) -> 75703.49
B41: 1 de Marzo del 2026 al 15 de Marzo del 2026 Fecha de Pago : 13 de Marzo del 2026
H42: Empleado | I42: Sueldo neto | J42: Area
G43: 1 | H43: FRANCISCO JAVIER BERRUETA GUTIERREZ | I43: 5989.43 | J43: Otros
B44: Empleado | C44: Sueldo neto | D44: Area | G44: 2 | H44: JOSE DE JESUS RAMIREZ GONZALEZ | I44: 0 | J44: Aperaciones
A45: 1 | B45: FRANCISCO JAVIER BERRUETA GUTIERREZ | C45: 5989.43 | D45: Otros | G45: 3 | H45: SUSANA RUTH GARCIA MARTINEZ | I45: 6499.95 | J45: Otros - LAE | L45: =C116*2 -> 9451.2
A46: 2 | B46: JOSE DE JESUS RAMIREZ GONZALEZ | C46: 0 | D46: Aperaciones | G46: 4 | H46: DIEGO JOSUE MALAGON MORALES | I46: 6499.95 | J46: Direccion
A47: 3 | B47: SUSANA RUTH GARCIA MARTINEZ | C47: 6499.95 | D47: Otros - LAE | G47: 5 | H47: DIEGO GUERRA GUTIERREZ | I47: 6499.95 | J47: Otros - LAE
A48: 4 | B48: DIEGO JOSUE MALAGON MORALES | C48: 6499.95 | D48: Direccion | G48: 6 | H48: ALEJANDRO MORALES ROMERO | I48: 13123.8 | J48: Tecnico
A49: 5 | B49: DIEGO GUERRA GUTIERREZ | C49: 6499.95 | D49: Otros - LAE | G49: 7 | H49: GINA ARLETTE DUARTE RODRIGUEZ | I49: 6499.95 | J49: Admon
A50: 6 | B50: ALEJANDRO MORALES ROMERO | C50: 13123.8 | D50: Tecnico | G50: 8 | H50: JOSE CARLOS SAENZ FERNANDEZ | I50: 11000.07 | J50: Admon
A51: 7 | B51: GINA ARLETTE DUARTE RODRIGUEZ | C51: 6499.95 | D51: Admon | G51: 9 | H51: NADIA YURIT ARAUJO ISLAS | I51: 6988.79 | J51: Operaciones
A52: 8 | B52: JOSE CARLOS SAENZ FERNANDEZ | C52: 11000.07 | D52: Admon | G52: 10 | H52: -EDGARDO RAMIRO VIDAL CAMBERO | I52: 4725.6 | J52: Operaciones
A53: 9 | B53: NADIA YURIT ARAUJO ISLAS | C53: 6988.79 | D53: Operaciones | G53: 11 | H53: -GERMAIN ACEVEDO LOPEZ | I53: 4725.6 | J53: Operaciones
A54: 10 | B54: -EDGARDO RAMIRO VIDAL CAMBERO | C54: 5218.19 | D54: Operaciones | G54: 12 | H54: -ALBA AMARIANA ARVIZU | I54: 4725.6 | J54: Operaciones
A55: 11 | B55: -GERMAIN ACEVEDO LOPEZ | C55: 5218.19 | D55: Operaciones | G55: 13 | H55: -NESTOR AXEL ESPINOSA MENDOZA | I55: 4725.6 | J55: Operaciones
A56: 12 | B56: -ALBA AMARIANA ARVIZU | C56: 5218.19 | D56: Operaciones | G56: 14 | H56: -MARIANA GUADALUPE VILLEGAS BOLAÑO | I56: 4725.6 | J56: Operaciones
A57: 13 | B57: -NESTOR AXEL ESPINOSA MENDOZA | C57: 5218.19 | D57: Operaciones | G57: 15 | H57: -IRIS SELENE HIDALGO JIMENEZ | I57: 4725.6 | J57: Operaciones
... A60: 16 | B60: -EBER GALLARDO PADILLA | C60: 5218.19 | D60: Operaciones | G60: 18 | H60: CINTHYA FERNANDA SALCIDO SOTO | I60: 4725.6 | J60: Operaciones
A61: 17 | B61: -OMAR ANGEL RANGEL SANCHEZ | C61: =I59 -> 4725.6 | D61: Operaciones | G61: 19 | H61: JOSE GUADALUPE GOMEZ GUZMAN | I61: 4725.6 | J61: Operaciones
A62: 18 | B62: CINTHYA FERNANDA SALCIDO SOTO | C62: 4725.6 | D62: Operaciones | G62: 20 | H62: FIDEL GARCIA VELAZQUEZ | I62: 4725.6 | J62: Operaciones | L62: =C62+I60 -> 9451.2
A63: 19 | B63: JOSE GUADALUPE GOMEZ GUZMAN | C63: 4725.6 | D63: Operaciones | G63: 21 | H63: LUIS JOAQUIN VASQUEZ JIMENEZ | I63: 4725.6 | J63: Operaciones | L63: =C63+I61 -> 9451.2
A64: 20 | B64: FIDEL GARCIA VELAZQUEZ | C64: 4725.6 | D64: Operaciones | G64: 22 | H64: JUAN LUIS MATUS GARCIA REPPER | I64: 4725.6 | J64: Operaciones | L64: =C64+I62 -> 9451.2
A65: 21 | B65: LUIS JOAQUIN VASQUEZ JIMENEZ | C65: 4725.6 | D65: Operaciones | G65: 23 | H65: RODRIGO ALVAREZ CABRERA | I65: 4725.6 | J65: Operaciones | L65: =C65+I63 -> 9451.2
A66: 22 | B66: JUAN LUIS MATUS GARCIA REPPER | C66: 4725.6 | D66: Operaciones | G66: 24 | H66: LUIS DIEGO LOPEZ LOPEZ | I66: 4725.6 | J66: Operaciones | L66: =C66+I64 -> 9451.2
A67: 23 | B67: RODRIGO ALVAREZ CABRERA | C67: 4725.6 | D67: Operaciones | G67: 25 | H67: IVAN JOEL ORTIZ PEÑA | I67: 4725.6 | J67: Operaciones | L67: =C67+I65 -> 9451.2
A68: 24 | B68: LUIS DIEGO LOPEZ LOPEZ | C68: 4725.6 | D68: Operaciones | G68: 26 | H68: IRAIDE SUSANA LOPEZ MENDEZ | I68: 4725.6 | J68: Operaciones | L68: =C68+I66 -> 9451.2
A69: 25 | B69: IVAN JOEL ORTIZ PEÑA | C69: 4725.6 | D69: Operaciones | G69: 27 | H69: ERICK ALAN DOMINGUEZ CORTES | I69: 4725.6 | J69: Operaciones | L69: =C69+I67 -> 9451.2
A70: 26 | B70: IRAIDE SUSANA LOPEZ MENDEZ | C70: 4725.6 | D70: Operaciones | G70: 28 | H70: XIMENA GUZMAN SILVA | I70: 4725.6 | J70: Operaciones | L70: =C70+I68 -> 9451.2
A71: 27 | B71: ERICK ALAN DOMINGUEZ CORTES | C71: 4725.6 | D71: Operaciones | G71: 29 | H71: ROMAN RAMON PENICHE MUÑOZ | I71: 4725.6 | J71: Operaciones | L71: =C71+I69 -> 9451.2
A72: 28 | B72: XIMENA GUZMAN SILVA | C72: 4725.6 | D72: Operaciones | G72: 30 | H72: EDGAR NICOLAS RIVAS NIETO | I72: 4725.6 | J72: Operaciones | L72: =C72+I70 -> 9451.2
A73: 29 | B73: ROMAN RAMON PENICHE MUÑOZ | C73: 4725.6 | D73: Operaciones | G73: 31 | H73: VICTOR HUGO JUAREZ QUEVEDO | I73: 4725.6 | J73: Operaciones | L73: =C73+I71 -> 9451.2
... A79: 35 | B79: ANTONIO BACA AGUIRRE | C79: 1890.24 | D79: Operaciones | G79: 37 | H79: MAGDIEL ISRAEL OCAMPO GUTIERREZ | I79: 4725.6 | J79: Operaciones | L79: =C79+I77 -> 6615.84
C80: =SUM(C45:C79) -> 172403.46 | G80: 38 | H80: SERGIO MENDIZABAL VAZQUEZ | I80: 4725.6 | J80: Operaciones | L80: =I78 -> 4725.6
G81: 39 | H81: ALBERTO NICOLAS ARRAZOLA SANTAELLA | I81: 4725.6 | J81: Operaciones | L81: =C81+I79 -> 4725.6
G82: 40 | H82: LUIS ENRIQUE ROJAS GERARDO | I82: 4725.6 | J82: Operaciones | L82: =C82+I80 -> 4725.6
G83: 41 | H83: JESUS ANTONIO VACA RODRIGUEZ | I83: 4725.6 | J83: Operaciones | L83: =C83+I81 -> 4725.6
G84: 42 | H84: BRENDA ALESSIA LARA MARTINEZ | I84: 2205.28 | J84: Operaciones | L84: =C84+I82 -> 4725.6
G85: 43 | H85: DAVID ALEJANDRO MUI DAZA | I85: 2205.28 | J85: Operaciones | L85: =C85+I83 -> 4725.6
G86: 44 | H86: ANDRES ROCHA GARCIA | I86: 630.08 | J86: Operaciones | L86: =C86+I84 -> 2205.28
I87: =SUM(I43:I86) -> 219361.73 | L87: =C87+I85 -> 2205.28
L88: =C88+I86 -> 630.08
B94: 1 de Abril del 2026 al 15 de Abril del 2026 Fecha de Pago : 16 de Abril del 2026 | H94: 16 de Abril del 2026 al 30 de Abril del 2026 Fecha de Pago : 30 de Abril del 2026
B96: Empleado | C96: Sueldo neto | D96: Area | H96: Empleado | I96: Sueldo neto | J96: Area
A97: 1 | B97: FRANCISCO JAVIER BERRUETA GUTIERREZ | C97: 5989.43 | D97: Otros | G97: 1 | H97: FRANCISCO JAVIER BERRUETA GUTIERREZ | I97: 5989.43 | J97: Otros
A98: 2 | B98: JOSE DE JESUS RAMIREZ GONZALEZ | C98: 0 | D98: Aperaciones | G98: 2 | H98: JOSE DE JESUS RAMIREZ GONZALEZ | I98: 0 | J98: Aperaciones
A99: 3 | B99: SUSANA RUTH GARCIA MARTINEZ | C99: 6499.95 | D99: Otros - LAE | G99: 3 | H99: SUSANA RUTH GARCIA MARTINEZ | I99: 6499.95 | J99: Otros - LAE
A100: 4 | B100: DIEGO JOSUE MALAGON MORALES | C100: 6499.95 | D100: Direccion | G100: 4 | H100: DIEGO JOSUE MALAGON MORALES | I100: 6499.95 | J100: Direccion
A101: 5 | B101: DIEGO GUERRA GUTIERREZ | C101: 6499.95 | D101: Otros - LAE | G101: 5 | H101: DIEGO GUERRA GUTIERREZ | I101: 6499.95 | J101: Otros - LAE
A102: 6 | B102: ALEJANDRO MORALES ROMERO | C102: 13123.8 | D102: Tecnico | G102: 6 | H102: ALEJANDRO MORALES ROMERO | I102: 13123.8 | J102: Tecnico
A103: 7 | B103: GINA ARLETTE DUARTE RODRIGUEZ | C103: 6499.95 | D103: Admon | G103: 7 | H103: GINA ARLETTE DUARTE RODRIGUEZ | I103: 6499.95 | J103: Admon
A104: 8 | B104: JOSE CARLOS SAENZ FERNANDEZ | C104: 11000.07 | D104: Admon | G104: 8 | H104: JOSE CARLOS SAENZ FERNANDEZ | I104: 11000.07 | J104: Admon
A105: 9 | B105: NADIA YURIT ARAUJO ISLAS | C105: 6988.79 | D105: Operaciones | G105: 9 | H105: NADIA YURIT ARAUJO ISLAS | I105: 6988.79 | J105: Operaciones
A106: 10 | B106: -EDGARDO RAMIRO VIDAL CAMBERO | C106: 4725.6 | D106: Operaciones | G106: 10 | H106: -EDGARDO RAMIRO VIDAL CAMBERO | I106: 4725.6 | J106: Operaciones
A107: 11 | B107: -GERMAIN ACEVEDO LOPEZ | C107: 4725.6 | D107: Operaciones | G107: 11 | H107: -GERMAIN ACEVEDO LOPEZ | I107: 4725.6 | J107: Operaciones
A108: 12 | B108: -ALBA AMARIANA ARVIZU | C108: 4725.6 | D108: Operaciones | G108: 12 | H108: -ALBA AMARIANA ARVIZU | I108: 4725.6 | J108: Operaciones
... A113: 17 | B113: -OMAR ANGEL RANGEL SANCHEZ | C113: 4725.6 | D113: Operaciones | G113: 17 | H113: -OMAR ANGEL RANGEL SANCHEZ | I113: 4725.6 | J113: Operaciones
A114: 18 | B114: CINTHYA FERNANDA SALCIDO SOTO | C114: 4725.6 | D114: Operaciones | G114: 18 | H114: CINTHYA FERNANDA SALCIDO SOTO | I114: 4725.6 | J114: Operaciones | L114: =C114+I114 -> 9451.2
A115: 19 | B115: JOSE GUADALUPE GOMEZ GUZMAN | C115: 4725.6 | D115: Operaciones | G115: 19 | H115: JOSE GUADALUPE GOMEZ GUZMAN | I115: 4725.6 | J115: Operaciones | L115: =C115+I115 -> 9451.2
A116: 20 | B116: FIDEL GARCIA VELAZQUEZ | C116: 4725.6 | D116: Operaciones | G116: 20 | H116: FIDEL GARCIA VELAZQUEZ | I116: 4725.6 | J116: Operaciones | L116: =C116+I116 -> 9451.2
A117: 21 | B117: LUIS JOAQUIN VASQUEZ JIMENEZ | C117: 4725.6 | D117: Operaciones | G117: 21 | H117: LUIS JOAQUIN VASQUEZ JIMENEZ | I117: 4725.6 | J117: Operaciones | L117: =C117+I117 -> 9451.2
A118: 22 | B118: JUAN LUIS MATUS GARCIA REPPER | C118: 4725.6 | D118: Operaciones | G118: 22 | H118: JUAN LUIS MATUS GARCIA REPPER | I118: 4725.6 | J118: Operaciones | L118: =C118+I118 -> 9451.2
A119: 23 | B119: RODRIGO ALVAREZ CABRERA | C119: 1854.6 | D119: Operaciones | G119: 23 | H119: RODRIGO ALVAREZ CABRERA | I119: 1854.6 | J119: Operaciones | L119: =C119+I119 -> 3709.2
A120: 24 | B120: LUIS DIEGO LOPEZ LOPEZ | C120: 4725.6 | D120: Operaciones | G120: 24 | H120: LUIS DIEGO LOPEZ LOPEZ | I120: 4725.6 | J120: Operaciones | L120: =C120+I120 -> 9451.2
A121: 25 | B121: IVAN JOEL ORTIZ PEÑA | C121: 4725.6 | D121: Operaciones | G121: 25 | H121: IVAN JOEL ORTIZ PEÑA | I121: 4725.6 | J121: Operaciones | L121: =C121+I121 -> 9451.2
A122: 26 | B122: IRAIDE SUSANA LOPEZ MENDEZ | C122: 4725.6 | D122: Operaciones | G122: 26 | H122: IRAIDE SUSANA LOPEZ MENDEZ | I122: 4725.6 | J122: Operaciones | L122: =C122+I122 -> 9451.2
A123: 27 | B123: ERICK ALAN DOMINGUEZ CORTES | C123: 4725.6 | D123: Operaciones | G123: 27 | H123: ERICK ALAN DOMINGUEZ CORTES | I123: 4725.6 | J123: Operaciones | L123: =C123+I123 -> 9451.2
...

Sheet respaldo otros egresos
A1: CATEGORIA_NETSUITE | B1: Concepto | C1: IS | D1: ÁREA | E1: ZONA PPTO | F1: EMPLEADO | G1: MONTO | H1: PERIODO | I1: AREA | J1: ZONA | K1: PCT_POND | L1: Cargos | M1: Fecha | N1: Tipo | O1: Número | P1: Clasf Efs | Q1: ID SGN | R1: PUESTO | S1: PAGADORA
A2: __EXCLUIR__ | B2: REVERSAS INGRESOS | G2: -619202.69 | L2: -619202.69 | M2: 31/Ene/2026 | N2: Diario | O2: 303 | P2: Diseño digital
A3: __EXCLUIR__ | B3: REVERSAS INGRESOS | G3: -33600 | L3: -33600 | M3: 31/Ene/2026 | N3: Diario | O3: 303 | P3: Diseño digital
A4: Agua | B4: MAGALI DESIREL RIOS NAVARROVIANEY MADERO CUADRAS | C4: GASTOS DE ADMINISTRACIÓN | D4: TÉCNICO | G4: 816.82222 | L4: 106 | M4: 01/Ene/2026 | N4: Diario | O4: 271 | P4: Agua
A5: Agua | B5: MAGALI DESIREL RIOS NAVARROVIANEY MADERO CUADRAS | C5: GASTOS DE ADMINISTRACIÓN | D5: RH | G5: 58.344444 | L5: 192 | M5: 01/Ene/2026 | N5: Diario | O5: 271 | P5: Agua
A6: Agua | B6: MAGALI DESIREL RIOS NAVARROVIANEY MADERO CUADRAS | C6: COGS | D6: OPERACIONES | G6: 1108.5444 | L6: 430 | M6: 01/Ene/2026 | N6: Diario | O6: 271 | P6: Agua
A7: Agua | B7: MAGALI DESIREL RIOS NAVARROVIANEY MADERO CUADRAS | C7: GASTOS DE ADMINISTRACIÓN | D7: FINANZAS | G7: 155.58519 | L7: 1897.5 | M7: 01/Ene/2026 | N7: Diario | O7: 271 | P7: Agua
A8: Agua | B8: MAGALI DESIREL RIOS NAVARROVIANEY MADERO CUADRAS | C8: GASTOS DE ADMINISTRACIÓN | D8: BRAND BUILDING | G8: 87.516667 | M8: 01/Ene/2026
A9: Agua | B9: MAGALI DESIREL RIOS NAVARROVIANEY MADERO CUADRAS | C9: GASTOS DE ADMINISTRACIÓN | D9: COMERCIAL | G9: 311.17037 | M9: 01/Ene/2026
A10: Agua | B10: MAGALI DESIREL RIOS NAVARROVIANEY MADERO CUADRAS | C10: GASTOS DE ADMINISTRACIÓN | D10: DIRECTIVO | G10: 87.516667 | M10: 01/Ene/2026
A11: Amortizacion acumulada de Software | B11: AMORTIZACION | C11: COGS | D11: OPERACIONES | F11: MONDAY | G11: 101529.4 | M11: 01/Ene/2026
A12: Amortizacion acumulada de Software | B12: AMORTIZACION | C12: GASTOS DE ADMINISTRACIÓN | D12: FINANZAS | F12: NETSUITE | G12: 101529.4 | M12: 01/Ene/2026
A13: Arrendamiento a pers fisicas residtes nal | B13: ANGEL OROSCO ANGELES | C13: POR CLASIFICAR | G13: 4258.36 | L13: 4258.36 | M13: 01/Ene/2026 | N13: Diario | O13: 272 | P13: Arrendamiento a pers físicas residtes nal
A14: Arrendamiento a pers fisicas residtes nal | B14: ANGEL OROSCO ANGELES | C14: POR CLASIFICAR | G14: 15365.54 | L14: 15365.54 | M14: 01/Ene/2026 | N14: Diario | O14: 272 | P14: Arrendamiento a pers morales residtes nal
A15: Arrendamiento a pers fisicas residtes nal | B15: ANGEL OROSCO ANGELES | C15: POR CLASIFICAR | G15: 17316.68 | L15: 17316.68 | M15: 01/Ene/2026 | N15: Diario | O15: 272 | P15: Arrendamiento a pers morales residtes nal
A16: Arrendamiento a pers morales residtes nal | B16: DELL LEASING MEXICO | C16: GASTOS DE ADMINISTRACIÓN | D16: TÉCNICO | G16: 15289.593 | L16: 3985.76 | M16: 01/Ene/2026 | N16: Diario | O16: 272 | P16: Arrendamiento a pers morales residtes nal
A17: Arrendamiento a pers morales residtes nal | B17: DELL LEASING MEXICO | C17: GASTOS DE ADMINISTRACIÓN | D17: RH | G17: 1092.1138 | L17: 4172.27 | M17: 01/Ene/2026 | N17: Diario | O17: 272 | P17: Arrendamiento a pers morales residtes nal
A18: Arrendamiento a pers morales residtes nal | B18: DELL LEASING MEXICO | C18: COGS | D18: OPERACIONES | G18: 20750.162 | L18: 4578.49 | M18: 01/Ene/2026 | N18: Diario | O18: 272 | P18: Arrendamiento a pers morales residtes nal
A19: Arrendamiento a pers morales residtes nal | B19: DELL LEASING MEXICO | C19: GASTOS DE ADMINISTRACIÓN | D19: FINANZAS | G19: 2912.3034 | L19: 6890.7 | M19: 01/Ene/2026 | N19: Diario | O19: 272 | P19: Arrendamiento a pers morales residtes nal
A20: Arrendamiento a pers morales residtes nal | B20: DELL LEASING MEXICO | C20: GASTOS DE ADMINISTRACIÓN | D20: BRAND BUILDING | G20: 1638.1707 | L20: 7734.15 | M20: 01/Ene/2026 | N20: Diario | O20: 272 | P20: Arrendamiento a pers morales residtes nal
A21: Arrendamiento a pers morales residtes nal | B21: DELL LEASING MEXICO | C21: GASTOS DE ADMINISTRACIÓN | D21: COMERCIAL | G21: 5824.6068 | L21: 9987.58 | M21: 01/Ene/2026 | N21: Diario | O21: 272 | P21: Arrendamiento a pers morales residtes nal
A22: Arrendamiento a pers morales residtes nal | B22: DELL LEASING MEXICO | C22: GASTOS DE ADMINISTRACIÓN | D22: DIRECTIVO | G22: 1638.1707 | L22: 11796.17 | M22: 01/Ene/2026 | N22: Diario | O22: 272 | P22: Arrendamiento a pers morales residtes nal
A23: Arrendamiento a pers morales residtes nal | B23: EXI TECNOLOGIAS DE LA INFORMACION | C23: POR CLASIFICAR | G23: 11900 | L23: 11900 | M23: 01/Ene/2026 | N23: Diario | O23: 272 | P23: Arrendamiento a pers morales residtes nal
A24: Arrendamiento a pers morales residtes nal | B24: FLEET CAR COMPANY MX | C24: COGS | D24: OPERACIONES | G24: 2392.85 | L24: 2392.85 | M24: 01/Ene/2026 | N24: Diario | O24: 272 | P24: Arrendamiento a pers morales residtes nal
A25: Arrendamiento a pers morales residtes nal | B25: FLEET CAR COMPANY MX | C25: COGS | D25: OPERACIONES | G25: 2758.62 | L25: 2758.62 | M25: 01/Ene/2026 | N25: Diario | O25: 272 | P25: Arrendamiento a pers morales residtes nal
A26: Arrendamiento a pers morales residtes nal | B26: FLEET CAR COMPANY MX | C26: COGS | D26: OPERACIONES | G26: 5475.37 | L26: 5475.37 | M26: 01/Ene/2026 | N26: Diario | O26: 272 | P26: Arrendamiento a pers morales residtes nal
A27: Arrendamiento a pers morales residtes nal | B27: PS GRAPH | C27: GASTOS DE ADMINISTRACIÓN | D27: TÉCNICO | G27: 145600 | M27: 01/Ene/2026 | N27: Diario | O27: 272 | P27: Arrendamiento a pers morales residtes nal
A28: Arrendamiento a pers morales residtes nal | B28: PS GRAPH | C28: GASTOS DE ADMINISTRACIÓN | D28: RH | G28: 10400 | M28: 01/Ene/2026 | N28: Diario | O28: 272 | P28: Arrendamiento a pers morales residtes nal
A29: Arrendamiento a pers morales residtes nal | B29: PS GRAPH | C29: COGS | D29: OPERACIONES | E29: CENTRO | G29: 197600 | M29: 01/Ene/2026 | N29: Diario | O29: 272 | P29: Arrendamiento a pers morales residtes nal
A30: Arrendamiento a pers morales residtes nal | B30: PS GRAPH | C30: GASTOS DE ADMINISTRACIÓN | D30: FINANZAS | G30: 27733.333 | M30: 01/Ene/2026
A31: Arrendamiento a pers morales residtes nal | B31: PS GRAPH | C31: GASTOS DE ADMINISTRACIÓN | D31: BRAND BUILDING | G31: 15600 | M31: 01/Ene/2026
A32: Arrendamiento a pers morales residtes nal | B32: PS GRAPH | C32: GASTOS DE ADMINISTRACIÓN | D32: COMERCIAL | G32: 55466.667 | M32: 01/Ene/2026
A33: Arrendamiento a pers morales residtes nal | B33: PS GRAPH | C33: GASTOS DE ADMINISTRACIÓN | D33: DIRECTIVO | G33: 15600 | M33: 01/Ene/2026
A34: Arrendamiento a pers morales residtes nal | B34: LOC BOX | C34: COGS | D34: OPERACIONES | G34: 4346.25 | L34: 4346.25 | M34: 01/Ene/2026 | N34: Diario | O34: 275 | P34: Casetas y estacionamientos
A35: Arrendamiento a pers morales residtes nal | B35: RESCUE 24 ASISTENCIA VIAL INTELIGENTE | C35: COGS | D35: OPERACIONES | G35: 4456 | L35: 4456 | M35: 01/Ene/2026 | N35: Diario | O35: 293 | P35: Viáticos uber/taxi
A36: Arrendamiento a pers morales residtes nal | B36: RESCUE 24 ASISTENCIA VIAL INTELIGENTE | C36: COGS | D36: OPERACIONES | G36: 4456 | L36: 4456 | M36: 01/Ene/2026 | N36: Diario | O36: 293 | P36: Viáticos uber/taxi
A37: Arrendamiento a personas fisicas resid nal | B37: FELIPE DE JESUS ORGANISTA ZAVALA | C37: POR CLASIFICAR | G37: 19503.8 | L37: 19503.8 | M37: 01/Ene/2026 | N37: Diario | O37: 272 | P37: Arrendamiento a pers morales residtes nal
A38: Arrendamiento a personas fisicas resid nal | B38: GUILLERMO ALBERTO MENDEZ ROMERO | C38: COGS | F38: ARRENDAMIENTO OFICINAS MONTERREY | G38: 17306.48 | L38: 17306.48 | M38: 01/Ene/2026 | N38: Diario | O38: 272 | P38: Arrendamiento a pers morales residtes nal
A39: Arrendamiento a personas fisicas resid nal | B39: EDGAR ALONSO AGUILAR NEGRETE | C39: GASTOS DE ADMINISTRACIÓN | D39: TÉCNICO | G39: 4275 | L39: 4275 | M39: 01/Ene/2026 | N39: Diario | O39: 276 | P39: Cuotas y suscripciones
A40: Arrendamiento Automotriz | B40: VOLKSWAGEN | C40: COGS | D40: OPERACIONES | G40: =20826.33*70% -> 14578.431 | L40: 20826.33 | M40: 01/Ene/2026 | N40: Diario | O40: 272 | P40: Arrendamiento a pers morales residtes nal
A41: Arrendamiento Automotriz | B41: VOLKSWAGEN | C41: COGS | D41: TÉCNICO | G41: =20826.33*30% -> 6247.899 | L41: 20826.33 | M41: 01/Ene/2026 | N41: Diario | O41: 272 | P41: Arrendamiento a pers morales residtes nal
A42: Asistencia Legal | B42: GRUMINER | C42: GASTOS DE ADMINISTRACIÓN | G42: 25000 | L42: 3370.7 | M42: 01/Ene/2026 | N42: Diario | O42: 284 | P42: Mantenimiento y conservación
A43: Asistencia Legal | B43: SERVICIOS MEDIDUS | C43: GASTOS DE ADMINISTRACIÓN | G43: 45000 | L43: 344.82 | M43: 01/Ene/2026 | N43: Diario | O43: 273 | P43: Asistencia Legal
A44: Capacitaciones | B44: SAMUEL HERRERA RAMIREZ | C44: GASTOS DE ADMINISTRACIÓN | D44: DIRECTIVO | G44: 8500 | L44: 8500 | M44: 01/Ene/2026 | N44: Diario | O44: 288 | P44: Servicios administrativos
A45: Capacitaciones | B45: SELH CONSULTORIA | C45: GASTOS DE ADMINISTRACIÓN | D45: COMERCIAL | G45: 5500
A46: Capacitaciones | B46: SASIT CORPORATION | C46: GASTOS DE ADMINISTRACIÓN | D46: COMERCIAL | G46: 2689.66 | L46: 5500 | M46: 01/Ene/2026 | N46: Diario | O46: 274 | P46: Capacitaciones
A47: Asistencia Legal | B47: ADMINISTRACION N23 | C47: GASTOS DE ADMINISTRACIÓN | D47: COMERCIAL | G47: 344.82 | L47: 2689.66 | M47: 01/Ene/2026 | N47: Diario | O47: 274 | P47: Capacitaciones
A48: Combustibles y lubricantes | B48: COMBUSTIBLES | C48: COGS | D48: OPERACIONES | G48: =19833.79*70% -> 13883.653 | L48: 19833.79 | M48: 01/Ene/2026 | N48: Diario | O48: 260 | P48: Combustibles y lubricantes
A49: Combustibles y lubricantes | B49: COMBUSTIBLES | C49: COGS | D49: TÉCNICO | G49: =19833.79*30% -> 5950.137 | L49: 19833.79 | M49: 01/Ene/2026 | N49: Diario | O49: 260 | P49: Combustibles y lubricantes
A50: Combustibles y lubricantes | B50: EFECTIVALE | C50: COGS | D50: OPERACIONES | G50: 858.75 | L50: 858.75 | M50: 01/Ene/2026 | N50: Diario | O50: 295 | P50: Comisiones Efectivale
A51: Combustibles y lubricantes | B51: EFECTIVALE | C51: COGS | D51: TÉCNICO | G51: 858.75 | L51: 858.75 | M51: 01/Ene/2026 | N51: Diario | O51: 295 | P51: Comisiones Efectivale
A52: Combustibles y lubricantes | B52: EFECTIVALE | C52: COGS | D52: OPERACIONES | G52: 1202.25 | L52: 1202.25 | M52: 01/Ene/2026 | N52: Diario | O52: 295 | P52: Comisiones Efectivale
A53: Combustibles y lubricantes | B53: EFECTIVALE | C53: COGS | D53: TÉCNICO | G53: 1374 | L53: 1374 | M53: 01/Ene/2026 | N53: Diario | O53: 295 | P53: Comisiones Efectivale
A54: Comisiones bancarias | B54: BBVA MEXICO | C54: OTROS INGRESOS / GASTOS | D54: OTROS | G54: 3700.28 | L54: 3700.28 | M54: 07/Ene/2026 | N54: Egresos | O54: 202 | P54: Comisiones Bancarias
A55: Comisiones bancarias | B55: COMISIONES BANCARIAS BBVA USD | C55: OTROS INGRESOS / GASTOS | D55: OTROS | G55: 524.48 | L55: 524.48 | M55: 23/Ene/2026 | N55: Egresos | O55: 240 | P55: Comisiones Bancarias
A56: Comisiones bancarias | B56: PAGO TC CLARA | C56: OTROS INGRESOS / GASTOS | D56: OTROS | G56: 9948.99 | L56: 9948.99 | M56: 23/Ene/2026 | N56: Diario | O56: 400 | P56: Comisiones Bancarias
A57: Comisiones bancarias | B57: AFIRME | C57: OTROS INGRESOS / GASTOS | D57: OTROS | G57: 400 | L57: 400 | M57: 30/Ene/2026 | N57: Egresos | O57: 243 | P57: Comisiones Bancarias
A58: Comisiones bancarias | B58: COMISIONES BANCARIAS INBURSA | C58: OTROS INGRESOS / GASTOS | G58: 256.55 | L58: 256.55 | M58: 31/Ene/2026 | N58: Egresos | O58: 246 | P58: Comisiones Bancarias
A59: Comisiones bancarias | B59: COMISIONES BANCARIAS SCOTIABANK | C59: OTROS INGRESOS / GASTOS | G59: 620 | L59: 620 | M59: 31/Ene/2026 | N59: Egresos | O59: 247 | P59: Comisiones Bancarias
A60: Cuotas al IMSS | B60: PROVISION IMSS ENERO 2026 | C60: POR CLASIFICAR | G60: 13833.01 | L60: 13833.01 | M60: 01/Ene/2026 | N60: Diario | O60: 500 | P60: Cuotas al IMSS
A61: Cuotas y suscripciones | B61: RODRIGO FERNANDO ROLDAN MORALES | C61: GASTOS DE ADMINISTRACIÓN | D61: OTROS | G61: 5244.76 | L61: 5244.76 | M61: 01/Ene/2026 | N61: Diario | O61: 288 | P61: Servicios administrativos
A62: Cuotas y suscripciones | B62: CUOTAS Y SUSCRIPCIONES | C62: GASTOS DE ADMINISTRACIÓN | D62: OTROS | G62: 585.56 | L62: 5700.83 | M62: 27/Ene/2026 | N62: Egresos | O62: 148 | P62: Seguros y fianzas
A63: Cuotas y suscripciones | B63: IMR SOFTWARE | C63: GASTOS DE ADMINISTRACIÓN | D63: FINANZAS | G63: 4500 | L63: 4500 | M63: 01/Ene/2026 | N63: Diario | O63: 276 | P63: Cuotas y suscripciones
A64: Cuotas y suscripciones | B64: IMR SOFTWARE | C64: GASTOS DE ADMINISTRACIÓN | D64: FINANZAS | G64: 3190 | L64: 3190 | M64: 01/Ene/2026 | N64: Diario | O64: 276 | P64: Cuotas y suscripciones
A65: Cuotas y suscripciones | B65: ONLINE CARRER CENTER MEXICO | C65: GASTOS DE ADMINISTRACIÓN | D65: RH | G65: 3864 | L65: 3190 | M65: 01/Ene/2026 | N65: Diario | O65: 276 | P65: Cuotas y suscripciones
A66: Cuotas y suscripciones | B66: GOOGLE MX | C66: GASTOS DE ADMINISTRACIÓN | D66: TÉCNICO | G66: 2681.9924 | L66: 3864 | M66: 01/Ene/2026 | N66: Diario | O66: 276 | P66: Cuotas y suscripciones
A67: Cuotas y suscripciones | B67: GOOGLE MX | C67: GASTOS DE ADMINISTRACIÓN | D67: RH | G67: 191.57089 | L67: -5233.75 | M67: 01/Ene/2026 | N67: Diario | O67: 281 | P67: Cuotas y suscripciones
A68: Cuotas y suscripciones | B68: GOOGLE MX | C68: GASTOS DE ADMINISTRACIÓN | D68: OPERACIONES | G68: 3639.8469 | L68: -3274.32 | M68: 01/Ene/2026 | N68: Diario | O68: 281 | P68: Cuotas y suscripciones
A69: Cuotas y suscripciones | B69: GOOGLE MX | C69: COGS | D69: FINANZAS | G69: 510.8557 | L69: 8508.07 | M69: 01/Ene/2026 | N69: Diario | O69: 281 | P69: Cuotas y suscripciones
A70: Cuotas y suscripciones | B70: GOOGLE MX | C70: GASTOS DE ADMINISTRACIÓN | D70: BRAND BUILDING | G70: 287.35633 | M70: 01/Ene/2026
A71: Cuotas y suscripciones | B71: GOOGLE MX | C71: GASTOS DE ADMINISTRACIÓN | D71: COMERCIAL | G71: 1021.7114 | M71: 01/Ene/2026
A72: Cuotas y suscripciones | B72: GOOGLE MX | C72: GASTOS DE ADMINISTRACIÓN | D72: DIRECTIVO | G72: 287.35633 | M72: 01/Ene/2026
A73: Honorarios a personas fis residentes nal | B73: JESUS ALEJANDRO GALLARZA ORTEGA | C73: GASTOS DE ADMINISTRACIÓN | D73: OTROS | G73: 46093.1 | L73: 8620.69 | M73: 01/Ene/2026 | N73: Diario | O73: 281 | P73: Cuotas y suscripciones
A74: Depr de autom, autob, camiones, tractoc | B74: DEPRECIACIONES | C74: COGS | D74: OPERACIONES | G74: 791.67 | L74: 791.67 | M74: 01/Ene/2026 | N74: Diario | O74: 502 | P74: Depr de autom, autob, camiones, tractoc
A75: Depreciacion de equipo de computo | B75: DEPRECIACIONES | C75: GASTOS DE ADMINISTRACIÓN | D75: TÉCNICO | G75: 10169.653 | L75: 32688.17 | M75: 01/Ene/2026 | N75: Diario | O75: 502 | P75: Depreciación de equipo de cómputo
A76: Depreciacion de equipo de computo | B76: DEPRECIACIONES | C76: GASTOS DE ADMINISTRACIÓN | D76: RH | G76: 726.40378 | M76: 01/Ene/2026
A77: Depreciacion de equipo de computo | B77: DEPRECIACIONES | C77: GASTOS DE ADMINISTRACIÓN | D77: OPERACIONES | G77: 13801.672 | M77: 01/Ene/2026
A78: Depreciacion de equipo de computo | B78: DEPRECIACIONES | C78: GASTOS DE ADMINISTRACIÓN | D78: FINANZAS | G78: 1937.0767 | M78: 01/Ene/2026
A79: Depreciacion de equipo de computo | B79: DEPRECIACIONES | C79: GASTOS DE ADMINISTRACIÓN | D79: BRAND BUILDING | G79: 1089.6057 | M79: 01/Ene/2026
A80: Depreciacion de equipo de computo | B80: DEPRECIACIONES | C80: GASTOS DE ADMINISTRACIÓN | D80: COMERCIAL | G80: 3874.1535 | M80: 01/Ene/2026
A81: Depreciacion de equipo de computo | B81: DEPRECIACIONES | C81: GASTOS DE ADMINISTRACIÓN | D81: DIRECTIVO | G81: 1089.6057 | M81: 01/Ene/2026
A82: Depreciacion de mobiliario y eq de ofic | B82: DEPRECIACIONES | C82: GASTOS DE ADMINISTRACIÓN | D82: TÉCNICO | G82: 2908.5871 | L82: 9349.03 | M82: 01/Ene/2026 | N82: Diario | O82: 502 | P82: Depreciación de mobiliario y eq de ofic
A83: Depreciacion de mobiliario y eq de ofic | B83: DEPRECIACIONES | C83: GASTOS DE ADMINISTRACIÓN | D83: RH | G83: 207.75622 | M83: 01/Ene/2026
A84: Depreciacion de mobiliario y eq de ofic | B84: DEPRECIACIONES | C84: COGS | D84: OPERACIONES | G84: 3947.3682 | M84: 01/Ene/2026
A85: Depreciacion de mobiliario y eq de ofic | B85: DEPRECIACIONES | C85: GASTOS DE ADMINISTRACIÓN | D85: FINANZAS | G85: 554.01659 | M85: 01/Ene/2026
A86: Depreciacion de mobiliario y eq de ofic | B86: DEPRECIACIONES | C86: GASTOS DE ADMINISTRACIÓN | D86: BRAND BUILDING | G86: 311.63433 | M86: 01/Ene/2026
A87: Depreciacion de mobiliario y eq de ofic | B87: DEPRECIACIONES | C87: GASTOS DE ADMINISTRACIÓN | D87: COMERCIAL | G87: 1108.0332 | M87: 01/Ene/2026
A88: Depreciacion de mobiliario y eq de ofic | B88: DEPRECIACIONES | C88: GASTOS DE ADMINISTRACIÓN | D88: DIRECTIVO | G88: 311.63433 | M88: 01/Ene/2026
A89: Depreciacion de otros activos fijos | B89: DEPRECIACIONES | C89: POR CLASIFICAR | G89: 5539.44 | L89: 5539.44 | M89: 01/Ene/2026 | N89: Diario | O89: 502 | P89: Depreciación de otros activos fijos
A90: Depreciacion de otros activos fijos | B90: DEPRECIACIONES | C90: POR CLASIFICAR | G90: 5828.89 | L90: 5828.89 | M90: 01/Ene/2026 | N90: Diario | O90: 502 | P90: Depreciación de instalación
A91: Dictamenes | B91: DISEÑO EDIFICACION Y ASESORIA CIVIL | C91: COGS | D91: OPERACIONES | G91: 8000 | L91: 8000 | M91: 01/Ene/2026 | N91: Diario | O91: 278 | P91: Dictamenes
A92: Dictamenes | B92: DISTRIBUIDORA PENINSULUX | C92: COGS | D92: OPERACIONES | G92: 24124.7
A93: Registros Gubernamentales | B93: GOBIERNO DEL ESTADO DE MEXICO | C93: GASTOS DE ADMINISTRACIÓN | D93: OTROS | G93: 8208 | L93: 24124.7 | M93: 01/Ene/2026 | N93: Diario | O93: 278 | P93: Dictamenes
A94: Dictamenes | B94: INOX, DISEÑO ARQUITECTONICO | C94: COGS | D94: OPERACIONES | G94: 14000 | L94: 14000 | M94: 01/Ene/2026 | N94: Diario | O94: 278 | P94: Dictamenes
A95: Dictamenes | B95: INOX, DISEÑO ARQUITECTONICO | C95: COGS | D95: OPERACIONES | G95: 18500 | L95: 18500 | M95: 01/Ene/2026 | N95: Diario | O95: 278 | P95: Dictamenes
A96: Dictamenes | B96: JOSE LUIS JACINTO DE LA TORRE | C96: COGS | D96: OPERACIONES | G96: 3097.23 | L96: 3097.23 | M96: 01/Ene/2026 | N96: Diario | O96: 278 | P96: Dictamenes
A97: Dictamenes | B97: JOSE LUIS JACINTO DE LA TORRE | C97: COGS | D97: OPERACIONES | G97: 6000 | L97: 4386.83 | M97: 01/Ene/2026 | N97: Diario | O97: 278 | P97: Dictamenes
A98: Dictamenes | B98: LUIS JAIME PARTIDA HERRERA | C98: COGS | D98: OPERACIONES | G98: 6500 | L98: 6000 | M98: 01/Ene/2026 | N98: Diario | O98: 278 | P98: Dictamenes
A99: Dictamenes | B99: MANUEL ARTURO DIAZ CARDIEL | C99: COGS | D99: OPERACIONES | G99: 18000 | L99: 6500 | M99: 01/Ene/2026 | N99: Diario | O99: 278 | P99: Dictamenes
A100: Dictamenes | B100: MARCELA PADRON BARRERA | C100: COGS | D100: OPERACIONES | G100: 13200 | L100: 18000 | M100: 01/Ene/2026 | N100: Diario | O100: 278 | P100: Dictamenes
...

Sheet respaldo sueldos y salarios
A1: CATEGORIA_NETSUITE | B1: Concepto | C1: IS | D1: ÁREA | E1: ZONA PPTO | F1: EMPLEADO | G1: MONTO | H1: PERIODO | I1: AREA | J1: ZONA | K1: PCT_POND | L1: Cargos | M1: Fecha | N1: Tipo | O1: Número | P1: Clasf Efs | Q1: ID SGN | R1: PUESTO | S1: PAGADORA
A2: Sueldos y salarios | B2: ACEVEDO LOPEZ GERMAIN | C2: COGS | D2: OPERACIONES | E2: CENTRO | F2: GERMAIN ACEVEDO LOPEZ | G2: 12269.305 | H2: ENERO
A3: Sueldos y salarios | B3: ACEVEDO LOPEZ GERMAIN | C3: COGS | D3: OPERACIONES | E3: CENTRO | F3: GERMAIN ACEVEDO LOPEZ | G3: 12620.03 | H3: MARZO
A4: Sueldos y salarios | B4: ACEVEDO LOPEZ GERMAIN | C4: COGS | D4: OPERACIONES | E4: CENTRO | F4: GERMAIN ACEVEDO LOPEZ | G4: 10861.391 | H4: FEBRERO
A5: Sueldos y salarios | B5: ACEVEDO LOPEZ GERMAIN | C5: COGS | D5: OPERACIONES | E5: CENTRO | F5: GERMAIN ACEVEDO LOPEZ | G5: 10842.303 | H5: ABRIL
A6: Sueldos y salarios | B6: AGUILAR MORALES EMANUEL | C6: COGS | D6: OPERACIONES | E6: CENTRO | F6: EMANUEL AGUILAR MORALES | G6: 24075.35 | H6: MARZO
A7: Sueldos y salarios | B7: AGUILAR MORALES EMANUEL | C7: COGS | D7: OPERACIONES | E7: CENTRO | F7: EMANUEL AGUILAR MORALES | G7: 14312.507 | H7: FEBRERO
A8: Sueldos y salarios | B8: ALCANTARA SEGURA MIRIAM JOSEFINA | C8: GASTOS DE ADMINISTRACIÓN | D8: TÉCNICO | F8: MIRIAM JOSEFINA ALCANTARA SEGURA | G8: 14378.848 | H8: ENERO
A9: Sueldos y salarios | B9: ALCANTARA SEGURA MIRIAM JOSEFINA | C9: GASTOS DE ADMINISTRACIÓN | D9: TÉCNICO | F9: MIRIAM JOSEFINA ALCANTARA SEGURA | G9: 15993.283 | H9: MARZO
A10: Sueldos y salarios | B10: ALCANTARA SEGURA MIRIAM JOSEFINA | C10: GASTOS DE ADMINISTRACIÓN | D10: TÉCNICO | F10: MIRIAM JOSEFINA ALCANTARA SEGURA | G10: 15770.154 | H10: FEBRERO
A11: Sueldos y salarios | B11: ALMADA NOZATO DANNA PAOLA | C11: COGS | D11: OPERACIONES | E11: PEPSICO SE | F11: DANNA PAOLA ALMADA NOZATO | G11: 13779.069 | H11: MARZO
A12: Sueldos y salarios | B12: ALMADA NOZATO DANNA PAOLA | C12: COGS | D12: OPERACIONES | E12: PEPSICO SE | F12: DANNA PAOLA ALMADA NOZATO | G12: 13493.097 | H12: FEBRERO
A13: Sueldos y salarios | B13: ALMADA NOZATO DANNA PAOLA | C13: COGS | D13: OPERACIONES | E13: PEPSICO SE | F13: DANNA PAOLA ALMADA NOZATO | G13: 13751.394 | H13: ENERO
A14: Sueldos y salarios | B14: ALMANZA GUZMAN FREDDY JESUS | C14: GASTOS DE ADMINISTRACIÓN | D14: BRAND BUILDING | F14: FREDDY JESUS ALMANZA GUZMAN | G14: 19234.553 | H14: ENERO
A15: Sueldos y salarios | B15: ALMANZA GUZMAN FREDDY JESUS | C15: GASTOS DE ADMINISTRACIÓN | D15: BRAND BUILDING | F15: FREDDY JESUS ALMANZA GUZMAN | G15: 23356.679 | H15: MARZO
A16: Sueldos y salarios | B16: ALMANZA GUZMAN FREDDY JESUS | C16: GASTOS DE ADMINISTRACIÓN | D16: BRAND BUILDING | F16: FREDDY JESUS ALMANZA GUZMAN | G16: 18896.204 | H16: FEBRERO
A17: Sueldos y salarios | B17: ALTAMIRANO DIAZ CIELO ANEL | C17: COGS | D17: OPERACIONES | E17: NOROESTE | F17: CIELO ANEL ALTAMIRANO DIAZ | G17: 11487.986 | H17: MARZO
A18: Sueldos y salarios | B18: ALTAMIRANO DIAZ CIELO ANEL | C18: COGS | D18: OPERACIONES | E18: NOROESTE | F18: CIELO ANEL ALTAMIRANO DIAZ | G18: 17785.736 | H18: FEBRERO
A19: Sueldos y salarios | B19: ALTAMIRANO DIAZ CIELO ANEL | C19: COGS | D19: OPERACIONES | E19: NOROESTE | F19: CIELO ANEL ALTAMIRANO DIAZ | G19: 18125.363 | H19: ENERO
A20: Sueldos y salarios | B20: ALVAREZ CABRERA RODRIGO | C20: COGS | D20: OPERACIONES | E20: OCCIDENTE | F20: RODRIGO ALVAREZ CABRERA | G20: 19431.204 | H20: FEBRERO
A21: Sueldos y salarios | B21: ALVAREZ CABRERA RODRIGO | C21: COGS | D21: OPERACIONES | E21: OCCIDENTE | F21: RODRIGO ALVAREZ CABRERA | G21: 19779.553 | H21: ENERO
A22: Sueldos y salarios | B22: ALVAREZ CABRERA RODRIGO | C22: COGS | D22: OPERACIONES | E22: OCCIDENTE | F22: RODRIGO ALVAREZ CABRERA | G22: 15802.44 | H22: MARZO
A23: Sueldos y salarios | B23: ALVAREZ CABRERA RODRIGO | C23: COGS | D23: OPERACIONES | E23: OCCIDENTE | F23: RODRIGO ALVAREZ CABRERA | G23: 10060.44 | H23: ABRIL
A24: Sueldos y salarios | B24: ALVAREZ CHAVEZ VICTOR MANUEL | C24: GASTOS DE ADMINISTRACIÓN | D24: COMERCIAL | F24: VICTOR MANUEL ALVAREZ CHAVEZ | G24: 18848.226 | H24: FEBRERO
A25: Sueldos y salarios | B25: ALVAREZ CHAVEZ VICTOR MANUEL | C25: GASTOS DE ADMINISTRACIÓN | D25: COMERCIAL | F25: VICTOR MANUEL ALVAREZ CHAVEZ | G25: 19080.558 | H25: MARZO
A26: Sueldos y salarios | B26: ALVAREZ CHAVEZ VICTOR MANUEL | C26: GASTOS DE ADMINISTRACIÓN | D26: COMERCIAL | F26: VICTOR MANUEL ALVAREZ CHAVEZ | G26: 19207.063 | H26: ENERO
A27: Sueldos y salarios | B27: AREVALO CERVANTES MIGUEL ANGEL | C27: GASTOS DE ADMINISTRACIÓN | D27: BRAND BUILDING | F27: MIGUEL ANGEL AREVALO CERVANTES | G27: 20193.283 | H27: MARZO
A28: Sueldos y salarios | B28: AREVALO CERVANTES MIGUEL ANGEL | C28: GASTOS DE ADMINISTRACIÓN | D28: BRAND BUILDING | F28: MIGUEL ANGEL AREVALO CERVANTES | G28: 20050.154 | H28: FEBRERO
A29: Sueldos y salarios | B29: AREVALO CERVANTES MIGUEL ANGEL | C29: GASTOS DE ADMINISTRACIÓN | D29: BRAND BUILDING | F29: MIGUEL ANGEL AREVALO CERVANTES | G29: 20427.175 | H29: ENERO
A30: Sueldos y salarios | B30: ARRAZOLA SANTAELLA ALBERTO NICOLAS | C30: COGS | D30: OPERACIONES | E30: SURESTE | F30: ALBERTO NICOLAS ARRAZOLA SANTAELLA | G30: 8107.3609 | H30: FEBRERO
A31: Sueldos y salarios | B31: ARRAZOLA SANTAELLA ALBERTO NICOLAS | C31: COGS | D31: OPERACIONES | E31: SURESTE | F31: ALBERTO NICOLAS ARRAZOLA SANTAELLA | G31: 20303.011 | H31: MARZO
A32: Sueldos y salarios | B32: ARRAZOLA SANTAELLA ALBERTO NICOLAS | C32: COGS | D32: OPERACIONES | E32: SURESTE | F32: ALBERTO NICOLAS ARRAZOLA SANTAELLA | G32: 18427.44 | H32: ABRIL
A33: Sueldos y salarios | B33: ARREOLA ALATRISTE ALEXANDRA ESTEPHANIA | C33: COGS | D33: TÉCNICO | F33: ALEXANDRA ESTEPHANIA ARREOLA ALATRISTE | G33: 13202.829 | H33: MARZO
A34: Sueldos y salarios | B34: ARREOLA ALATRISTE ALEXANDRA ESTEPHANIA | C34: COGS | D34: TÉCNICO | F34: ALEXANDRA ESTEPHANIA ARREOLA ALATRISTE | G34: 10059.743 | H34: FEBRERO
A35: Sueldos y salarios | B35: ARREOLA ALATRISTE ALEXANDRA ESTEPHANIA | C35: COGS | D35: TÉCNICO | F35: ALEXANDRA ESTEPHANIA ARREOLA ALATRISTE | G35: 7350 | H35: ENERO
A36: Sueldos y salarios | B36: ARVIZU ESTRADA ALBA MARIANA | C36: COGS | D36: OPERACIONES | E36: CENTRO | F36: ALBA MARIANA ARVIZU ESTRADA | G36: 15770.03 | H36: MARZO
A37: Sueldos y salarios | B37: ARVIZU ESTRADA ALBA MARIANA | C37: COGS | D37: OPERACIONES | E37: CENTRO | F37: ALBA MARIANA ARVIZU ESTRADA | G37: 14071.391 | H37: FEBRERO
A38: Sueldos y salarios | B38: ARVIZU ESTRADA ALBA MARIANA | C38: COGS | D38: OPERACIONES | E38: CENTRO | F38: ALBA MARIANA ARVIZU ESTRADA | G38: 3209.1708 | H38: ENERO
A39: Sueldos y salarios | B39: ARVIZU ESTRADA ALBA MARIANA | C39: COGS | D39: OPERACIONES | E39: CENTRO | F39: ALBA MARIANA ARVIZU ESTRADA | G39: 15277.44 | H39: ABRIL
A40: Sueldos y salarios | B40: BACA AGUIRRE ANTONIO | C40: COGS | D40: OPERACIONES | E40: NOROESTE | F40: ANTONIO BACA AGUIRRE | G40: 17823.58 | H40: FEBRERO
A41: Sueldos y salarios | B41: BACA AGUIRRE ANTONIO | C41: COGS | D41: OPERACIONES | E41: NOROESTE | F41: ANTONIO BACA AGUIRRE | G41: 18141.678 | H41: ENERO
A42: Sueldos y salarios | B42: BACA AGUIRRE ANTONIO | C42: COGS | D42: OPERACIONES | E42: NOROESTE | F42: ANTONIO BACA AGUIRRE | G42: 10866.02 | H42: MARZO
A43: Sueldos y salarios | B43: BACA AGUIRRE ANTONIO | C43: COGS | D43: OPERACIONES | E43: NOROESTE | F43: ANTONIO BACA AGUIRRE | G43: 7247.5095 | H43: ABRIL
A44: Sueldos y salarios | B44: BALTAZAR RODRIGUEZ SERGIO ALBERTO | C44: COGS | D44: OPERACIONES | E44: NORTE | F44: SERGIO ALBERTO BALTAZAR RODRIGUEZ | G44: 16006.679 | H44: MARZO
A45: Sueldos y salarios | B45: BALTAZAR RODRIGUEZ SERGIO ALBERTO | C45: COGS | D45: OPERACIONES | E45: NORTE | F45: SERGIO ALBERTO BALTAZAR RODRIGUEZ | G45: 15686.204 | H45: FEBRERO
A46: Sueldos y salarios | B46: BALTAZAR RODRIGUEZ SERGIO ALBERTO | C46: COGS | D46: OPERACIONES | E46: NORTE | F46: SERGIO ALBERTO BALTAZAR RODRIGUEZ | G46: 15964.553 | H46: ENERO
A47: Sueldos y salarios | B47: BERNAL MONROY MARIA DEL PILAR JAZMINE | C47: COGS | D47: OPERACIONES | E47: CENTRO | F47: MARIA DEL PILAR JAZMINE BERNAL MONROY | G47: 14885.847 | H47: ENERO
... A49: Sueldos y salarios | B49: BERNAL MONROY MARIA DEL PILAR JAZMINE | C49: COGS | D49: OPERACIONES | E49: CENTRO | F49: MARIA DEL PILAR JAZMINE BERNAL MONROY | G49: 16766.512 | H49: FEBRERO
A50: Sueldos y salarios | B50: FRANCISCO JAVIER BERRUETA GUTIERREZ | C50: OTROS Facturación / GASTOS | D50: SOCIOS | F50: FRANCISCO JAVIER BERRUETA GUTIERREZ | G50: 143227.36 | H50: ENERO
A51: Sueldos y salarios | B51: FRANCISCO JAVIER BERRUETA GUTIERREZ | C51: OTROS Facturación / GASTOS | D51: SOCIOS | F51: FRANCISCO JAVIER BERRUETA GUTIERREZ | G51: 143228.86 | H51: FEBRERO
A52: Sueldos y salarios | B52: FRANCISCO JAVIER BERRUETA GUTIERREZ | C52: OTROS Facturación / GASTOS | D52: SOCIOS | F52: FRANCISCO JAVIER BERRUETA GUTIERREZ | G52: 143228.86 | H52: MARZO
A53: Sueldos y salarios | B53: FRANCISCO JAVIER BERRUETA GUTIERREZ | C53: OTROS Facturación / GASTOS | D53: SOCIOS | F53: FRANCISCO JAVIER BERRUETA GUTIERREZ | G53: 143228.86 | H53: ABRIL
A54: Sueldos y salarios | B54: JOSE DE JESUS RAMIREZ GONZALEZ | C54: COGS | D54: OPERACIONES | F54: JOSE DE JESUS RAMIREZ GONZALEZ | G54: 20127.76 | H54: ENERO
A55: Sueldos y salarios | B55: LAE | C55: OTROS Facturación / GASTOS | D55: OTROS | F55: SUSANA RUTH GARCIA MARTINEZ | G55: 12999.9 | H55: ENERO
A56: Sueldos y salarios | B56: LAE | C56: OTROS Facturación / GASTOS | D56: OTROS | F56: SUSANA RUTH GARCIA MARTINEZ | G56: 12999.9 | H56: FEBRERO
A57: Sueldos y salarios | B57: LAE | C57: OTROS Facturación / GASTOS | D57: OTROS | F57: SUSANA RUTH GARCIA MARTINEZ | G57: 12999.9 | H57: MARZO
A58: Sueldos y salarios | B58: LAE | C58: OTROS Facturación / GASTOS | D58: OTROS | F58: SUSANA RUTH GARCIA MARTINEZ | G58: 12999.9 | H58: ABRIL
A59: Sueldos y salarios | B59: LAE | C59: OTROS Facturación / GASTOS | D59: OTROS | F59: DIEGO GUERRA GUTIERREZ | G59: 12999.9 | H59: ENERO
A60: Sueldos y salarios | B60: LAE | C60: OTROS Facturación / GASTOS | D60: OTROS | F60: DIEGO GUERRA GUTIERREZ | G60: 12999.9 | H60: FEBRERO
A61: Sueldos y salarios | B61: LAE | C61: OTROS Facturación / GASTOS | D61: OTROS | F61: DIEGO GUERRA GUTIERREZ | G61: 12999.9 | H61: MARZO
... A85: Sueldos y salarios | B85: CABRERA TERAN ARTURO | C85: GASTOS DE ADMINISTRACIÓN | D85: BRAND BUILDING | F85: ARTURO CABRERA TERAN | G85: 14418.283 | H85: MARZO
A86: Sueldos y salarios | B86: CAMACHO MONCADA MARIA JOSE | C86: COGS | D86: OPERACIONES | E86: OCCIDENTE | F86: MARIA JOSE CAMACHO MONCADA | G86: 15633.097 | H86: FEBRERO
A87: Sueldos y salarios | B87: CAMACHO MONCADA MARIA JOSE | C87: COGS | D87: OPERACIONES | E87: OCCIDENTE | F87: MARIA JOSE CAMACHO MONCADA | G87: 3181.7528 | H87: ENERO
A88: Sueldos y salarios | B88: CAMACHO MONCADA MARIA JOSE | C88: COGS | D88: OPERACIONES | E88: OCCIDENTE | F88: MARIA JOSE CAMACHO MONCADA | G88: 15924.755 | H88: MARZO
A89: Sueldos y salarios | B89: CAMACHO NUÑO IVAN ANGEL | C89: COGS | D89: OPERACIONES | E89: OCCIDENTE | F89: IVAN ANGEL CAMACHO NUÑO | G89: 17051.678 | H89: ENERO
A90: Sueldos y salarios | B90: CAMACHO NUÑO IVAN ANGEL | C90: COGS | D90: OPERACIONES | E90: OCCIDENTE | F90: IVAN ANGEL CAMACHO NUÑO | G90: 8493.071 | H90: FEBRERO
A91: Sueldos y salarios | B91: CATARINO TENORIO GRISELDA | C91: COGS | D91: OPERACIONES | E91: PEPSICO OCC | F91: GRISELDA CATARINO TENORIO | G91: 14652.097 | H91: FEBRERO
A92: Sueldos y salarios | B92: CATARINO TENORIO GRISELDA | C92: COGS | D92: OPERACIONES | E92: PEPSICO OCC | F92: GRISELDA CATARINO TENORIO | G92: 13969.394 | H92: ENERO
A93: Sueldos y salarios | B93: CATARINO TENORIO GRISELDA | C93: COGS | D93: OPERACIONES | E93: PEPSICO OCC | F93: GRISELDA CATARINO TENORIO | G93: 15924.755 | H93: MARZO
A94: Sueldos y salarios | B94: CERVANTES AGUILAR JENNIFER MICHELLE | C94: OTROS Facturación / GASTOS | D94: TÉCNICO | F94: JENNIFER MICHELLE CERVANTES AGUILAR | G94: 17571.832 | H94: MARZO
A95: Sueldos y salarios | B95: CERVANTES AGUILAR JENNIFER MICHELLE | C95: OTROS Facturación / GASTOS | D95: TÉCNICO | F95: JENNIFER MICHELLE CERVANTES AGUILAR | G95: 17355.964 | H95: FEBRERO
A96: Sueldos y salarios | B96: CERVANTES AGUILAR JENNIFER MICHELLE | C96: OTROS Facturación / GASTOS | D96: TÉCNICO | F96: JENNIFER MICHELLE CERVANTES AGUILAR | G96: 17763.365 | H96: ENERO
A97: Sueldos y salarios | B97: CORNEJO JIMENEZ MARLEN | C97: COGS | D97: OPERACIONES | E97: PEPSICO NAC. | F97: MARLEN CORNEJO JIMENEZ | G97: 26433.846 | H97: MARZO
A98: Sueldos y salarios | B98: CORNEJO JIMENEZ MARLEN | C98: COGS | D98: OPERACIONES | E98: PEPSICO NAC. | F98: MARLEN CORNEJO JIMENEZ | G98: 18888.877 | H98: FEBRERO
A99: Sueldos y salarios | B99: CORNEJO JIMENEZ MARLEN | C99: COGS | D99: OPERACIONES | E99: PEPSICO NAC. | F99: MARLEN CORNEJO JIMENEZ | G99: 20299.695 | H99: ENERO
A100: Sueldos y salarios | B100: CRISOSTOMO ARENAS MARIA DE LOURDES | C100: COGS | D100: OPERACIONES | F100: MARIA DE LOURDES CRISOSTOMO ARENAS | G100: 16929.069 | H100: MARZO
A101: Sueldos y salarios | B101: CRISOSTOMO ARENAS MARIA DE LOURDES | C101: COGS | D101: OPERACIONES | F101: MARIA DE LOURDES CRISOSTOMO ARENAS | G101: 4494.6253 | H101: FEBRERO
A102: Sueldos y salarios | B102: CRUZ GARCIA KELLY | C102: GASTOS DE ADMINISTRACIÓN | D102: RH | F102: KELLY CRUZ GARCIA | G102: 19146.252 | H102: MARZO
A103: Sueldos y salarios | B103: CRUZ GARCIA KELLY | C103: GASTOS DE ADMINISTRACIÓN | D103: RH | F103: KELLY CRUZ GARCIA | G103: 15198.144 | H103: ENERO
A104: Sueldos y salarios | B104: CRUZ GARCIA KELLY | C104: GASTOS DE ADMINISTRACIÓN | D104: RH | F104: KELLY CRUZ GARCIA | G104: 17892.853 | H104: FEBRERO
A105: Sueldos y salarios | B105: CRUZ RODRIGUEZ MARINA CRISTHEL | C105: COGS | D105: OPERACIONES | F105: MARINA CRISTHEL CRUZ RODRIGUEZ | G105: 7350 | H105: ENERO
A106: Sueldos y salarios | B106: CRUZ RODRIGUEZ MARINA CRISTHEL | C106: COGS | D106: OPERACIONES | F106: MARINA CRISTHEL CRUZ RODRIGUEZ | G106: 3675 | H106: MARZO
A107: Sueldos y salarios | B107: CRUZ RODRIGUEZ MARINA CRISTHEL | C107: COGS | D107: OPERACIONES | F107: MARINA CRISTHEL CRUZ RODRIGUEZ | G107: 7350 | H107: FEBRERO
A108: Sueldos y salarios | B108: DE LA VEGA ALCALA BIANCA FRANCISCA | C108: GASTOS DE ADMINISTRACIÓN | D108: COMERCIAL | F108: VEGA ALCALA BIANCA FRANCISCA DE LA | G108: 20297.063 | H108: ENERO
A109: Sueldos y salarios | B109: DE LA VEGA ALCALA BIANCA FRANCISCA | C109: GASTOS DE ADMINISTRACIÓN | D109: COMERCIAL | F109: VEGA ALCALA BIANCA FRANCISCA DE LA | G109: 20130.558 | H109: MARZO
A110: Sueldos y salarios | B110: DE LA VEGA ALCALA BIANCA FRANCISCA | C110: GASTOS DE ADMINISTRACIÓN | D110: COMERCIAL | F110: VEGA ALCALA BIANCA FRANCISCA DE LA | G110: 19918.226 | H110: FEBRERO
A111: Sueldos y salarios | B111: DE LOS SANTOS ALARCON GIOVANNI ALEXANDER | C111: COGS | D111: OPERACIONES | E111: SURESTE | F111: SANTOS ALARCON GIOVANNI ALEXANDER DE LOS | G111: 16974.755 | H111: MARZO
A112: Sueldos y salarios | B112: DE LOS SANTOS ALARCON GIOVANNI ALEXANDER | C112: COGS | D112: OPERACIONES | E112: SURESTE | F112: SANTOS ALARCON GIOVANNI ALEXANDER DE LOS | G112: 13884.568 | H112: FEBRERO
A113: Sueldos y salarios | B113: DIAZ GARCIA MARIA NARELI | C113: COGS | D113: OPERACIONES | E113: SURESTE | F113: MARIA NARELI DIAZ GARCIA | G113: 15635.662 | H113: FEBRERO
A114: Sueldos y salarios | B114: DIAZ GARCIA MARIA NARELI | C114: COGS | D114: OPERACIONES | E114: SURESTE | F114: MARIA NARELI DIAZ GARCIA | G114: 15934.228 | H114: ENERO
A115: Sueldos y salarios | B115: DIAZ GARCIA MARIA NARELI | C115: COGS | D115: OPERACIONES | E115: SURESTE | F115: MARIA NARELI DIAZ GARCIA | G115: 15927.656 | H115: MARZO
A116: Sueldos y salarios | B116: DOMINGUEZ CORTES ERICK ALAN | C116: GASTOS DE ADMINISTRACIÓN | D116: TÉCNICO | F116: ERICK ALAN DOMINGUEZ CORTES | G116: 23200.976 | H116: FEBRERO
A117: Sueldos y salarios | B117: DOMINGUEZ CORTES ERICK ALAN | C117: GASTOS DE ADMINISTRACIÓN | D117: TÉCNICO | F117: ERICK ALAN DOMINGUEZ CORTES | G117: 22655.843 | H117: ENERO
A118: Sueldos y salarios | B118: DOMINGUEZ CORTES ERICK ALAN | C118: GASTOS DE ADMINISTRACIÓN | D118: TÉCNICO | F118: ERICK ALAN DOMINGUEZ CORTES | G118: 20527.44 | H118: MARZO
A119: Sueldos y salarios | B119: DOMINGUEZ CORTES ERICK ALAN | C119: GASTOS DE ADMINISTRACIÓN | D119: TÉCNICO | F119: ERICK ALAN DOMINGUEZ CORTES | G119: 20527.44 | H119: ABRIL
A120: Sueldos y salarios | B120: DOMINGUEZ LOPEZ IRACEMA | C120: COGS | D120: OPERACIONES | F120: IRACEMA DOMINGUEZ LOPEZ | G120: 10128.071 | H120: FEBRERO
A121: Sueldos y salarios | B121: DOMINGUEZ LOPEZ IRACEMA | C121: COGS | D121: OPERACIONES | F121: IRACEMA DOMINGUEZ LOPEZ | G121: 20321.678 | H121: ENERO
A122: Sueldos y salarios | B122: DUARTE RODRIGUEZ GINA ARLETTE | C122: GASTOS DE ADMINISTRACIÓN | D122: DIRECTIVO | F122: GINA ARLETTE DUARTE RODRIGUEZ | G122: 34524.9 | H122: FEBRERO
A123: Sueldos y salarios | B123: DUARTE RODRIGUEZ GINA ARLETTE | C123: GASTOS DE ADMINISTRACIÓN | D123: DIRECTIVO | F123: GINA ARLETTE DUARTE RODRIGUEZ | G123: 34524.9 | H123: MARZO
A124: Sueldos y salarios | B124: DUARTE RODRIGUEZ GINA ARLETTE | C124: GASTOS DE ADMINISTRACIÓN | D124: DIRECTIVO | F124: GINA ARLETTE DUARTE RODRIGUEZ | G124: 34524.9 | H124: ENERO
...

Sheet Sheet2
A1: CATEGORIA_NETSUITE | B1: Concepto | C1: IS | D1: ÁREA | E1: ZONA PPTO | F1: EMPLEADO | G1: MONTO | H1: PERIODO | I1: AREA | J1: ZONA | K1: PCT_POND | L1: Cargos | M1: Fecha | N1: Tipo | O1: Número | P1: Clasf Efs | Q1: ID SGN | R1: PUESTO | S1: PAGADORA
A2: Sueldos y salarios | B2: ACEVEDO LOPEZ GERMAIN | C2: COGS | D2: OPERACIONES | E2: CENTRO | F2: GERMAIN ACEVEDO LOPEZ | G2: 12269.305 | H2: ENERO
A3: Sueldos y salarios | B3: ACEVEDO LOPEZ GERMAIN | C3: COGS | D3: OPERACIONES | E3: CENTRO | F3: GERMAIN ACEVEDO LOPEZ | G3: =2676.24+nom_interna!C55+nom_interna!I53 -> 12620.03 | H3: MARZO
A4: Sueldos y salarios | B4: ACEVEDO LOPEZ GERMAIN | C4: COGS | D4: OPERACIONES | E4: CENTRO | F4: GERMAIN ACEVEDO LOPEZ | G4: =9286.191037+nom_interna!I30 -> 10861.391 | H4: FEBRERO
A5: Sueldos y salarios | B5: ACEVEDO LOPEZ GERMAIN | C5: COGS | D5: OPERACIONES | E5: CENTRO | F5: GERMAIN ACEVEDO LOPEZ | G5: =1391.103+nom_interna!C107+nom_interna!I107 -> 10842.303 | H5: ABRIL
A6: Sueldos y salarios | B6: AGUILAR MORALES EMANUEL | C6: COGS | D6: OPERACIONES | E6: CENTRO | F6: EMANUEL AGUILAR MORALES | G6: 24075.35 | H6: MARZO
A7: Sueldos y salarios | B7: AGUILAR MORALES EMANUEL | C7: COGS | D7: OPERACIONES | E7: CENTRO | F7: EMANUEL AGUILAR MORALES | G7: 14312.507 | H7: FEBRERO
A8: Sueldos y salarios | B8: ALCANTARA SEGURA MIRIAM JOSEFINA | C8: GASTOS DE ADMINISTRACIÓN | D8: TÉCNICO | F8: MIRIAM JOSEFINA ALCANTARA SEGURA | G8: 14378.848 | H8: ENERO
A9: Sueldos y salarios | B9: ALCANTARA SEGURA MIRIAM JOSEFINA | C9: GASTOS DE ADMINISTRACIÓN | D9: TÉCNICO | F9: MIRIAM JOSEFINA ALCANTARA SEGURA | G9: 15993.283 | H9: MARZO
A10: Sueldos y salarios | B10: ALCANTARA SEGURA MIRIAM JOSEFINA | C10: GASTOS DE ADMINISTRACIÓN | D10: TÉCNICO | F10: MIRIAM JOSEFINA ALCANTARA SEGURA | G10: 15770.154 | H10: FEBRERO
A11: Sueldos y salarios | B11: ALMADA NOZATO DANNA PAOLA | C11: COGS | D11: OPERACIONES | E11: PEPSICO SE | F11: DANNA PAOLA ALMADA NOZATO | G11: 13779.069 | H11: MARZO
A12: Sueldos y salarios | B12: ALMADA NOZATO DANNA PAOLA | C12: COGS | D12: OPERACIONES | E12: PEPSICO SE | F12: DANNA PAOLA ALMADA NOZATO | G12: 13493.097 | H12: FEBRERO
A13: Sueldos y salarios | B13: ALMADA NOZATO DANNA PAOLA | C13: COGS | D13: OPERACIONES | E13: PEPSICO SE | F13: DANNA PAOLA ALMADA NOZATO | G13: 13751.394 | H13: ENERO
A14: Sueldos y salarios | B14: ALMANZA GUZMAN FREDDY JESUS | C14: GASTOS DE ADMINISTRACIÓN | D14: BRAND BUILDING | F14: FREDDY JESUS ALMANZA GUZMAN | G14: 19234.553 | H14: ENERO
A15: Sueldos y salarios | B15: ALMANZA GUZMAN FREDDY JESUS | C15: GASTOS DE ADMINISTRACIÓN | D15: BRAND BUILDING | F15: FREDDY JESUS ALMANZA GUZMAN | G15: 23356.679 | H15: MARZO
A16: Sueldos y salarios | B16: ALMANZA GUZMAN FREDDY JESUS | C16: GASTOS DE ADMINISTRACIÓN | D16: BRAND BUILDING | F16: FREDDY JESUS ALMANZA GUZMAN | G16: 18896.204 | H16: FEBRERO
A17: Sueldos y salarios | B17: ALTAMIRANO DIAZ CIELO ANEL | C17: COGS | D17: OPERACIONES | E17: NOROESTE | F17: CIELO ANEL ALTAMIRANO DIAZ | G17: 11487.986 | H17: MARZO
A18: Sueldos y salarios | B18: ALTAMIRANO DIAZ CIELO ANEL | C18: COGS | D18: OPERACIONES | E18: NOROESTE | F18: CIELO ANEL ALTAMIRANO DIAZ | G18: 17785.736 | H18: FEBRERO
A19: Sueldos y salarios | B19: ALTAMIRANO DIAZ CIELO ANEL | C19: COGS | D19: OPERACIONES | E19: NOROESTE | F19: CIELO ANEL ALTAMIRANO DIAZ | G19: 18125.363 | H19: ENERO
A20: Sueldos y salarios | B20: ALVAREZ CABRERA RODRIGO | C20: COGS | D20: OPERACIONES | E20: OCCIDENTE | F20: RODRIGO ALVAREZ CABRERA | G20: 19431.204 | H20: FEBRERO
A21: Sueldos y salarios | B21: ALVAREZ CABRERA RODRIGO | C21: COGS | D21: OPERACIONES | E21: OCCIDENTE | F21: RODRIGO ALVAREZ CABRERA | G21: 19779.553 | H21: ENERO
A22: Sueldos y salarios | B22: ALVAREZ CABRERA RODRIGO | C22: COGS | D22: OPERACIONES | E22: OCCIDENTE | F22: RODRIGO ALVAREZ CABRERA | G22: =6351.24+nom_interna!L67 -> 15802.44 | H22: MARZO
A23: Sueldos y salarios | B23: ALVAREZ CABRERA RODRIGO | C23: COGS | D23: OPERACIONES | E23: OCCIDENTE | F23: RODRIGO ALVAREZ CABRERA | G23: =6351.24+nom_interna!L119 -> 10060.44 | H23: ABRIL
A24: Sueldos y salarios | B24: ALVAREZ CHAVEZ VICTOR MANUEL | C24: GASTOS DE ADMINISTRACIÓN | D24: COMERCIAL | F24: VICTOR MANUEL ALVAREZ CHAVEZ | G24: 18848.226 | H24: FEBRERO
A25: Sueldos y salarios | B25: ALVAREZ CHAVEZ VICTOR MANUEL | C25: GASTOS DE ADMINISTRACIÓN | D25: COMERCIAL | F25: VICTOR MANUEL ALVAREZ CHAVEZ | G25: 19080.558 | H25: MARZO
A26: Sueldos y salarios | B26: ALVAREZ CHAVEZ VICTOR MANUEL | C26: GASTOS DE ADMINISTRACIÓN | D26: COMERCIAL | F26: VICTOR MANUEL ALVAREZ CHAVEZ | G26: 19207.063 | H26: ENERO
A27: Sueldos y salarios | B27: AREVALO CERVANTES MIGUEL ANGEL | C27: GASTOS DE ADMINISTRACIÓN | D27: BRAND BUILDING | F27: MIGUEL ANGEL AREVALO CERVANTES | G27: 20193.283 | H27: MARZO
A28: Sueldos y salarios | B28: AREVALO CERVANTES MIGUEL ANGEL | C28: GASTOS DE ADMINISTRACIÓN | D28: BRAND BUILDING | F28: MIGUEL ANGEL AREVALO CERVANTES | G28: 20050.154 | H28: FEBRERO
A29: Sueldos y salarios | B29: AREVALO CERVANTES MIGUEL ANGEL | C29: GASTOS DE ADMINISTRACIÓN | D29: BRAND BUILDING | F29: MIGUEL ANGEL AREVALO CERVANTES | G29: 20427.175 | H29: ENERO
A30: Sueldos y salarios | B30: ARRAZOLA SANTAELLA ALBERTO NICOLAS | C30: COGS | D30: OPERACIONES | E30: SURESTE | F30: ALBERTO NICOLAS ARRAZOLA SANTAELLA | G30: 8107.3609 | H30: FEBRERO
A31: Sueldos y salarios | B31: ARRAZOLA SANTAELLA ALBERTO NICOLAS | C31: COGS | D31: OPERACIONES | E31: SURESTE | F31: ALBERTO NICOLAS ARRAZOLA SANTAELLA | G31: =15577.41058+nom_interna!I81 -> 20303.011 | H31: MARZO
A32: Sueldos y salarios | B32: ARRAZOLA SANTAELLA ALBERTO NICOLAS | C32: COGS | D32: OPERACIONES | E32: SURESTE | F32: ALBERTO NICOLAS ARRAZOLA SANTAELLA | G32: =8976.24+nom_interna!L135 -> 18427.44 | H32: ABRIL
A33: Sueldos y salarios | B33: ARREOLA ALATRISTE ALEXANDRA ESTEPHANIA | C33: COGS | D33: TÉCNICO | F33: ALEXANDRA ESTEPHANIA ARREOLA ALATRISTE | G33: 13202.829 | H33: MARZO
A34: Sueldos y salarios | B34: ARREOLA ALATRISTE ALEXANDRA ESTEPHANIA | C34: COGS | D34: TÉCNICO | F34: ALEXANDRA ESTEPHANIA ARREOLA ALATRISTE | G34: 10059.743 | H34: FEBRERO
A35: Sueldos y salarios | B35: ARREOLA ALATRISTE ALEXANDRA ESTEPHANIA | C35: COGS | D35: TÉCNICO | F35: ALEXANDRA ESTEPHANIA ARREOLA ALATRISTE | G35: 7350 | H35: ENERO
A36: Sueldos y salarios | B36: ARVIZU ESTRADA ALBA MARIANA | C36: COGS | D36: OPERACIONES | E36: CENTRO | F36: ALBA MARIANA ARVIZU ESTRADA | G36: =5826.24+nom_interna!C56+nom_interna!I54 -> 15770.03 | H36: MARZO
A37: Sueldos y salarios | B37: ARVIZU ESTRADA ALBA MARIANA | C37: COGS | D37: OPERACIONES | E37: CENTRO | F37: ALBA MARIANA ARVIZU ESTRADA | G37: =12496.191037+nom_interna!I31 -> 14071.391 | H37: FEBRERO
A38: Sueldos y salarios | B38: ARVIZU ESTRADA ALBA MARIANA | C38: COGS | D38: OPERACIONES | E38: CENTRO | F38: ALBA MARIANA ARVIZU ESTRADA | G38: 3209.1708 | H38: ENERO
A39: Sueldos y salarios | B39: ARVIZU ESTRADA ALBA MARIANA | C39: COGS | D39: OPERACIONES | E39: CENTRO | F39: ALBA MARIANA ARVIZU ESTRADA | G39: =5826.24+nom_interna!C108+nom_interna!I108 -> 15277.44 | H39: ABRIL
A40: Sueldos y salarios | B40: BACA AGUIRRE ANTONIO | C40: COGS | D40: OPERACIONES | E40: NOROESTE | F40: ANTONIO BACA AGUIRRE | G40: 17823.58 | H40: FEBRERO
A41: Sueldos y salarios | B41: BACA AGUIRRE ANTONIO | C41: COGS | D41: OPERACIONES | E41: NOROESTE | F41: ANTONIO BACA AGUIRRE | G41: 18141.678 | H41: ENERO
A42: Sueldos y salarios | B42: BACA AGUIRRE ANTONIO | C42: COGS | D42: OPERACIONES | E42: NOROESTE | F42: ANTONIO BACA AGUIRRE | G42: =4250.1795+nom_interna!L79 -> 10866.02 | H42: MARZO
A43: Sueldos y salarios | B43: BACA AGUIRRE ANTONIO | C43: COGS | D43: OPERACIONES | E43: NOROESTE | F43: ANTONIO BACA AGUIRRE | G43: =2967.7095+nom_interna!L131 -> 7247.5095 | H43: ABRIL
A44: Sueldos y salarios | B44: BALTAZAR RODRIGUEZ SERGIO ALBERTO | C44: COGS | D44: OPERACIONES | E44: NORTE | F44: SERGIO ALBERTO BALTAZAR RODRIGUEZ | G44: 16006.679 | H44: MARZO
A45: Sueldos y salarios | B45: BALTAZAR RODRIGUEZ SERGIO ALBERTO | C45: COGS | D45: OPERACIONES | E45: NORTE | F45: SERGIO ALBERTO BALTAZAR RODRIGUEZ | G45: 15686.204 | H45: FEBRERO
A46: Sueldos y salarios | B46: BALTAZAR RODRIGUEZ SERGIO ALBERTO | C46: COGS | D46: OPERACIONES | E46: NORTE | F46: SERGIO ALBERTO BALTAZAR RODRIGUEZ | G46: 15964.553 | H46: ENERO
A47: Sueldos y salarios | B47: BERNAL MONROY MARIA DEL PILAR JAZMINE | C47: COGS | D47: OPERACIONES | E47: CENTRO | F47: MARIA DEL PILAR JAZMINE BERNAL MONROY | G47: 14885.847 | H47: ENERO
A48: Sueldos y salarios | B48: BERNAL MONROY MARIA DEL PILAR JAZMINE | C48: COGS | D48: OPERACIONES | E48: CENTRO | F48: MARIA DEL PILAR JAZMINE BERNAL MONROY | G48: 17068.443 | H48: MARZO
A49: Sueldos y salarios | B49: BERNAL MONROY MARIA DEL PILAR JAZMINE | C49: COGS | D49: OPERACIONES | E49: CENTRO | F49: MARIA DEL PILAR JAZMINE BERNAL MONROY | G49: 16766.512 | H49: FEBRERO
A50: Sueldos y salarios | B50: FRANCISCO JAVIER BERRUETA GUTIERREZ | C50: OTROS Facturación / GASTOS | D50: SOCIOS | F50: FRANCISCO JAVIER BERRUETA GUTIERREZ | G50: =nom_interna!C4+nom_interna!I4 + 131250 -> 143227.36 | H50: ENERO
A51: Sueldos y salarios | B51: FRANCISCO JAVIER BERRUETA GUTIERREZ | C51: OTROS Facturación / GASTOS | D51: SOCIOS | F51: FRANCISCO JAVIER BERRUETA GUTIERREZ | G51: =nom_interna!C19+nom_interna!I20 + 131250 -> 143228.86 | H51: FEBRERO
A52: Sueldos y salarios | B52: FRANCISCO JAVIER BERRUETA GUTIERREZ | C52: OTROS Facturación / GASTOS | D52: SOCIOS | F52: FRANCISCO JAVIER BERRUETA GUTIERREZ | G52: =nom_interna!C45+nom_interna!I43 + 131250 -> 143228.86 | H52: MARZO
A53: Sueldos y salarios | B53: FRANCISCO JAVIER BERRUETA GUTIERREZ | C53: OTROS Facturación / GASTOS | D53: SOCIOS | F53: FRANCISCO JAVIER BERRUETA GUTIERREZ | G53: =nom_interna!C97+nom_interna!I97 + 131250 -> 143228.86 | H53: ABRIL
A54: Sueldos y salarios | B54: JOSE DE JESUS RAMIREZ GONZALEZ | C54: COGS | D54: OPERACIONES | F54: JOSE DE JESUS RAMIREZ GONZALEZ | G54: =nom_interna!C5+nom_interna!I5 -> 20127.76 | H54: ENERO
A55: Sueldos y salarios | B55: LAE | C55: OTROS Facturación / GASTOS | D55: OTROS | F55: SUSANA RUTH GARCIA MARTINEZ | G55: =nom_interna!C6+nom_interna!I6 -> 12999.9 | H55: ENERO
A56: Sueldos y salarios | B56: LAE | C56: OTROS Facturación / GASTOS | D56: OTROS | F56: SUSANA RUTH GARCIA MARTINEZ | G56: =nom_interna!C21+nom_interna!I22 -> 12999.9 | H56: FEBRERO
A57: Sueldos y salarios | B57: LAE | C57: OTROS Facturación / GASTOS | D57: OTROS | F57: SUSANA RUTH GARCIA MARTINEZ | G57: =nom_interna!C47+nom_interna!I45 -> 12999.9 | H57: MARZO
A58: Sueldos y salarios | B58: LAE | C58: OTROS Facturación / GASTOS | D58: OTROS | F58: SUSANA RUTH GARCIA MARTINEZ | G58: 12999.9 | H58: ABRIL
A59: Sueldos y salarios | B59: LAE | C59: OTROS Facturación / GASTOS | D59: OTROS | F59: DIEGO GUERRA GUTIERREZ | G59: =nom_interna!C8+nom_interna!I8 -> 12999.9 | H59: ENERO
A60: Sueldos y salarios | B60: LAE | C60: OTROS Facturación / GASTOS | D60: OTROS | F60: DIEGO GUERRA GUTIERREZ | G60: 12999.9 | H60: FEBRERO
A61: Sueldos y salarios | B61: LAE | C61: OTROS Facturación / GASTOS | D61: OTROS | F61: DIEGO GUERRA GUTIERREZ | G61: 12999.9 | H61: MARZO
A62: Sueldos y salarios | B62: LAE | C62: OTROS Facturación / GASTOS | D62: OTROS | F62: DIEGO GUERRA GUTIERREZ | G62: 12999.9 | H62: ABRIL
A63: Sueldos y salarios | B63: JOSE CARLOS SAENZ FERNANDEZ | C63: GASTOS DE ADMINISTRACIÓN | D63: COMERCIAL | F63: JOSE CARLOS SAENZ FERNANDEZ | G63: =nom_interna!C11+nom_interna!I11 -> 16219.1 | H63: ENERO
A64: Sueldos y salarios | B64: JOSE CARLOS SAENZ FERNANDEZ | C64: GASTOS DE ADMINISTRACIÓN | D64: COMERCIAL | F64: JOSE CARLOS SAENZ FERNANDEZ | G64: =nom_interna!C26+nom_interna!I27 -> 22000.14 | H64: FEBRERO
A65: Sueldos y salarios | B65: JOSE CARLOS SAENZ FERNANDEZ | C65: GASTOS DE ADMINISTRACIÓN | D65: COMERCIAL | F65: JOSE CARLOS SAENZ FERNANDEZ | G65: =nom_interna!C52+nom_interna!I50 -> 22000.14 | H65: MARZO
A66: Sueldos y salarios | B66: JOSE CARLOS SAENZ FERNANDEZ | C66: GASTOS DE ADMINISTRACIÓN | D66: COMERCIAL | F66: JOSE CARLOS SAENZ FERNANDEZ | G66: =nom_interna!C104+nom_interna!I104 -> 22000.14 | H66: ABRIL
A67: Sueldos y salarios | B67: NADIA YURIT ARAUJO ISLAS | C67: COGS | D67: OPERACIONES | F67: NADIA YURIT ARAUJO ISLAS | G67: =nom_interna!C12+nom_interna!I12 -> 5192.95 | H67: ENERO
A68: Sueldos y salarios | B68: NADIA YURIT ARAUJO ISLAS | C68: COGS | D68: OPERACIONES | F68: NADIA YURIT ARAUJO ISLAS | G68: =nom_interna!C27+nom_interna!I28 -> 12182.49 | H68: FEBRERO
A69: Sueldos y salarios | B69: NADIA YURIT ARAUJO ISLAS | C69: COGS | D69: OPERACIONES | F69: NADIA YURIT ARAUJO ISLAS | G69: =nom_interna!C53+nom_interna!I51 -> 13977.58 | H69: MARZO
A70: Sueldos y salarios | B70: NADIA YURIT ARAUJO ISLAS | C70: COGS | D70: OPERACIONES | F70: NADIA YURIT ARAUJO ISLAS | G70: =nom_interna!C105+nom_interna!I105 -> 13977.58 | H70: ABRIL
A71: Sueldos y salarios | B71: BERRUETA GONZALEZ FRANCISCO JAVIER | C71: GASTOS DE ADMINISTRACIÓN | D71: PENDIENTE | F71: FRANCISCO JAVIER BERRUETA GONZALEZ | G71: 30450 | H71: ENERO
A72: Sueldos y salarios | B72: BERRUETA GONZALEZ FRANCISCO JAVIER | C72: GASTOS DE ADMINISTRACIÓN | D72: PENDIENTE | F72: FRANCISCO JAVIER BERRUETA GONZALEZ | G72: 30450 | H72: MARZO
A73: Sueldos y salarios | B73: BERRUETA GONZALEZ FRANCISCO JAVIER | C73: GASTOS DE ADMINISTRACIÓN | D73: PENDIENTE | F73: FRANCISCO JAVIER BERRUETA GONZALEZ | G73: 30450 | H73: FEBRERO
A74: Sueldos y salarios | B74: BERRUETA GUTIERREZ SOFIA | C74: GASTOS DE ADMINISTRACIÓN | D74: TÉCNICO | F74: SOFIA BERRUETA GUTIERREZ | G74: 23583.237 | H74: MARZO
A75: Sueldos y salarios | B75: BERRUETA GUTIERREZ SOFIA | C75: GASTOS DE ADMINISTRACIÓN | D75: TÉCNICO | F75: SOFIA BERRUETA GUTIERREZ | G75: 13045.633 | H75: FEBRERO
A76: Sueldos y salarios | B76: BERRUETA GUTIERREZ SOFIA | C76: GASTOS DE ADMINISTRACIÓN | D76: TÉCNICO | F76: SOFIA BERRUETA GUTIERREZ | G76: 13291.944 | H76: ENERO
A77: Sueldos y salarios | B77: BOCANEGRA MARTINEZ ELEAZAR | C77: COGS | D77: TÉCNICO | F77: ELEAZAR BOCANEGRA MARTINEZ | G77: 16300.949 | H77: FEBRERO
A78: Sueldos y salarios | B78: BOCANEGRA MARTINEZ ELEAZAR | C78: COGS | D78: TÉCNICO | F78: ELEAZAR BOCANEGRA MARTINEZ | G78: 16669.546 | H78: ENERO
A79: Sueldos y salarios | B79: BOCANEGRA MARTINEZ ELEAZAR | C79: COGS | D79: TÉCNICO | F79: ELEAZAR BOCANEGRA MARTINEZ | G79: 16518.123 | H79: MARZO
A80: Sueldos y salarios | B80: BRAVO ZAPIAIN NATALIA | C80: GASTOS DE ADMINISTRACIÓN | D80: COMERCIAL | F80: NATALIA BRAVO ZAPIAIN | G80: 18843.097 | H80: FEBRERO
A81: Sueldos y salarios | B81: BRAVO ZAPIAIN NATALIA | C81: GASTOS DE ADMINISTRACIÓN | D81: COMERCIAL | F81: NATALIA BRAVO ZAPIAIN | G81: 15931.394 | H81: ENERO
A82: Sueldos y salarios | B82: BRAVO ZAPIAIN NATALIA | C82: GASTOS DE ADMINISTRACIÓN | D82: COMERCIAL | F82: NATALIA BRAVO ZAPIAIN | G82: 19074.755 | H82: MARZO
... A85: Sueldos y salarios | B85: CABRERA TERAN ARTURO | C85: GASTOS DE ADMINISTRACIÓN | D85: BRAND BUILDING | F85: ARTURO CABRERA TERAN | G85: 14418.283 | H85: MARZO
A86: Sueldos y salarios | B86: CAMACHO MONCADA MARIA JOSE | C86: COGS | D86: OPERACIONES | E86: OCCIDENTE | F86: MARIA JOSE CAMACHO MONCADA | G86: 15633.097 | H86: FEBRERO
A87: Sueldos y salarios | B87: CAMACHO MONCADA MARIA JOSE | C87: COGS | D87: OPERACIONES | E87: OCCIDENTE | F87: MARIA JOSE CAMACHO MONCADA | G87: 3181.7528 | H87: ENERO
A88: Sueldos y salarios | B88: CAMACHO MONCADA MARIA JOSE | C88: COGS | D88: OPERACIONES | E88: OCCIDENTE | F88: MARIA JOSE CAMACHO MONCADA | G88: 15924.755 | H88: MARZO
A89: Sueldos y salarios | B89: CAMACHO NUÑO IVAN ANGEL | C89: COGS | D89: OPERACIONES | E89: OCCIDENTE | F89: IVAN ANGEL CAMACHO NUÑO | G89: 17051.678 | H89: ENERO
A90: Sueldos y salarios | B90: CAMACHO NUÑO IVAN ANGEL | C90: COGS | D90: OPERACIONES | E90: OCCIDENTE | F90: IVAN ANGEL CAMACHO NUÑO | G90: 8493.071 | H90: FEBRERO
A91: Sueldos y salarios | B91: CATARINO TENORIO GRISELDA | C91: COGS | D91: OPERACIONES | E91: PEPSICO OCC | F91: GRISELDA CATARINO TENORIO | G91: 14652.097 | H91: FEBRERO
A92: Sueldos y salarios | B92: CATARINO TENORIO GRISELDA | C92: COGS | D92: OPERACIONES | E92: PEPSICO OCC | F92: GRISELDA CATARINO TENORIO | G92: 13969.394 | H92: ENERO
A93: Sueldos y salarios | B93: CATARINO TENORIO GRISELDA | C93: COGS | D93: OPERACIONES | E93: PEPSICO OCC | F93: GRISELDA CATARINO TENORIO | G93: 15924.755 | H93: MARZO
A94: Sueldos y salarios | B94: CERVANTES AGUILAR JENNIFER MICHELLE | C94: OTROS Facturación / GASTOS | D94: TÉCNICO | F94: JENNIFER MICHELLE CERVANTES AGUILAR | G94: 17571.832 | H94: MARZO
A95: Sueldos y salarios | B95: CERVANTES AGUILAR JENNIFER MICHELLE | C95: OTROS Facturación / GASTOS | D95: TÉCNICO | F95: JENNIFER MICHELLE CERVANTES AGUILAR | G95: 17355.964 | H95: FEBRERO
A96: Sueldos y salarios | B96: CERVANTES AGUILAR JENNIFER MICHELLE | C96: OTROS Facturación / GASTOS | D96: TÉCNICO | F96: JENNIFER MICHELLE CERVANTES AGUILAR | G96: 17763.365 | H96: ENERO
A97: Sueldos y salarios | B97: CORNEJO JIMENEZ MARLEN | C97: COGS | D97: OPERACIONES | E97: PEPSICO NAC. | F97: MARLEN CORNEJO JIMENEZ | G97: 26433.846 | H97: MARZO
A98: Sueldos y salarios | B98: CORNEJO JIMENEZ MARLEN | C98: COGS | D98: OPERACIONES | E98: PEPSICO NAC. | F98: MARLEN CORNEJO JIMENEZ | G98: 18888.877 | H98: FEBRERO
A99: Sueldos y salarios | B99: CORNEJO JIMENEZ MARLEN | C99: COGS | D99: OPERACIONES | E99: PEPSICO NAC. | F99: MARLEN CORNEJO JIMENEZ | G99: 20299.695 | H99: ENERO
A100: Sueldos y salarios | B100: CRISOSTOMO ARENAS MARIA DE LOURDES | C100: COGS | D100: OPERACIONES | F100: MARIA DE LOURDES CRISOSTOMO ARENAS | G100: 16929.069 | H100: MARZO
A101: Sueldos y salarios | B101: CRISOSTOMO ARENAS MARIA DE LOURDES | C101: COGS | D101: OPERACIONES | F101: MARIA DE LOURDES CRISOSTOMO ARENAS | G101: 4494.6253 | H101: FEBRERO
A102: Sueldos y salarios | B102: CRUZ GARCIA KELLY | C102: GASTOS DE ADMINISTRACIÓN | D102: RH | F102: KELLY CRUZ GARCIA | G102: 19146.252 | H102: MARZO
...
